Workbook

Sheet README
A1: Travel Itineraries — Relational Workbook
A3: How the sheets connect (same structure as the database tables)
A4: Itineraries (1 row per itinerary) PRIMARY KEY: itinerary_id
A5: Themes (1 row per itinerary) itinerary_id → Itineraries
A6: Days (1 row per day) itinerary_id → Itineraries, key = itinerary_id + day_number
A7: Locations (1 row per unique place) PRIMARY KEY: location_id
A8: Day_Locations (stops of each day, ordered) itinerary_id + day_number → Days, location_id → Locations
A9: Tags (1 row per unique tag) PRIMARY KEY: tag_id, category = occasion / travel_style / culture / season / trip_type
A10: Itinerary_Tags (which tags an itinerary has) itinerary_id → Itineraries, tag_id → Tags
A12: Colour legend
A13: Dark blue header = data you type / paste.
A14: Grey-blue header + shaded cells = formulas (auto-calculated; do not overwrite).
... A41: Frontend filter controls and runtime filtering are implemented in the Next.js source code, not in this workbook. Verify the frontend Direction filter separately.

Sheet Filter_Options
A1: category_no | B1: category_name | C1: option_no | D1: option_label | E1: rule_type | F1: rule_text | G1: min | H1: max | I1: tag_id_1 | J1: tag_id_2 | K1: tag_id_3 | L1: option_code | M1: itineraries_matching | N1: tags_used (auto)
A2: 1 | B2: Direction | C2: 1 | D2: North | E2: direction | F2: north | L2: =A2&"."&C2 | M2: =SUM(INDEX(Filter_Matrix!$C$2:$AL$100,0,ROW()-1)) | N2: =IF(I2="","",IFERROR(INDEX(Tags!$C:$C,MATCH(I2,Tags!$A:$A,0)),"?")&IF(J2="","",", "&IFERROR(INDEX(Tags!$C:$C,MATCH(J2,Tags!$A:$A,0)),"?"))&IF(K2="","",", "&IFERROR(INDEX(Tags!$C:$C,MATCH(K2,Tags!$A:$A,0)),"?")))
A3: 1 | B3: Direction | C3: 2 | D3: South | E3: direction | F3: south | L3: =A3&"."&C3 | M3: =SUM(INDEX(Filter_Matrix!$C$2:$AL$100,0,ROW()-1)) | N3: =IF(I3="","",IFERROR(INDEX(Tags!$C:$C,MATCH(I3,Tags!$A:$A,0)),"?")&IF(J3="","",", "&IFERROR(INDEX(Tags!$C:$C,MATCH(J3,Tags!$A:$A,0)),"?"))&IF(K3="","",", "&IFERROR(INDEX(Tags!$C:$C,MATCH(K3,Tags!$A:$A,0)),"?")))
A4: 1 | B4: Direction | C4: 3 | D4: East | E4: direction | F4: east | L4: =A4&"."&C4 | M4: =SUM(INDEX(Filter_Matrix!$C$2:$AL$100,0,ROW()-1)) | N4: =IF(I4="","",IFERROR(INDEX(Tags!$C:$C,MATCH(I4,Tags!$A:$A,0)),"?")&IF(J4="","",", "&IFERROR(INDEX(Tags!$C:$C,MATCH(J4,Tags!$A:$A,0)),"?"))&IF(K4="","",", "&IFERROR(INDEX(Tags!$C:$C,MATCH(K4,Tags!$A:$A,0)),"?")))
A5: 1 | B5: Direction | C5: 4 | D5: West | E5: direction | F5: west | L5: =A5&"."&C5 | M5: =SUM(INDEX(Filter_Matrix!$C$2:$AL$100,0,ROW()-1)) | N5: =IF(I5="","",IFERROR(INDEX(Tags!$C:$C,MATCH(I5,Tags!$A:$A,0)),"?")&IF(J5="","",", "&IFERROR(INDEX(Tags!$C:$C,MATCH(J5,Tags!$A:$A,0)),"?"))&IF(K5="","",", "&IFERROR(INDEX(Tags!$C:$C,MATCH(K5,Tags!$A:$A,0)),"?")))
A6: 1 | B6: Direction | C6: 5 | D6: Northeast | E6: direction | F6: northeast | L6: =A6&"."&C6 | M6: =SUM(INDEX(Filter_Matrix!$C$2:$AL$100,0,ROW()-1)) | N6: =IF(I6="","",IFERROR(INDEX(Tags!$C:$C,MATCH(I6,Tags!$A:$A,0)),"?")&IF(J6="","",", "&IFERROR(INDEX(Tags!$C:$C,MATCH(J6,Tags!$A:$A,0)),"?"))&IF(K6="","",", "&IFERROR(INDEX(Tags!$C:$C,MATCH(K6,Tags!$A:$A,0)),"?")))
A7: 1 | B7: Direction | C7: 6 | D7: Central | E7: direction | F7: central | L7: =A7&"."&C7 | M7: =SUM(INDEX(Filter_Matrix!$C$2:$AL$100,0,ROW()-1)) | N7: =IF(I7="","",IFERROR(INDEX(Tags!$C:$C,MATCH(I7,Tags!$A:$A,0)),"?")&IF(J7="","",", "&IFERROR(INDEX(Tags!$C:$C,MATCH(J7,Tags!$A:$A,0)),"?"))&IF(K7="","",", "&IFERROR(INDEX(Tags!$C:$C,MATCH(K7,Tags!$A:$A,0)),"?")))
A8: 2 | B8: Budget (INR) | C8: 1 | D8: Under 5,000 | E8: range_overlap | G8: 0 | H8: 4999 | L8: =A8&"."&C8 | M8: =SUM(INDEX(Filter_Matrix!$C$2:$AL$100,0,ROW()-1)) | N8: =IF(I8="","",IFERROR(INDEX(Tags!$C:$C,MATCH(I8,Tags!$A:$A,0)),"?")&IF(J8="","",", "&IFERROR(INDEX(Tags!$C:$C,MATCH(J8,Tags!$A:$A,0)),"?"))&IF(K8="","",", "&IFERROR(INDEX(Tags!$C:$C,MATCH(K8,Tags!$A:$A,0)),"?")))
A9: 2 | B9: Budget (INR) | C9: 2 | D9: 5,000 – 7,999 | E9: range_overlap | G9: 5000 | H9: 7999 | L9: =A9&"."&C9 | M9: =SUM(INDEX(Filter_Matrix!$C$2:$AL$100,0,ROW()-1)) | N9: =IF(I9="","",IFERROR(INDEX(Tags!$C:$C,MATCH(I9,Tags!$A:$A,0)),"?")&IF(J9="","",", "&IFERROR(INDEX(Tags!$C:$C,MATCH(J9,Tags!$A:$A,0)),"?"))&IF(K9="","",", "&IFERROR(INDEX(Tags!$C:$C,MATCH(K9,Tags!$A:$A,0)),"?")))
A10: 2 | B10: Budget (INR) | C10: 3 | D10: 8,000 – 11,999 | E10: range_overlap | G10: 8000 | H10: 11999 | L10: =A10&"."&C10 | M10: =SUM(INDEX(Filter_Matrix!$C$2:$AL$100,0,ROW()-1)) | N10: =IF(I10="","",IFERROR(INDEX(Tags!$C:$C,MATCH(I10,Tags!$A:$A,0)),"?")&IF(J10="","",", "&IFERROR(INDEX(Tags!$C:$C,MATCH(J10,Tags!$A:$A,0)),"?"))&IF(K10="","",", "&IFERROR(INDEX(Tags!$C:$C,MATCH(K10,Tags!$A:$A,0)),"?")))
A11: 2 | B11: Budget (INR) | C11: 4 | D11: 12,000 – 17,999 | E11: range_overlap | G11: 12000 | H11: 17999 | L11: =A11&"."&C11 | M11: =SUM(INDEX(Filter_Matrix!$C$2:$AL$100,0,ROW()-1)) | N11: =IF(I11="","",IFERROR(INDEX(Tags!$C:$C,MATCH(I11,Tags!$A:$A,0)),"?")&IF(J11="","",", "&IFERROR(INDEX(Tags!$C:$C,MATCH(J11,Tags!$A:$A,0)),"?"))&IF(K11="","",", "&IFERROR(INDEX(Tags!$C:$C,MATCH(K11,Tags!$A:$A,0)),"?")))
A12: 2 | B12: Budget (INR) | C12: 5 | D12: 18,000 – 24,999 | E12: range_overlap | G12: 18000 | H12: 24999 | L12: =A12&"."&C12 | M12: =SUM(INDEX(Filter_Matrix!$C$2:$AL$100,0,ROW()-1)) | N12: =IF(I12="","",IFERROR(INDEX(Tags!$C:$C,MATCH(I12,Tags!$A:$A,0)),"?")&IF(J12="","",", "&IFERROR(INDEX(Tags!$C:$C,MATCH(J12,Tags!$A:$A,0)),"?"))&IF(K12="","",", "&IFERROR(INDEX(Tags!$C:$C,MATCH(K12,Tags!$A:$A,0)),"?")))
A13: 2 | B13: Budget (INR) | C13: 6 | D13: 25,000 and above | E13: range_overlap | G13: 25000 | H13: 999999 | L13: =A13&"."&C13 | M13: =SUM(INDEX(Filter_Matrix!$C$2:$AL$100,0,ROW()-1)) | N13: =IF(I13="","",IFERROR(INDEX(Tags!$C:$C,MATCH(I13,Tags!$A:$A,0)),"?")&IF(J13="","",", "&IFERROR(INDEX(Tags!$C:$C,MATCH(J13,Tags!$A:$A,0)),"?"))&IF(K13="","",", "&IFERROR(INDEX(Tags!$C:$C,MATCH(K13,Tags!$A:$A,0)),"?")))
A14: 3 | B14: Available Time (days) | C14: 1 | D14: 1–2 days | E14: range_in | G14: 1 | H14: 2 | L14: =A14&"."&C14 | M14: =SUM(INDEX(Filter_Matrix!$C$2:$AL$100,0,ROW()-1)) | N14: =IF(I14="","",IFERROR(INDEX(Tags!$C:$C,MATCH(I14,Tags!$A:$A,0)),"?")&IF(J14="","",", "&IFERROR(INDEX(Tags!$C:$C,MATCH(J14,Tags!$A:$A,0)),"?"))&IF(K14="","",", "&IFERROR(INDEX(Tags!$C:$C,MATCH(K14,Tags!$A:$A,0)),"?")))
A15: 3 | B15: Available Time (days) | C15: 2 | D15: 3 days | E15: range_in | G15: 3 | H15: 3 | L15: =A15&"."&C15 | M15: =SUM(INDEX(Filter_Matrix!$C$2:$AL$100,0,ROW()-1)) | N15: =IF(I15="","",IFERROR(INDEX(Tags!$C:$C,MATCH(I15,Tags!$A:$A,0)),"?")&IF(J15="","",", "&IFERROR(INDEX(Tags!$C:$C,MATCH(J15,Tags!$A:$A,0)),"?"))&IF(K15="","",", "&IFERROR(INDEX(Tags!$C:$C,MATCH(K15,Tags!$A:$A,0)),"?")))
A16: 3 | B16: Available Time (days) | C16: 3 | D16: 4 days | E16: range_in | G16: 4 | H16: 4 | L16: =A16&"."&C16 | M16: =SUM(INDEX(Filter_Matrix!$C$2:$AL$100,0,ROW()-1)) | N16: =IF(I16="","",IFERROR(INDEX(Tags!$C:$C,MATCH(I16,Tags!$A:$A,0)),"?")&IF(J16="","",", "&IFERROR(INDEX(Tags!$C:$C,MATCH(J16,Tags!$A:$A,0)),"?"))&IF(K16="","",", "&IFERROR(INDEX(Tags!$C:$C,MATCH(K16,Tags!$A:$A,0)),"?")))
A17: 3 | B17: Available Time (days) | C17: 4 | D17: 5 days | E17: range_in | G17: 5 | H17: 5 | L17: =A17&"."&C17 | M17: =SUM(INDEX(Filter_Matrix!$C$2:$AL$100,0,ROW()-1)) | N17: =IF(I17="","",IFERROR(INDEX(Tags!$C:$C,MATCH(I17,Tags!$A:$A,0)),"?")&IF(J17="","",", "&IFERROR(INDEX(Tags!$C:$C,MATCH(J17,Tags!$A:$A,0)),"?"))&IF(K17="","",", "&IFERROR(INDEX(Tags!$C:$C,MATCH(K17,Tags!$A:$A,0)),"?")))
A18: 3 | B18: Available Time (days) | C18: 5 | D18: 6–7 days | E18: range_in | G18: 6 | H18: 7 | L18: =A18&"."&C18 | M18: =SUM(INDEX(Filter_Matrix!$C$2:$AL$100,0,ROW()-1)) | N18: =IF(I18="","",IFERROR(INDEX(Tags!$C:$C,MATCH(I18,Tags!$A:$A,0)),"?")&IF(J18="","",", "&IFERROR(INDEX(Tags!$C:$C,MATCH(J18,Tags!$A:$A,0)),"?"))&IF(K18="","",", "&IFERROR(INDEX(Tags!$C:$C,MATCH(K18,Tags!$A:$A,0)),"?")))
A19: 3 | B19: Available Time (days) | C19: 6 | D19: 8+ days | E19: range_in | G19: 8 | H19: 99 | L19: =A19&"."&C19 | M19: =SUM(INDEX(Filter_Matrix!$C$2:$AL$100,0,ROW()-1)) | N19: =IF(I19="","",IFERROR(INDEX(Tags!$C:$C,MATCH(I19,Tags!$A:$A,0)),"?")&IF(J19="","",", "&IFERROR(INDEX(Tags!$C:$C,MATCH(J19,Tags!$A:$A,0)),"?"))&IF(K19="","",", "&IFERROR(INDEX(Tags!$C:$C,MATCH(K19,Tags!$A:$A,0)),"?")))
A20: 4 | B20: Occasion | C20: 1 | D20: Weekend | E20: tag | I20: 15 | L20: =A20&"."&C20 | M20: =SUM(INDEX(Filter_Matrix!$C$2:$AL$100,0,ROW()-1)) | N20: =IF(I20="","",IFERROR(INDEX(Tags!$C:$C,MATCH(I20,Tags!$A:$A,0)),"?")&IF(J20="","",", "&IFERROR(INDEX(Tags!$C:$C,MATCH(J20,Tags!$A:$A,0)),"?"))&IF(K20="","",", "&IFERROR(INDEX(Tags!$C:$C,MATCH(K20,Tags!$A:$A,0)),"?")))
A21: 4 | B21: Occasion | C21: 2 | D21: Long weekend | E21: tag | I21: 1 | L21: =A21&"."&C21 | M21: =SUM(INDEX(Filter_Matrix!$C$2:$AL$100,0,ROW()-1)) | N21: =IF(I21="","",IFERROR(INDEX(Tags!$C:$C,MATCH(I21,Tags!$A:$A,0)),"?")&IF(J21="","",", "&IFERROR(INDEX(Tags!$C:$C,MATCH(J21,Tags!$A:$A,0)),"?"))&IF(K21="","",", "&IFERROR(INDEX(Tags!$C:$C,MATCH(K21,Tags!$A:$A,0)),"?")))
A22: 4 | B22: Occasion | C22: 3 | D22: Spontaneous | E22: tag | I22: 18 | L22: =A22&"."&C22 | M22: =SUM(INDEX(Filter_Matrix!$C$2:$AL$100,0,ROW()-1)) | N22: =IF(I22="","",IFERROR(INDEX(Tags!$C:$C,MATCH(I22,Tags!$A:$A,0)),"?")&IF(J22="","",", "&IFERROR(INDEX(Tags!$C:$C,MATCH(J22,Tags!$A:$A,0)),"?"))&IF(K22="","",", "&IFERROR(INDEX(Tags!$C:$C,MATCH(K22,Tags!$A:$A,0)),"?")))
A23: 4 | B23: Occasion | C23: 4 | D23: Festive | E23: tag | I23: 58 | J23: 48 | L23: =A23&"."&C23 | M23: =SUM(INDEX(Filter_Matrix!$C$2:$AL$100,0,ROW()-1)) | N23: =IF(I23="","",IFERROR(INDEX(Tags!$C:$C,MATCH(I23,Tags!$A:$A,0)),"?")&IF(J23="","",", "&IFERROR(INDEX(Tags!$C:$C,MATCH(J23,Tags!$A:$A,0)),"?"))&IF(K23="","",", "&IFERROR(INDEX(Tags!$C:$C,MATCH(K23,Tags!$A:$A,0)),"?")))
A24: 4 | B24: Occasion | C24: 5 | D24: Solo | E24: tag | I24: 32 | L24: =A24&"."&C24 | M24: =SUM(INDEX(Filter_Matrix!$C$2:$AL$100,0,ROW()-1)) | N24: =IF(I24="","",IFERROR(INDEX(Tags!$C:$C,MATCH(I24,Tags!$A:$A,0)),"?")&IF(J24="","",", "&IFERROR(INDEX(Tags!$C:$C,MATCH(J24,Tags!$A:$A,0)),"?"))&IF(K24="","",", "&IFERROR(INDEX(Tags!$C:$C,MATCH(K24,Tags!$A:$A,0)),"?")))
A25: 4 | B25: Occasion | C25: 6 | D25: Friends, couple & family | E25: tag | I25: 33 | J25: 34 | K25: 35 | L25: =A25&"."&C25 | M25: =SUM(INDEX(Filter_Matrix!$C$2:$AL$100,0,ROW()-1)) | N25: =IF(I25="","",IFERROR(INDEX(Tags!$C:$C,MATCH(I25,Tags!$A:$A,0)),"?")&IF(J25="","",", "&IFERROR(INDEX(Tags!$C:$C,MATCH(J25,Tags!$A:$A,0)),"?"))&IF(K25="","",", "&IFERROR(INDEX(Tags!$C:$C,MATCH(K25,Tags!$A:$A,0)),"?")))
A26: 5 | B26: Culture | C26: 1 | D26: Heritage | E26: tag | I26: 6 | L26: =A26&"."&C26 | M26: =SUM(INDEX(Filter_Matrix!$C$2:$AL$100,0,ROW()-1)) | N26: =IF(I26="","",IFERROR(INDEX(Tags!$C:$C,MATCH(I26,Tags!$A:$A,0)),"?")&IF(J26="","",", "&IFERROR(INDEX(Tags!$C:$C,MATCH(J26,Tags!$A:$A,0)),"?"))&IF(K26="","",", "&IFERROR(INDEX(Tags!$C:$C,MATCH(K26,Tags!$A:$A,0)),"?")))
A27: 5 | B27: Culture | C27: 2 | D27: Local food | E27: tag | I27: 7 | L27: =A27&"."&C27 | M27: =SUM(INDEX(Filter_Matrix!$C$2:$AL$100,0,ROW()-1)) | N27: =IF(I27="","",IFERROR(INDEX(Tags!$C:$C,MATCH(I27,Tags!$A:$A,0)),"?")&IF(J27="","",", "&IFERROR(INDEX(Tags!$C:$C,MATCH(J27,Tags!$A:$A,0)),"?"))&IF(K27="","",", "&IFERROR(INDEX(Tags!$C:$C,MATCH(K27,Tags!$A:$A,0)),"?")))
A28: 5 | B28: Culture | C28: 3 | D28: Folk art & crafts | E28: tag | I28: 8 | J28: 9 | L28: =A28&"."&C28 | M28: =SUM(INDEX(Filter_Matrix!$C$2:$AL$100,0,ROW()-1)) | N28: =IF(I28="","",IFERROR(INDEX(Tags!$C:$C,MATCH(I28,Tags!$A:$A,0)),"?")&IF(J28="","",", "&IFERROR(INDEX(Tags!$C:$C,MATCH(J28,Tags!$A:$A,0)),"?"))&IF(K28="","",", "&IFERROR(INDEX(Tags!$C:$C,MATCH(K28,Tags!$A:$A,0)),"?")))
A29: 5 | B29: Culture | C29: 4 | D29: Villages | E29: tag | I29: 21 | L29: =A29&"."&C29 | M29: =SUM(INDEX(Filter_Matrix!$C$2:$AL$100,0,ROW()-1)) | N29: =IF(I29="","",IFERROR(INDEX(Tags!$C:$C,MATCH(I29,Tags!$A:$A,0)),"?")&IF(J29="","",", "&IFERROR(INDEX(Tags!$C:$C,MATCH(J29,Tags!$A:$A,0)),"?"))&IF(K29="","",", "&IFERROR(INDEX(Tags!$C:$C,MATCH(K29,Tags!$A:$A,0)),"?")))
A30: 5 | B30: Culture | C30: 5 | D30: Festivals | E30: tag | I30: 41 | J30: 49 | L30: =A30&"."&C30 | M30: =SUM(INDEX(Filter_Matrix!$C$2:$AL$100,0,ROW()-1)) | N30: =IF(I30="","",IFERROR(INDEX(Tags!$C:$C,MATCH(I30,Tags!$A:$A,0)),"?")&IF(J30="","",", "&IFERROR(INDEX(Tags!$C:$C,MATCH(J30,Tags!$A:$A,0)),"?"))&IF(K30="","",", "&IFERROR(INDEX(Tags!$C:$C,MATCH(K30,Tags!$A:$A,0)),"?")))
A31: 5 | B31: Culture | C31: 6 | D31: Local culture | E31: tag | I31: 50 | L31: =A31&"."&C31 | M31: =SUM(INDEX(Filter_Matrix!$C$2:$AL$100,0,ROW()-1)) | N31: =IF(I31="","",IFERROR(INDEX(Tags!$C:$C,MATCH(I31,Tags!$A:$A,0)),"?")&IF(J31="","",", "&IFERROR(INDEX(Tags!$C:$C,MATCH(J31,Tags!$A:$A,0)),"?"))&IF(K31="","",", "&IFERROR(INDEX(Tags!$C:$C,MATCH(K31,Tags!$A:$A,0)),"?")))
A32: 6 | B32: Weather & Season | C32: 1 | D32: Winter | E32: tag | I32: 10 | L32: =A32&"."&C32 | M32: =SUM(INDEX(Filter_Matrix!$C$2:$AL$100,0,ROW()-1)) | N32: =IF(I32="","",IFERROR(INDEX(Tags!$C:$C,MATCH(I32,Tags!$A:$A,0)),"?")&IF(J32="","",", "&IFERROR(INDEX(Tags!$C:$C,MATCH(J32,Tags!$A:$A,0)),"?"))&IF(K32="","",", "&IFERROR(INDEX(Tags!$C:$C,MATCH(K32,Tags!$A:$A,0)),"?")))
A33: 6 | B33: Weather & Season | C33: 2 | D33: Summer | E33: tag | I33: 27 | L33: =A33&"."&C33 | M33: =SUM(INDEX(Filter_Matrix!$C$2:$AL$100,0,ROW()-1)) | N33: =IF(I33="","",IFERROR(INDEX(Tags!$C:$C,MATCH(I33,Tags!$A:$A,0)),"?")&IF(J33="","",", "&IFERROR(INDEX(Tags!$C:$C,MATCH(J33,Tags!$A:$A,0)),"?"))&IF(K33="","",", "&IFERROR(INDEX(Tags!$C:$C,MATCH(K33,Tags!$A:$A,0)),"?")))
A34: 6 | B34: Weather & Season | C34: 3 | D34: Monsoon & waterfalls | E34: tag | I34: 29 | J34: 36 | L34: =A34&"."&C34 | M34: =SUM(INDEX(Filter_Matrix!$C$2:$AL$100,0,ROW()-1)) | N34: =IF(I34="","",IFERROR(INDEX(Tags!$C:$C,MATCH(I34,Tags!$A:$A,0)),"?")&IF(J34="","",", "&IFERROR(INDEX(Tags!$C:$C,MATCH(J34,Tags!$A:$A,0)),"?"))&IF(K34="","",", "&IFERROR(INDEX(Tags!$C:$C,MATCH(K34,Tags!$A:$A,0)),"?")))
A35: 6 | B35: Weather & Season | C35: 4 | D35: Autumn | E35: tag | I35: 22 | L35: =A35&"."&C35 | M35: =SUM(INDEX(Filter_Matrix!$C$2:$AL$100,0,ROW()-1)) | N35: =IF(I35="","",IFERROR(INDEX(Tags!$C:$C,MATCH(I35,Tags!$A:$A,0)),"?")&IF(J35="","",", "&IFERROR(INDEX(Tags!$C:$C,MATCH(J35,Tags!$A:$A,0)),"?"))&IF(K35="","",", "&IFERROR(INDEX(Tags!$C:$C,MATCH(K35,Tags!$A:$A,0)),"?")))
A36: 6 | B36: Weather & Season | C36: 5 | D36: Spring | E36: tag | I36: 57 | L36: =A36&"."&C36 | M36: =SUM(INDEX(Filter_Matrix!$C$2:$AL$100,0,ROW()-1)) | N36: =IF(I36="","",IFERROR(INDEX(Tags!$C:$C,MATCH(I36,Tags!$A:$A,0)),"?")&IF(J36="","",", "&IFERROR(INDEX(Tags!$C:$C,MATCH(J36,Tags!$A:$A,0)),"?"))&IF(K36="","",", "&IFERROR(INDEX(Tags!$C:$C,MATCH(K36,Tags!$A:$A,0)),"?")))
A37: 6 | B37: Weather & Season | C37: 6 | D37: Pleasant | E37: tag | I37: 11 | L37: =A37&"."&C37 | M37: =SUM(INDEX(Filter_Matrix!$C$2:$AL$100,0,ROW()-1)) | N37: =IF(I37="","",IFERROR(INDEX(Tags!$C:$C,MATCH(I37,Tags!$A:$A,0)),"?")&IF(J37="","",", "&IFERROR(INDEX(Tags!$C:$C,MATCH(J37,Tags!$A:$A,0)),"?"))&IF(K37="","",", "&IFERROR(INDEX(Tags!$C:$C,MATCH(K37,Tags!$A:$A,0)),"?")))

Sheet Filter_Matrix
A1: itinerary_id | B1: title | C1: =Filter_Options!$L$2 | D1: =Filter_Options!$L$3 | E1: =Filter_Options!$L$4 | F1: =Filter_Options!$L$5 | G1: =Filter_Options!$L$6 | H1: =Filter_Options!$L$7 | I1: =Filter_Options!$L$8 | J1: =Filter_Options!$L$9 | K1: =Filter_Options!$L$10 | L1: =Filter_Options!$L$11 | M1: =Filter_Options!$L$12 | N1: =Filter_Options!$L$13 | O1: =Filter_Options!$L$14 | P1: =Filter_Options!$L$15 | Q1: =Filter_Options!$L$16 | R1: =Filter_Options!$L$17 | S1: =Filter_Options!$L$18 | T1: =Filter_Options!$L$19 | U1: =Filter_Options!$L$20 | V1: =Filter_Options!$L$21 | W1: =Filter_Options!$L$22 | X1: =Filter_Options!$L$23 | Y1: =Filter_Options!$L$24 | Z1: =Filter_Options!$L$25 | AA1: =Filter_Options!$L$26 | AB1: =Filter_Options!$L$27 | AC1: =Filter_Options!$L$28 | AD1: =Filter_Options!$L$29 | AE1: =Filter_Options!$L$30 | AF1: =Filter_Options!$L$31 | AG1: =Filter_Options!$L$32 | AH1: =Filter_Options!$L$33 | AI1: =Filter_Options!$L$34 | AJ1: =Filter_Options!$L$35 | AK1: =Filter_Options!$L$36 | AL1: =Filter_Options!$L$37
A2: =IF(Itineraries!A2="","",Itineraries!A2) | B2: =IF(Itineraries!A2="","",Itineraries!C2) | C2: =IF($A2="","",--(Itineraries!$J2=Filter_Options!$F$2)) | D2: =IF($A2="","",--(Itineraries!$J2=Filter_Options!$F$3)) | E2: =IF($A2="","",--(Itineraries!$J2=Filter_Options!$F$4)) | F2: =IF($A2="","",--(Itineraries!$J2=Filter_Options!$F$5)) | G2: =IF($A2="","",--(Itineraries!$J2=Filter_Options!$F$6)) | H2: =IF($A2="","",--(Itineraries!$J2=Filter_Options!$F$7)) | I2: =IF($A2="","",--AND(Itineraries!$K2<=Filter_Options!$H$8,Itineraries!$L2>=Filter_Options!$G$8)) | J2: =IF($A2="","",--AND(Itineraries!$K2<=Filter_Options!$H$9,Itineraries!$L2>=Filter_Options!$G$9)) | K2: =IF($A2="","",--AND(Itineraries!$K2<=Filter_Options!$H$10,Itineraries!$L2>=Filter_Options!$G$10)) | L2: =IF($A2="","",--AND(Itineraries!$K2<=Filter_Options!$H$11,Itineraries!$L2>=Filter_Options!$G$11)) | M2: =IF($A2="","",--AND(Itineraries!$K2<=Filter_Options!$H$12,Itineraries!$L2>=Filter_Options!$G$12)) | N2: =IF($A2="","",--AND(Itineraries!$K2<=Filter_Options!$H$13,Itineraries!$L2>=Filter_Options!$G$13)) | O2: =IF($A2="","",--AND(Itineraries!$E2>=Filter_Options!$G$14,Itineraries!$E2<=Filter_Options!$H$14)) | P2: =IF($A2="","",--AND(Itineraries!$E2>=Filter_Options!$G$15,Itineraries!$E2<=Filter_Options!$H$15)) | Q2: =IF($A2="","",--AND(Itineraries!$E2>=Filter_Options!$G$16,Itineraries!$E2<=Filter_Options!$H$16)) | R2: =IF($A2="","",--AND(Itineraries!$E2>=Filter_Options!$G$17,Itineraries!$E2<=Filter_Options!$H$17)) | S2: =IF($A2="","",--AND(Itineraries!$E2>=Filter_Options!$G$18,Itineraries!$E2<=Filter_Options!$H$18)) | T2: =IF($A2="","",--AND(Itineraries!$E2>=Filter_Options!$G$19,Itineraries!$E2<=Filter_Options!$H$19)) | U2: =IF($A2="","",--((IF(Filter_Options!$I$20="",0,COUNTIFS(Itinerary_Tags!$A:$A,$A2,Itinerary_Tags!$B:$B,Filter_Options!$I$20))+IF(Filter_Options!$J$20="",0,COUNTIFS(Itinerary_Tags!$A:$A,$A2,Itinerary_Tags!$B:$B,Filter_Options!$J$20))+IF(Filter_Options!$K$20="",0,COUNTIFS(Itinerary_Tags!$A:$A,$A2,Itinerary_Tags!$B:$B,Filter_Options!$K$20)))>0)) | V2: =IF($A2="","",--((IF(Filter_Options!$I$21="",0,COUNTIFS(Itinerary_Tags!$A:$A,$A2,Itinerary_Tags!$B:$B,Filter_Options!$I$21))+IF(Filter_Options!$J$21="",0,COUNTIFS(Itinerary_Tags!$A:$A,$A2,Itinerary_Tags!$B:$B,Filter_Options!$J$21))+IF(Filter_Options!$K$21="",0,COUNTIFS(Itinerary_Tags!$A:$A,$A2,Itinerary_Tags!$B:$B,Filter_Options!$K$21)))>0)) | W2: =IF($A2="","",--((IF(Filter_Options!$I$22="",0,COUNTIFS(Itinerary_Tags!$A:$A,$A2,Itinerary_Tags!$B:$B,Filter_Options!$I$22))+IF(Filter_Options!$J$22="",0,COUNTIFS(Itinerary_Tags!$A:$A,$A2,Itinerary_Tags!$B:$B,Filter_Options!$J$22))+IF(Filter_Options!$K$22="",0,COUNTIFS(Itinerary_Tags!$A:$A,$A2,Itinerary_Tags!$B:$B,Filter_Options!$K$22)))>0)) | X2: =IF($A2="","",--((IF(Filter_Options!$I$23="",0,COUNTIFS(Itinerary_Tags!$A:$A,$A2,Itinerary_Tags!$B:$B,Filter_Options!$I$23))+IF(Filter_Options!$J$23="",0,COUNTIFS(Itinerary_Tags!$A:$A,$A2,Itinerary_Tags!$B:$B,Filter_Options!$J$23))+IF(Filter_Options!$K$23="",0,COUNTIFS(Itinerary_Tags!$A:$A,$A2,Itinerary_Tags!$B:$B,Filter_Options!$K$23)))>0)) | Y2: =IF($A2="","",--((IF(Filter_Options!$I$24="",0,COUNTIFS(Itinerary_Tags!$A:$A,$A2,Itinerary_Tags!$B:$B,Filter_Options!$I$24))+IF(Filter_Options!$J$24="",0,COUNTIFS(Itinerary_Tags!$A:$A,$A2,Itinerary_Tags!$B:$B,Filter_Options!$J$24))+IF(Filter_Options!$K$24="",0,COUNTIFS(Itinerary_Tags!$A:$A,$A2,Itinerary_Tags!$B:$B,Filter_Options!$K$24)))>0)) | Z2: =IF($A2="","",--((IF(Filter_Options!$I$25="",0,COUNTIFS(Itinerary_Tags!$A:$A,$A2,Itinerary_Tags!$B:$B,Filter_Options!$I$25))+IF(Filter_Options!$J$25="",0,COUNTIFS(Itinerary_Tags!$A:$A,$A2,Itinerary_Tags!$B:$B,Filter_Options!$J$25))+IF(Filter_Options!$K$25="",0,COUNTIFS(Itinerary_Tags!$A:$A,$A2,Itinerary_Tags!$B:$B,Filter_Options!$K$25)))>0)) | AA2: =IF($A2="","",--((IF(Filter_Options!$I$26="",0,COUNTIFS(Itinerary_Tags!$A:$A,$A2,Itinerary_Tags!$B:$B,Filter_Options!$I$26))+IF(Filter_Options!$J$26="",0,COUNTIFS(Itinerary_Tags!$A:$A,$A2,Itinerary_Tags!$B:$B,Filter_Options!$J$26))+IF(Filter_Options!$K$26="",0,COUNTIFS(Itinerary_Tags!$A:$A,$A2,Itinerary_Tags!$B:$B,Filter_Options!$K$26)))>0)) | AB2: =IF($A2="","",--((IF(Filter_Options!$I$27="",0,COUNTIFS(Itinerary_Tags!$A:$A,$A2,Itinerary_Tags!$B:$B,Filter_Options!$I$27))+IF(Filter_Options!$J$27="",0,COUNTIFS(Itinerary_Tags!$A:$A,$A2,Itinerary_Tags!$B:$B,Filter_Options!$J$27))+IF(Filter_Options!$K$27="",0,COUNTIFS(Itinerary_Tags!$A:$A,$A2,Itinerary_Tags!$B:$B,Filter_Options!$K$27)))>0)) | AC2: =IF($A2="","",--((IF(Filter_Options!$I$28="",0,COUNTIFS(Itinerary_Tags!$A:$A,$A2,Itinerary_Tags!$B:$B,Filter_Options!$I$28))+IF(Filter_Options!$J$28="",0,COUNTIFS(Itinerary_Tags!$A:$A,$A2,Itinerary_Tags!$B:$B,Filter_Options!$J$28))+IF(Filter_Options!$K$28="",0,COUNTIFS(Itinerary_Tags!$A:$A,$A2,Itinerary_Tags!$B:$B,Filter_Options!$K$28)))>0)) | AD2: =IF($A2="","",--((IF(Filter_Options!$I$29="",0,COUNTIFS(Itinerary_Tags!$A:$A,$A2,Itinerary_Tags!$B:$B,Filter_Options!$I$29))+IF(Filter_Options!$J$29="",0,COUNTIFS(Itinerary_Tags!$A:$A,$A2,Itinerary_Tags!$B:$B,Filter_Options!$J$29))+IF(Filter_Options!$K$29="",0,COUNTIFS(Itinerary_Tags!$A:$A,$A2,Itinerary_Tags!$B:$B,Filter_Options!$K$29)))>0)) | AE2: =IF($A2="","",--((IF(Filter_Options!$I$30="",0,COUNTIFS(Itinerary_Tags!$A:$A,$A2,Itinerary_Tags!$B:$B,Filter_Options!$I$30))+IF(Filter_Options!$J$30="",0,COUNTIFS(Itinerary_Tags!$A:$A,$A2,Itinerary_Tags!$B:$B,Filter_Options!$J$30))+IF(Filter_Options!$K$30="",0,COUNTIFS(Itinerary_Tags!$A:$A,$A2,Itinerary_Tags!$B:$B,Filter_Options!$K$30)))>0)) | AF2: =IF($A2="","",--((IF(Filter_Options!$I$31="",0,COUNTIFS(Itinerary_Tags!$A:$A,$A2,Itinerary_Tags!$B:$B,Filter_Options!$I$31))+IF(Filter_Options!$J$31="",0,COUNTIFS(Itinerary_Tags!$A:$A,$A2,Itinerary_Tags!$B:$B,Filter_Options!$J$31))+IF(Filter_Options!$K$31="",0,COUNTIFS(Itinerary_Tags!$A:$A,$A2,Itinerary_Tags!$B:$B,Filter_Options!$K$31)))>0)) | AG2: =IF($A2="","",--((IF(Filter_Options!$I$32="",0,COUNTIFS(Itinerary_Tags!$A:$A,$A2,Itinerary_Tags!$B:$B,Filter_Options!$I$32))+IF(Filter_Options!$J$32="",0,COUNTIFS(Itinerary_Tags!$A:$A,$A2,Itinerary_Tags!$B:$B,Filter_Options!$J$32))+IF(Filter_Options!$K$32="",0,COUNTIFS(Itinerary_Tags!$A:$A,$A2,Itinerary_Tags!$B:$B,Filter_Options!$K$32)))>0)) | AH2: =IF($A2="","",--((IF(Filter_Options!$I$33="",0,COUNTIFS(Itinerary_Tags!$A:$A,$A2,Itinerary_Tags!$B:$B,Filter_Options!$I$33))+IF(Filter_Options!$J$33="",0,COUNTIFS(Itinerary_Tags!$A:$A,$A2,Itinerary_Tags!$B:$B,Filter_Options!$J$33))+IF(Filter_Options!$K$33="",0,COUNTIFS(Itinerary_Tags!$A:$A,$A2,Itinerary_Tags!$B:$B,Filter_Options!$K$33)))>0)) | AI2: =IF($A2="","",--((IF(Filter_Options!$I$34="",0,COUNTIFS(Itinerary_Tags!$A:$A,$A2,Itinerary_Tags!$B:$B,Filter_Options!$I$34))+IF(Filter_Options!$J$34="",0,COUNTIFS(Itinerary_Tags!$A:$A,$A2,Itinerary_Tags!$B:$B,Filter_Options!$J$34))+IF(Filter_Options!$K$34="",0,COUNTIFS(Itinerary_Tags!$A:$A,$A2,Itinerary_Tags!$B:$B,Filter_Options!$K$34)))>0)) | AJ2: =IF($A2="","",--((IF(Filter_Options!$I$35="",0,COUNTIFS(Itinerary_Tags!$A:$A,$A2,Itinerary_Tags!$B:$B,Filter_Options!$I$35))+IF(Filter_Options!$J$35="",0,COUNTIFS(Itinerary_Tags!$A:$A,$A2,Itinerary_Tags!$B:$B,Filter_Options!$J$35))+IF(Filter_Options!$K$35="",0,COUNTIFS(Itinerary_Tags!$A:$A,$A2,Itinerary_Tags!$B:$B,Filter_Options!$K$35)))>0)) | AK2: =IF($A2="","",--((IF(Filter_Options!$I$36="",0,COUNTIFS(Itinerary_Tags!$A:$A,$A2,Itinerary_Tags!$B:$B,Filter_Options!$I$36))+IF(Filter_Options!$J$36="",0,COUNTIFS(Itinerary_Tags!$A:$A,$A2,Itinerary_Tags!$B:$B,Filter_Options!$J$36))+IF(Filter_Options!$K$36="",0,COUNTIFS(Itinerary_Tags!$A:$A,$A2,Itinerary_Tags!$B:$B,Filter_Options!$K$36)))>0)) | AL2: =IF($A2="","",--((IF(Filter_Options!$I$37="",0,COUNTIFS(Itinerary_Tags!$A:$A,$A2,Itinerary_Tags!$B:$B,Filter_Options!$I$37))+IF(Filter_Options!$J$37="",0,COUNTIFS(Itinerary_Tags!$A:$A,$A2,Itinerary_Tags!$B:$B,Filter_Options!$J$37))+IF(Filter_Options!$K$37="",0,COUNTIFS(Itinerary_Tags!$A:$A,$A2,Itinerary_Tags!$B:$B,Filter_Options!$K$37)))>0))
A3: =IF(Itineraries!A3="","",Itineraries!A3) | B3: =IF(Itineraries!A3="","",Itineraries!C3) | C3: =IF($A3="","",--(Itineraries!$J3=Filter_Options!$F$2)) | D3: =IF($A3="","",--(Itineraries!$J3=Filter_Options!$F$3)) | E3: =IF($A3="","",--(Itineraries!$J3=Filter_Options!$F$4)) | F3: =IF($A3="","",--(Itineraries!$J3=Filter_Options!$F$5)) | G3: =IF($A3="","",--(Itineraries!$J3=Filter_Options!$F$6)) | H3: =IF($A3="","",--(Itineraries!$J3=Filter_Options!$F$7)) | I3: =IF($A3="","",--AND(Itineraries!$K3<=Filter_Options!$H$8,Itineraries!$L3>=Filter_Options!$G$8)) | J3: =IF($A3="","",--AND(Itineraries!$K3<=Filter_Options!$H$9,Itineraries!$L3>=Filter_Options!$G$9)) | K3: =IF($A3="","",--AND(Itineraries!$K3<=Filter_Options!$H$10,Itineraries!$L3>=Filter_Options!$G$10)) | L3: =IF($A3="","",--AND(Itineraries!$K3<=Filter_Options!$H$11,Itineraries!$L3>=Filter_Options!$G$11)) | M3: =IF($A3="","",--AND(Itineraries!$K3<=Filter_Options!$H$12,Itineraries!$L3>=Filter_Options!$G$12)) | N3: =IF($A3="","",--AND(Itineraries!$K3<=Filter_Options!$H$13,Itineraries!$L3>=Filter_Options!$G$13)) | O3: =IF($A3="","",--AND(Itineraries!$E3>=Filter_Options!$G$14,Itineraries!$E3<=Filter_Options!$H$14)) | P3: =IF($A3="","",--AND(Itineraries!$E3>=Filter_Options!$G$15,Itineraries!$E3<=Filter_Options!$H$15)) | Q3: =IF($A3="","",--AND(Itineraries!$E3>=Filter_Options!$G$16,Itineraries!$E3<=Filter_Options!$H$16)) | R3: =IF($A3="","",--AND(Itineraries!$E3>=Filter_Options!$G$17,Itineraries!$E3<=Filter_Options!$H$17)) | S3: =IF($A3="","",--AND(Itineraries!$E3>=Filter_Options!$G$18,Itineraries!$E3<=Filter_Options!$H$18)) | T3: =IF($A3="","",--AND(Itineraries!$E3>=Filter_Options!$G$19,Itineraries!$E3<=Filter_Options!$H$19)) | U3: =IF($A3="","",--((IF(Filter_Options!$I$20="",0,COUNTIFS(Itinerary_Tags!$A:$A,$A3,Itinerary_Tags!$B:$B,Filter_Options!$I$20))+IF(Filter_Options!$J$20="",0,COUNTIFS(Itinerary_Tags!$A:$A,$A3,Itinerary_Tags!$B:$B,Filter_Options!$J$20))+IF(Filter_Options!$K$20="",0,COUNTIFS(Itinerary_Tags!$A:$A,$A3,Itinerary_Tags!$B:$B,Filter_Options!$K$20)))>0)) | V3: =IF($A3="","",--((IF(Filter_Options!$I$21="",0,COUNTIFS(Itinerary_Tags!$A:$A,$A3,Itinerary_Tags!$B:$B,Filter_Options!$I$21))+IF(Filter_Options!$J$21="",0,COUNTIFS(Itinerary_Tags!$A:$A,$A3,Itinerary_Tags!$B:$B,Filter_Options!$J$21))+IF(Filter_Options!$K$21="",0,COUNTIFS(Itinerary_Tags!$A:$A,$A3,Itinerary_Tags!$B:$B,Filter_Options!$K$21)))>0)) | W3: =IF($A3="","",--((IF(Filter_Options!$I$22="",0,COUNTIFS(Itinerary_Tags!$A:$A,$A3,Itinerary_Tags!$B:$B,Filter_Options!$I$22))+IF(Filter_Options!$J$22="",0,COUNTIFS(Itinerary_Tags!$A:$A,$A3,Itinerary_Tags!$B:$B,Filter_Options!$J$22))+IF(Filter_Options!$K$22="",0,COUNTIFS(Itinerary_Tags!$A:$A,$A3,Itinerary_Tags!$B:$B,Filter_Options!$K$22)))>0)) | X3: =IF($A3="","",--((IF(Filter_Options!$I$23="",0,COUNTIFS(Itinerary_Tags!$A:$A,$A3,Itinerary_Tags!$B:$B,Filter_Options!$I$23))+IF(Filter_Options!$J$23="",0,COUNTIFS(Itinerary_Tags!$A:$A,$A3,Itinerary_Tags!$B:$B,Filter_Options!$J$23))+IF(Filter_Options!$K$23="",0,COUNTIFS(Itinerary_Tags!$A:$A,$A3,Itinerary_Tags!$B:$B,Filter_Options!$K$23)))>0)) | Y3: =IF($A3="","",--((IF(Filter_Options!$I$24="",0,COUNTIFS(Itinerary_Tags!$A:$A,$A3,Itinerary_Tags!$B:$B,Filter_Options!$I$24))+IF(Filter_Options!$J$24="",0,COUNTIFS(Itinerary_Tags!$A:$A,$A3,Itinerary_Tags!$B:$B,Filter_Options!$J$24))+IF(Filter_Options!$K$24="",0,COUNTIFS(Itinerary_Tags!$A:$A,$A3,Itinerary_Tags!$B:$B,Filter_Options!$K$24)))>0)) | Z3: =IF($A3="","",--((IF(Filter_Options!$I$25="",0,COUNTIFS(Itinerary_Tags!$A:$A,$A3,Itinerary_Tags!$B:$B,Filter_Options!$I$25))+IF(Filter_Options!$J$25="",0,COUNTIFS(Itinerary_Tags!$A:$A,$A3,Itinerary_Tags!$B:$B,Filter_Options!$J$25))+IF(Filter_Options!$K$25="",0,COUNTIFS(Itinerary_Tags!$A:$A,$A3,Itinerary_Tags!$B:$B,Filter_Options!$K$25)))>0)) | AA3: =IF($A3="","",--((IF(Filter_Options!$I$26="",0,COUNTIFS(Itinerary_Tags!$A:$A,$A3,Itinerary_Tags!$B:$B,Filter_Options!$I$26))+IF(Filter_Options!$J$26="",0,COUNTIFS(Itinerary_Tags!$A:$A,$A3,Itinerary_Tags!$B:$B,Filter_Options!$J$26))+IF(Filter_Options!$K$26="",0,COUNTIFS(Itinerary_Tags!$A:$A,$A3,Itinerary_Tags!$B:$B,Filter_Options!$K$26)))>0)) | AB3: =IF($A3="","",--((IF(Filter_Options!$I$27="",0,COUNTIFS(Itinerary_Tags!$A:$A,$A3,Itinerary_Tags!$B:$B,Filter_Options!$I$27))+IF(Filter_Options!$J$27="",0,COUNTIFS(Itinerary_Tags!$A:$A,$A3,Itinerary_Tags!$B:$B,Filter_Options!$J$27))+IF(Filter_Options!$K$27="",0,COUNTIFS(Itinerary_Tags!$A:$A,$A3,Itinerary_Tags!$B:$B,Filter_Options!$K$27)))>0)) | AC3: =IF($A3="","",--((IF(Filter_Options!$I$28="",0,COUNTIFS(Itinerary_Tags!$A:$A,$A3,Itinerary_Tags!$B:$B,Filter_Options!$I$28))+IF(Filter_Options!$J$28="",0,COUNTIFS(Itinerary_Tags!$A:$A,$A3,Itinerary_Tags!$B:$B,Filter_Options!$J$28))+IF(Filter_Options!$K$28="",0,COUNTIFS(Itinerary_Tags!$A:$A,$A3,Itinerary_Tags!$B:$B,Filter_Options!$K$28)))>0)) | AD3: =IF($A3="","",--((IF(Filter_Options!$I$29="",0,COUNTIFS(Itinerary_Tags!$A:$A,$A3,Itinerary_Tags!$B:$B,Filter_Options!$I$29))+IF(Filter_Options!$J$29="",0,COUNTIFS(Itinerary_Tags!$A:$A,$A3,Itinerary_Tags!$B:$B,Filter_Options!$J$29))+IF(Filter_Options!$K$29="",0,COUNTIFS(Itinerary_Tags!$A:$A,$A3,Itinerary_Tags!$B:$B,Filter_Options!$K$29)))>0)) | AE3: =IF($A3="","",--((IF(Filter_Options!$I$30="",0,COUNTIFS(Itinerary_Tags!$A:$A,$A3,Itinerary_Tags!$B:$B,Filter_Options!$I$30))+IF(Filter_Options!$J$30="",0,COUNTIFS(Itinerary_Tags!$A:$A,$A3,Itinerary_Tags!$B:$B,Filter_Options!$J$30))+IF(Filter_Options!$K$30="",0,COUNTIFS(Itinerary_Tags!$A:$A,$A3,Itinerary_Tags!$B:$B,Filter_Options!$K$30)))>0)) | AF3: =IF($A3="","",--((IF(Filter_Options!$I$31="",0,COUNTIFS(Itinerary_Tags!$A:$A,$A3,Itinerary_Tags!$B:$B,Filter_Options!$I$31))+IF(Filter_Options!$J$31="",0,COUNTIFS(Itinerary_Tags!$A:$A,$A3,Itinerary_Tags!$B:$B,Filter_Options!$J$31))+IF(Filter_Options!$K$31="",0,COUNTIFS(Itinerary_Tags!$A:$A,$A3,Itinerary_Tags!$B:$B,Filter_Options!$K$31)))>0)) | AG3: =IF($A3="","",--((IF(Filter_Options!$I$32="",0,COUNTIFS(Itinerary_Tags!$A:$A,$A3,Itinerary_Tags!$B:$B,Filter_Options!$I$32))+IF(Filter_Options!$J$32="",0,COUNTIFS(Itinerary_Tags!$A:$A,$A3,Itinerary_Tags!$B:$B,Filter_Options!$J$32))+IF(Filter_Options!$K$32="",0,COUNTIFS(Itinerary_Tags!$A:$A,$A3,Itinerary_Tags!$B:$B,Filter_Options!$K$32)))>0)) | AH3: =IF($A3="","",--((IF(Filter_Options!$I$33="",0,COUNTIFS(Itinerary_Tags!$A:$A,$A3,Itinerary_Tags!$B:$B,Filter_Options!$I$33))+IF(Filter_Options!$J$33="",0,COUNTIFS(Itinerary_Tags!$A:$A,$A3,Itinerary_Tags!$B:$B,Filter_Options!$J$33))+IF(Filter_Options!$K$33="",0,COUNTIFS(Itinerary_Tags!$A:$A,$A3,Itinerary_Tags!$B:$B,Filter_Options!$K$33)))>0)) | AI3: =IF($A3="","",--((IF(Filter_Options!$I$34="",0,COUNTIFS(Itinerary_Tags!$A:$A,$A3,Itinerary_Tags!$B:$B,Filter_Options!$I$34))+IF(Filter_Options!$J$34="",0,COUNTIFS(Itinerary_Tags!$A:$A,$A3,Itinerary_Tags!$B:$B,Filter_Options!$J$34))+IF(Filter_Options!$K$34="",0,COUNTIFS(Itinerary_Tags!$A:$A,$A3,Itinerary_Tags!$B:$B,Filter_Options!$K$34)))>0)) | AJ3: =IF($A3="","",--((IF(Filter_Options!$I$35="",0,COUNTIFS(Itinerary_Tags!$A:$A,$A3,Itinerary_Tags!$B:$B,Filter_Options!$I$35))+IF(Filter_Options!$J$35="",0,COUNTIFS(Itinerary_Tags!$A:$A,$A3,Itinerary_Tags!$B:$B,Filter_Options!$J$35))+IF(Filter_Options!$K$35="",0,COUNTIFS(Itinerary_Tags!$A:$A,$A3,Itinerary_Tags!$B:$B,Filter_Options!$K$35)))>0)) | AK3: =IF($A3="","",--((IF(Filter_Options!$I$36="",0,COUNTIFS(Itinerary_Tags!$A:$A,$A3,Itinerary_Tags!$B:$B,Filter_Options!$I$36))+IF(Filter_Options!$J$36="",0,COUNTIFS(Itinerary_Tags!$A:$A,$A3,Itinerary_Tags!$B:$B,Filter_Options!$J$36))+IF(Filter_Options!$K$36="",0,COUNTIFS(Itinerary_Tags!$A:$A,$A3,Itinerary_Tags!$B:$B,Filter_Options!$K$36)))>0)) | AL3: =IF($A3="","",--((IF(Filter_Options!$I$37="",0,COUNTIFS(Itinerary_Tags!$A:$A,$A3,Itinerary_Tags!$B:$B,Filter_Options!$I$37))+IF(Filter_Options!$J$37="",0,COUNTIFS(Itinerary_Tags!$A:$A,$A3,Itinerary_Tags!$B:$B,Filter_Options!$J$37))+IF(Filter_Options!$K$37="",0,COUNTIFS(Itinerary_Tags!$A:$A,$A3,Itinerary_Tags!$B:$B,Filter_Options!$K$37)))>0))
A4: =IF(Itineraries!A4="","",Itineraries!A4) | B4: =IF(Itineraries!A4="","",Itineraries!C4) | C4: =IF($A4="","",--(Itineraries!$J4=Filter_Options!$F$2)) | D4: =IF($A4="","",--(Itineraries!$J4=Filter_Options!$F$3)) | E4: =IF($A4="","",--(Itineraries!$J4=Filter_Options!$F$4)) | F4: =IF($A4="","",--(Itineraries!$J4=Filter_Options!$F$5)) | G4: =IF($A4="","",--(Itineraries!$J4=Filter_Options!$F$6)) | H4: =IF($A4="","",--(Itineraries!$J4=Filter_Options!$F$7)) | I4: =IF($A4="","",--AND(Itineraries!$K4<=Filter_Options!$H$8,Itineraries!$L4>=Filter_Options!$G$8)) | J4: =IF($A4="","",--AND(Itineraries!$K4<=Filter_Options!$H$9,Itineraries!$L4>=Filter_Options!$G$9)) | K4: =IF($A4="","",--AND(Itineraries!$K4<=Filter_Options!$H$10,Itineraries!$L4>=Filter_Options!$G$10)) | L4: =IF($A4="","",--AND(Itineraries!$K4<=Filter_Options!$H$11,Itineraries!$L4>=Filter_Options!$G$11)) | M4: =IF($A4="","",--AND(Itineraries!$K4<=Filter_Options!$H$12,Itineraries!$L4>=Filter_Options!$G$12)) | N4: =IF($A4="","",--AND(Itineraries!$K4<=Filter_Options!$H$13,Itineraries!$L4>=Filter_Options!$G$13)) | O4: =IF($A4="","",--AND(Itineraries!$E4>=Filter_Options!$G$14,Itineraries!$E4<=Filter_Options!$H$14)) | P4: =IF($A4="","",--AND(Itineraries!$E4>=Filter_Options!$G$15,Itineraries!$E4<=Filter_Options!$H$15)) | Q4: =IF($A4="","",--AND(Itineraries!$E4>=Filter_Options!$G$16,Itineraries!$E4<=Filter_Options!$H$16)) | R4: =IF($A4="","",--AND(Itineraries!$E4>=Filter_Options!$G$17,Itineraries!$E4<=Filter_Options!$H$17)) | S4: =IF($A4="","",--AND(Itineraries!$E4>=Filter_Options!$G$18,Itineraries!$E4<=Filter_Options!$H$18)) | T4: =IF($A4="","",--AND(Itineraries!$E4>=Filter_Options!$G$19,Itineraries!$E4<=Filter_Options!$H$19)) | U4: =IF($A4="","",--((IF(Filter_Options!$I$20="",0,COUNTIFS(Itinerary_Tags!$A:$A,$A4,Itinerary_Tags!$B:$B,Filter_Options!$I$20))+IF(Filter_Options!$J$20="",0,COUNTIFS(Itinerary_Tags!$A:$A,$A4,Itinerary_Tags!$B:$B,Filter_Options!$J$20))+IF(Filter_Options!$K$20="",0,COUNTIFS(Itinerary_Tags!$A:$A,$A4,Itinerary_Tags!$B:$B,Filter_Options!$K$20)))>0)) | V4: =IF($A4="","",--((IF(Filter_Options!$I$21="",0,COUNTIFS(Itinerary_Tags!$A:$A,$A4,Itinerary_Tags!$B:$B,Filter_Options!$I$21))+IF(Filter_Options!$J$21="",0,COUNTIFS(Itinerary_Tags!$A:$A,$A4,Itinerary_Tags!$B:$B,Filter_Options!$J$21))+IF(Filter_Options!$K$21="",0,COUNTIFS(Itinerary_Tags!$A:$A,$A4,Itinerary_Tags!$B:$B,Filter_Options!$K$21)))>0)) | W4: =IF($A4="","",--((IF(Filter_Options!$I$22="",0,COUNTIFS(Itinerary_Tags!$A:$A,$A4,Itinerary_Tags!$B:$B,Filter_Options!$I$22))+IF(Filter_Options!$J$22="",0,COUNTIFS(Itinerary_Tags!$A:$A,$A4,Itinerary_Tags!$B:$B,Filter_Options!$J$22))+IF(Filter_Options!$K$22="",0,COUNTIFS(Itinerary_Tags!$A:$A,$A4,Itinerary_Tags!$B:$B,Filter_Options!$K$22)))>0)) | X4: =IF($A4="","",--((IF(Filter_Options!$I$23="",0,COUNTIFS(Itinerary_Tags!$A:$A,$A4,Itinerary_Tags!$B:$B,Filter_Options!$I$23))+IF(Filter_Options!$J$23="",0,COUNTIFS(Itinerary_Tags!$A:$A,$A4,Itinerary_Tags!$B:$B,Filter_Options!$J$23))+IF(Filter_Options!$K$23="",0,COUNTIFS(Itinerary_Tags!$A:$A,$A4,Itinerary_Tags!$B:$B,Filter_Options!$K$23)))>0)) | Y4: =IF($A4="","",--((IF(Filter_Options!$I$24="",0,COUNTIFS(Itinerary_Tags!$A:$A,$A4,Itinerary_Tags!$B:$B,Filter_Options!$I$24))+IF(Filter_Options!$J$24="",0,COUNTIFS(Itinerary_Tags!$A:$A,$A4,Itinerary_Tags!$B:$B,Filter_Options!$J$24))+IF(Filter_Options!$K$24="",0,COUNTIFS(Itinerary_Tags!$A:$A,$A4,Itinerary_Tags!$B:$B,Filter_Options!$K$24)))>0)) | Z4: =IF($A4="","",--((IF(Filter_Options!$I$25="",0,COUNTIFS(Itinerary_Tags!$A:$A,$A4,Itinerary_Tags!$B:$B,Filter_Options!$I$25))+IF(Filter_Options!$J$25="",0,COUNTIFS(Itinerary_Tags!$A:$A,$A4,Itinerary_Tags!$B:$B,Filter_Options!$J$25))+IF(Filter_Options!$K$25="",0,COUNTIFS(Itinerary_Tags!$A:$A,$A4,Itinerary_Tags!$B:$B,Filter_Options!$K$25)))>0)) | AA4: =IF($A4="","",--((IF(Filter_Options!$I$26="",0,COUNTIFS(Itinerary_Tags!$A:$A,$A4,Itinerary_Tags!$B:$B,Filter_Options!$I$26))+IF(Filter_Options!$J$26="",0,COUNTIFS(Itinerary_Tags!$A:$A,$A4,Itinerary_Tags!$B:$B,Filter_Options!$J$26))+IF(Filter_Options!$K$26="",0,COUNTIFS(Itinerary_Tags!$A:$A,$A4,Itinerary_Tags!$B:$B,Filter_Options!$K$26)))>0)) | AB4: =IF($A4="","",--((IF(Filter_Options!$I$27="",0,COUNTIFS(Itinerary_Tags!$A:$A,$A4,Itinerary_Tags!$B:$B,Filter_Options!$I$27))+IF(Filter_Options!$J$27="",0,COUNTIFS(Itinerary_Tags!$A:$A,$A4,Itinerary_Tags!$B:$B,Filter_Options!$J$27))+IF(Filter_Options!$K$27="",0,COUNTIFS(Itinerary_Tags!$A:$A,$A4,Itinerary_Tags!$B:$B,Filter_Options!$K$27)))>0)) | AC4: =IF($A4="","",--((IF(Filter_Options!$I$28="",0,COUNTIFS(Itinerary_Tags!$A:$A,$A4,Itinerary_Tags!$B:$B,Filter_Options!$I$28))+IF(Filter_Options!$J$28="",0,COUNTIFS(Itinerary_Tags!$A:$A,$A4,Itinerary_Tags!$B:$B,Filter_Options!$J$28))+IF(Filter_Options!$K$28="",0,COUNTIFS(Itinerary_Tags!$A:$A,$A4,Itinerary_Tags!$B:$B,Filter_Options!$K$28)))>0)) | AD4: =IF($A4="","",--((IF(Filter_Options!$I$29="",0,COUNTIFS(Itinerary_Tags!$A:$A,$A4,Itinerary_Tags!$B:$B,Filter_Options!$I$29))+IF(Filter_Options!$J$29="",0,COUNTIFS(Itinerary_Tags!$A:$A,$A4,Itinerary_Tags!$B:$B,Filter_Options!$J$29))+IF(Filter_Options!$K$29="",0,COUNTIFS(Itinerary_Tags!$A:$A,$A4,Itinerary_Tags!$B:$B,Filter_Options!$K$29)))>0)) | AE4: =IF($A4="","",--((IF(Filter_Options!$I$30="",0,COUNTIFS(Itinerary_Tags!$A:$A,$A4,Itinerary_Tags!$B:$B,Filter_Options!$I$30))+IF(Filter_Options!$J$30="",0,COUNTIFS(Itinerary_Tags!$A:$A,$A4,Itinerary_Tags!$B:$B,Filter_Options!$J$30))+IF(Filter_Options!$K$30="",0,COUNTIFS(Itinerary_Tags!$A:$A,$A4,Itinerary_Tags!$B:$B,Filter_Options!$K$30)))>0)) | AF4: =IF($A4="","",--((IF(Filter_Options!$I$31="",0,COUNTIFS(Itinerary_Tags!$A:$A,$A4,Itinerary_Tags!$B:$B,Filter_Options!$I$31))+IF(Filter_Options!$J$31="",0,COUNTIFS(Itinerary_Tags!$A:$A,$A4,Itinerary_Tags!$B:$B,Filter_Options!$J$31))+IF(Filter_Options!$K$31="",0,COUNTIFS(Itinerary_Tags!$A:$A,$A4,Itinerary_Tags!$B:$B,Filter_Options!$K$31)))>0)) | AG4: =IF($A4="","",--((IF(Filter_Options!$I$32="",0,COUNTIFS(Itinerary_Tags!$A:$A,$A4,Itinerary_Tags!$B:$B,Filter_Options!$I$32))+IF(Filter_Options!$J$32="",0,COUNTIFS(Itinerary_Tags!$A:$A,$A4,Itinerary_Tags!$B:$B,Filter_Options!$J$32))+IF(Filter_Options!$K$32="",0,COUNTIFS(Itinerary_Tags!$A:$A,$A4,Itinerary_Tags!$B:$B,Filter_Options!$K$32)))>0)) | AH4: =IF($A4="","",--((IF(Filter_Options!$I$33="",0,COUNTIFS(Itinerary_Tags!$A:$A,$A4,Itinerary_Tags!$B:$B,Filter_Options!$I$33))+IF(Filter_Options!$J$33="",0,COUNTIFS(Itinerary_Tags!$A:$A,$A4,Itinerary_Tags!$B:$B,Filter_Options!$J$33))+IF(Filter_Options!$K$33="",0,COUNTIFS(Itinerary_Tags!$A:$A,$A4,Itinerary_Tags!$B:$B,Filter_Options!$K$33)))>0)) | AI4: =IF($A4="","",--((IF(Filter_Options!$I$34="",0,COUNTIFS(Itinerary_Tags!$A:$A,$A4,Itinerary_Tags!$B:$B,Filter_Options!$I$34))+IF(Filter_Options!$J$34="",0,COUNTIFS(Itinerary_Tags!$A:$A,$A4,Itinerary_Tags!$B:$B,Filter_Options!$J$34))+IF(Filter_Options!$K$34="",0,COUNTIFS(Itinerary_Tags!$A:$A,$A4,Itinerary_Tags!$B:$B,Filter_Options!$K$34)))>0)) | AJ4: =IF($A4="","",--((IF(Filter_Options!$I$35="",0,COUNTIFS(Itinerary_Tags!$A:$A,$A4,Itinerary_Tags!$B:$B,Filter_Options!$I$35))+IF(Filter_Options!$J$35="",0,COUNTIFS(Itinerary_Tags!$A:$A,$A4,Itinerary_Tags!$B:$B,Filter_Options!$J$35))+IF(Filter_Options!$K$35="",0,COUNTIFS(Itinerary_Tags!$A:$A,$A4,Itinerary_Tags!$B:$B,Filter_Options!$K$35)))>0)) | AK4: =IF($A4="","",--((IF(Filter_Options!$I$36="",0,COUNTIFS(Itinerary_Tags!$A:$A,$A4,Itinerary_Tags!$B:$B,Filter_Options!$I$36))+IF(Filter_Options!$J$36="",0,COUNTIFS(Itinerary_Tags!$A:$A,$A4,Itinerary_Tags!$B:$B,Filter_Options!$J$36))+IF(Filter_Options!$K$36="",0,COUNTIFS(Itinerary_Tags!$A:$A,$A4,Itinerary_Tags!$B:$B,Filter_Options!$K$36)))>0)) | AL4: =IF($A4="","",--((IF(Filter_Options!$I$37="",0,COUNTIFS(Itinerary_Tags!$A:$A,$A4,Itinerary_Tags!$B:$B,Filter_Options!$I$37))+IF(Filter_Options!$J$37="",0,COUNTIFS(Itinerary_Tags!$A:$A,$A4,Itinerary_Tags!$B:$B,Filter_Options!$J$37))+IF(Filter_Options!$K$37="",0,COUNTIFS(Itinerary_Tags!$A:$A,$A4,Itinerary_Tags!$B:$B,Filter_Options!$K$37)))>0))
A5: =IF(Itineraries!A5="","",Itineraries!A5) | B5: =IF(Itineraries!A5="","",Itineraries!C5) | C5: =IF($A5="","",--(Itineraries!$J5=Filter_Options!$F$2)) | D5: =IF($A5="","",--(Itineraries!$J5=Filter_Options!$F$3)) | E5: =IF($A5="","",--(Itineraries!$J5=Filter_Options!$F$4)) | F5: =IF($A5="","",--(Itineraries!$J5=Filter_Options!$F$5)) | G5: =IF($A5="","",--(Itineraries!$J5=Filter_Options!$F$6)) | H5: =IF($A5="","",--(Itineraries!$J5=Filter_Options!$F$7)) | I5: =IF($A5="","",--AND(Itineraries!$K5<=Filter_Options!$H$8,Itineraries!$L5>=Filter_Options!$G$8)) | J5: =IF($A5="","",--AND(Itineraries!$K5<=Filter_Options!$H$9,Itineraries!$L5>=Filter_Options!$G$9)) | K5: =IF($A5="","",--AND(Itineraries!$K5<=Filter_Options!$H$10,Itineraries!$L5>=Filter_Options!$G$10)) | L5: =IF($A5="","",--AND(Itineraries!$K5<=Filter_Options!$H$11,Itineraries!$L5>=Filter_Options!$G$11)) | M5: =IF($A5="","",--AND(Itineraries!$K5<=Filter_Options!$H$12,Itineraries!$L5>=Filter_Options!$G$12)) | N5: =IF($A5="","",--AND(Itineraries!$K5<=Filter_Options!$H$13,Itineraries!$L5>=Filter_Options!$G$13)) | O5: =IF($A5="","",--AND(Itineraries!$E5>=Filter_Options!$G$14,Itineraries!$E5<=Filter_Options!$H$14)) | P5: =IF($A5="","",--AND(Itineraries!$E5>=Filter_Options!$G$15,Itineraries!$E5<=Filter_Options!$H$15)) | Q5: =IF($A5="","",--AND(Itineraries!$E5>=Filter_Options!$G$16,Itineraries!$E5<=Filter_Options!$H$16)) | R5: =IF($A5="","",--AND(Itineraries!$E5>=Filter_Options!$G$17,Itineraries!$E5<=Filter_Options!$H$17)) | S5: =IF($A5="","",--AND(Itineraries!$E5>=Filter_Options!$G$18,Itineraries!$E5<=Filter_Options!$H$18)) | T5: =IF($A5="","",--AND(Itineraries!$E5>=Filter_Options!$G$19,Itineraries!$E5<=Filter_Options!$H$19)) | U5: =IF($A5="","",--((IF(Filter_Options!$I$20="",0,COUNTIFS(Itinerary_Tags!$A:$A,$A5,Itinerary_Tags!$B:$B,Filter_Options!$I$20))+IF(Filter_Options!$J$20="",0,COUNTIFS(Itinerary_Tags!$A:$A,$A5,Itinerary_Tags!$B:$B,Filter_Options!$J$20))+IF(Filter_Options!$K$20="",0,COUNTIFS(Itinerary_Tags!$A:$A,$A5,Itinerary_Tags!$B:$B,Filter_Options!$K$20)))>0)) | V5: =IF($A5="","",--((IF(Filter_Options!$I$21="",0,COUNTIFS(Itinerary_Tags!$A:$A,$A5,Itinerary_Tags!$B:$B,Filter_Options!$I$21))+IF(Filter_Options!$J$21="",0,COUNTIFS(Itinerary_Tags!$A:$A,$A5,Itinerary_Tags!$B:$B,Filter_Options!$J$21))+IF(Filter_Options!$K$21="",0,COUNTIFS(Itinerary_Tags!$A:$A,$A5,Itinerary_Tags!$B:$B,Filter_Options!$K$21)))>0)) | W5: =IF($A5="","",--((IF(Filter_Options!$I$22="",0,COUNTIFS(Itinerary_Tags!$A:$A,$A5,Itinerary_Tags!$B:$B,Filter_Options!$I$22))+IF(Filter_Options!$J$22="",0,COUNTIFS(Itinerary_Tags!$A:$A,$A5,Itinerary_Tags!$B:$B,Filter_Options!$J$22))+IF(Filter_Options!$K$22="",0,COUNTIFS(Itinerary_Tags!$A:$A,$A5,Itinerary_Tags!$B:$B,Filter_Options!$K$22)))>0)) | X5: =IF($A5="","",--((IF(Filter_Options!$I$23="",0,COUNTIFS(Itinerary_Tags!$A:$A,$A5,Itinerary_Tags!$B:$B,Filter_Options!$I$23))+IF(Filter_Options!$J$23="",0,COUNTIFS(Itinerary_Tags!$A:$A,$A5,Itinerary_Tags!$B:$B,Filter_Options!$J$23))+IF(Filter_Options!$K$23="",0,COUNTIFS(Itinerary_Tags!$A:$A,$A5,Itinerary_Tags!$B:$B,Filter_Options!$K$23)))>0)) | Y5: =IF($A5="","",--((IF(Filter_Options!$I$24="",0,COUNTIFS(Itinerary_Tags!$A:$A,$A5,Itinerary_Tags!$B:$B,Filter_Options!$I$24))+IF(Filter_Options!$J$24="",0,COUNTIFS(Itinerary_Tags!$A:$A,$A5,Itinerary_Tags!$B:$B,Filter_Options!$J$24))+IF(Filter_Options!$K$24="",0,COUNTIFS(Itinerary_Tags!$A:$A,$A5,Itinerary_Tags!$B:$B,Filter_Options!$K$24)))>0)) | Z5: =IF($A5="","",--((IF(Filter_Options!$I$25="",0,COUNTIFS(Itinerary_Tags!$A:$A,$A5,Itinerary_Tags!$B:$B,Filter_Options!$I$25))+IF(Filter_Options!$J$25="",0,COUNTIFS(Itinerary_Tags!$A:$A,$A5,Itinerary_Tags!$B:$B,Filter_Options!$J$25))+IF(Filter_Options!$K$25="",0,COUNTIFS(Itinerary_Tags!$A:$A,$A5,Itinerary_Tags!$B:$B,Filter_Options!$K$25)))>0)) | AA5: =IF($A5="","",--((IF(Filter_Options!$I$26="",0,COUNTIFS(Itinerary_Tags!$A:$A,$A5,Itinerary_Tags!$B:$B,Filter_Options!$I$26))+IF(Filter_Options!$J$26="",0,COUNTIFS(Itinerary_Tags!$A:$A,$A5,Itinerary_Tags!$B:$B,Filter_Options!$J$26))+IF(Filter_Options!$K$26="",0,COUNTIFS(Itinerary_Tags!$A:$A,$A5,Itinerary_Tags!$B:$B,Filter_Options!$K$26)))>0)) | AB5: =IF($A5="","",--((IF(Filter_Options!$I$27="",0,COUNTIFS(Itinerary_Tags!$A:$A,$A5,Itinerary_Tags!$B:$B,Filter_Options!$I$27))+IF(Filter_Options!$J$27="",0,COUNTIFS(Itinerary_Tags!$A:$A,$A5,Itinerary_Tags!$B:$B,Filter_Options!$J$27))+IF(Filter_Options!$K$27="",0,COUNTIFS(Itinerary_Tags!$A:$A,$A5,Itinerary_Tags!$B:$B,Filter_Options!$K$27)))>0)) | AC5: =IF($A5="","",--((IF(Filter_Options!$I$28="",0,COUNTIFS(Itinerary_Tags!$A:$A,$A5,Itinerary_Tags!$B:$B,Filter_Options!$I$28))+IF(Filter_Options!$J$28="",0,COUNTIFS(Itinerary_Tags!$A:$A,$A5,Itinerary_Tags!$B:$B,Filter_Options!$J$28))+IF(Filter_Options!$K$28="",0,COUNTIFS(Itinerary_Tags!$A:$A,$A5,Itinerary_Tags!$B:$B,Filter_Options!$K$28)))>0)) | AD5: =IF($A5="","",--((IF(Filter_Options!$I$29="",0,COUNTIFS(Itinerary_Tags!$A:$A,$A5,Itinerary_Tags!$B:$B,Filter_Options!$I$29))+IF(Filter_Options!$J$29="",0,COUNTIFS(Itinerary_Tags!$A:$A,$A5,Itinerary_Tags!$B:$B,Filter_Options!$J$29))+IF(Filter_Options!$K$29="",0,COUNTIFS(Itinerary_Tags!$A:$A,$A5,Itinerary_Tags!$B:$B,Filter_Options!$K$29)))>0)) | AE5: =IF($A5="","",--((IF(Filter_Options!$I$30="",0,COUNTIFS(Itinerary_Tags!$A:$A,$A5,Itinerary_Tags!$B:$B,Filter_Options!$I$30))+IF(Filter_Options!$J$30="",0,COUNTIFS(Itinerary_Tags!$A:$A,$A5,Itinerary_Tags!$B:$B,Filter_Options!$J$30))+IF(Filter_Options!$K$30="",0,COUNTIFS(Itinerary_Tags!$A:$A,$A5,Itinerary_Tags!$B:$B,Filter_Options!$K$30)))>0)) | AF5: =IF($A5="","",--((IF(Filter_Options!$I$31="",0,COUNTIFS(Itinerary_Tags!$A:$A,$A5,Itinerary_Tags!$B:$B,Filter_Options!$I$31))+IF(Filter_Options!$J$31="",0,COUNTIFS(Itinerary_Tags!$A:$A,$A5,Itinerary_Tags!$B:$B,Filter_Options!$J$31))+IF(Filter_Options!$K$31="",0,COUNTIFS(Itinerary_Tags!$A:$A,$A5,Itinerary_Tags!$B:$B,Filter_Options!$K$31)))>0)) | AG5: =IF($A5="","",--((IF(Filter_Options!$I$32="",0,COUNTIFS(Itinerary_Tags!$A:$A,$A5,Itinerary_Tags!$B:$B,Filter_Options!$I$32))+IF(Filter_Options!$J$32="",0,COUNTIFS(Itinerary_Tags!$A:$A,$A5,Itinerary_Tags!$B:$B,Filter_Options!$J$32))+IF(Filter_Options!$K$32="",0,COUNTIFS(Itinerary_Tags!$A:$A,$A5,Itinerary_Tags!$B:$B,Filter_Options!$K$32)))>0)) | AH5: =IF($A5="","",--((IF(Filter_Options!$I$33="",0,COUNTIFS(Itinerary_Tags!$A:$A,$A5,Itinerary_Tags!$B:$B,Filter_Options!$I$33))+IF(Filter_Options!$J$33="",0,COUNTIFS(Itinerary_Tags!$A:$A,$A5,Itinerary_Tags!$B:$B,Filter_Options!$J$33))+IF(Filter_Options!$K$33="",0,COUNTIFS(Itinerary_Tags!$A:$A,$A5,Itinerary_Tags!$B:$B,Filter_Options!$K$33)))>0)) | AI5: =IF($A5="","",--((IF(Filter_Options!$I$34="",0,COUNTIFS(Itinerary_Tags!$A:$A,$A5,Itinerary_Tags!$B:$B,Filter_Options!$I$34))+IF(Filter_Options!$J$34="",0,COUNTIFS(Itinerary_Tags!$A:$A,$A5,Itinerary_Tags!$B:$B,Filter_Options!$J$34))+IF(Filter_Options!$K$34="",0,COUNTIFS(Itinerary_Tags!$A:$A,$A5,Itinerary_Tags!$B:$B,Filter_Options!$K$34)))>0)) | AJ5: =IF($A5="","",--((IF(Filter_Options!$I$35="",0,COUNTIFS(Itinerary_Tags!$A:$A,$A5,Itinerary_Tags!$B:$B,Filter_Options!$I$35))+IF(Filter_Options!$J$35="",0,COUNTIFS(Itinerary_Tags!$A:$A,$A5,Itinerary_Tags!$B:$B,Filter_Options!$J$35))+IF(Filter_Options!$K$35="",0,COUNTIFS(Itinerary_Tags!$A:$A,$A5,Itinerary_Tags!$B:$B,Filter_Options!$K$35)))>0)) | AK5: =IF($A5="","",--((IF(Filter_Options!$I$36="",0,COUNTIFS(Itinerary_Tags!$A:$A,$A5,Itinerary_Tags!$B:$B,Filter_Options!$I$36))+IF(Filter_Options!$J$36="",0,COUNTIFS(Itinerary_Tags!$A:$A,$A5,Itinerary_Tags!$B:$B,Filter_Options!$J$36))+IF(Filter_Options!$K$36="",0,COUNTIFS(Itinerary_Tags!$A:$A,$A5,Itinerary_Tags!$B:$B,Filter_Options!$K$36)))>0)) | AL5: =IF($A5="","",--((IF(Filter_Options!$I$37="",0,COUNTIFS(Itinerary_Tags!$A:$A,$A5,Itinerary_Tags!$B:$B,Filter_Options!$I$37))+IF(Filter_Options!$J$37="",0,COUNTIFS(Itinerary_Tags!$A:$A,$A5,Itinerary_Tags!$B:$B,Filter_Options!$J$37))+IF(Filter_Options!$K$37="",0,COUNTIFS(Itinerary_Tags!$A:$A,$A5,Itinerary_Tags!$B:$B,Filter_Options!$K$37)))>0))
A6: =IF(Itineraries!A6="","",Itineraries!A6) | B6: =IF(Itineraries!A6="","",Itineraries!C6) | C6: =IF($A6="","",--(Itineraries!$J6=Filter_Options!$F$2)) | D6: =IF($A6="","",--(Itineraries!$J6=Filter_Options!$F$3)) | E6: =IF($A6="","",--(Itineraries!$J6=Filter_Options!$F$4)) | F6: =IF($A6="","",--(Itineraries!$J6=Filter_Options!$F$5)) | G6: =IF($A6="","",--(Itineraries!$J6=Filter_Options!$F$6)) | H6: =IF($A6="","",--(Itineraries!$J6=Filter_Options!$F$7)) | I6: =IF($A6="","",--AND(Itineraries!$K6<=Filter_Options!$H$8,Itineraries!$L6>=Filter_Options!$G$8)) | J6: =IF($A6="","",--AND(Itineraries!$K6<=Filter_Options!$H$9,Itineraries!$L6>=Filter_Options!$G$9)) | K6: =IF($A6="","",--AND(Itineraries!$K6<=Filter_Options!$H$10,Itineraries!$L6>=Filter_Options!$G$10)) | L6: =IF($A6="","",--AND(Itineraries!$K6<=Filter_Options!$H$11,Itineraries!$L6>=Filter_Options!$G$11)) | M6: =IF($A6="","",--AND(Itineraries!$K6<=Filter_Options!$H$12,Itineraries!$L6>=Filter_Options!$G$12)) | N6: =IF($A6="","",--AND(Itineraries!$K6<=Filter_Options!$H$13,Itineraries!$L6>=Filter_Options!$G$13)) | O6: =IF($A6="","",--AND(Itineraries!$E6>=Filter_Options!$G$14,Itineraries!$E6<=Filter_Options!$H$14)) | P6: =IF($A6="","",--AND(Itineraries!$E6>=Filter_Options!$G$15,Itineraries!$E6<=Filter_Options!$H$15)) | Q6: =IF($A6="","",--AND(Itineraries!$E6>=Filter_Options!$G$16,Itineraries!$E6<=Filter_Options!$H$16)) | R6: =IF($A6="","",--AND(Itineraries!$E6>=Filter_Options!$G$17,Itineraries!$E6<=Filter_Options!$H$17)) | S6: =IF($A6="","",--AND(Itineraries!$E6>=Filter_Options!$G$18,Itineraries!$E6<=Filter_Options!$H$18)) | T6: =IF($A6="","",--AND(Itineraries!$E6>=Filter_Options!$G$19,Itineraries!$E6<=Filter_Options!$H$19)) | U6: =IF($A6="","",--((IF(Filter_Options!$I$20="",0,COUNTIFS(Itinerary_Tags!$A:$A,$A6,Itinerary_Tags!$B:$B,Filter_Options!$I$20))+IF(Filter_Options!$J$20="",0,COUNTIFS(Itinerary_Tags!$A:$A,$A6,Itinerary_Tags!$B:$B,Filter_Options!$J$20))+IF(Filter_Options!$K$20="",0,COUNTIFS(Itinerary_Tags!$A:$A,$A6,Itinerary_Tags!$B:$B,Filter_Options!$K$20)))>0)) | V6: =IF($A6="","",--((IF(Filter_Options!$I$21="",0,COUNTIFS(Itinerary_Tags!$A:$A,$A6,Itinerary_Tags!$B:$B,Filter_Options!$I$21))+IF(Filter_Options!$J$21="",0,COUNTIFS(Itinerary_Tags!$A:$A,$A6,Itinerary_Tags!$B:$B,Filter_Options!$J$21))+IF(Filter_Options!$K$21="",0,COUNTIFS(Itinerary_Tags!$A:$A,$A6,Itinerary_Tags!$B:$B,Filter_Options!$K$21)))>0)) | W6: =IF($A6="","",--((IF(Filter_Options!$I$22="",0,COUNTIFS(Itinerary_Tags!$A:$A,$A6,Itinerary_Tags!$B:$B,Filter_Options!$I$22))+IF(Filter_Options!$J$22="",0,COUNTIFS(Itinerary_Tags!$A:$A,$A6,Itinerary_Tags!$B:$B,Filter_Options!$J$22))+IF(Filter_Options!$K$22="",0,COUNTIFS(Itinerary_Tags!$A:$A,$A6,Itinerary_Tags!$B:$B,Filter_Options!$K$22)))>0)) | X6: =IF($A6="","",--((IF(Filter_Options!$I$23="",0,COUNTIFS(Itinerary_Tags!$A:$A,$A6,Itinerary_Tags!$B:$B,Filter_Options!$I$23))+IF(Filter_Options!$J$23="",0,COUNTIFS(Itinerary_Tags!$A:$A,$A6,Itinerary_Tags!$B:$B,Filter_Options!$J$23))+IF(Filter_Options!$K$23="",0,COUNTIFS(Itinerary_Tags!$A:$A,$A6,Itinerary_Tags!$B:$B,Filter_Options!$K$23)))>0)) | Y6: =IF($A6="","",--((IF(Filter_Options!$I$24="",0,COUNTIFS(Itinerary_Tags!$A:$A,$A6,Itinerary_Tags!$B:$B,Filter_Options!$I$24))+IF(Filter_Options!$J$24="",0,COUNTIFS(Itinerary_Tags!$A:$A,$A6,Itinerary_Tags!$B:$B,Filter_Options!$J$24))+IF(Filter_Options!$K$24="",0,COUNTIFS(Itinerary_Tags!$A:$A,$A6,Itinerary_Tags!$B:$B,Filter_Options!$K$24)))>0)) | Z6: =IF($A6="","",--((IF(Filter_Options!$I$25="",0,COUNTIFS(Itinerary_Tags!$A:$A,$A6,Itinerary_Tags!$B:$B,Filter_Options!$I$25))+IF(Filter_Options!$J$25="",0,COUNTIFS(Itinerary_Tags!$A:$A,$A6,Itinerary_Tags!$B:$B,Filter_Options!$J$25))+IF(Filter_Options!$K$25="",0,COUNTIFS(Itinerary_Tags!$A:$A,$A6,Itinerary_Tags!$B:$B,Filter_Options!$K$25)))>0)) | AA6: =IF($A6="","",--((IF(Filter_Options!$I$26="",0,COUNTIFS(Itinerary_Tags!$A:$A,$A6,Itinerary_Tags!$B:$B,Filter_Options!$I$26))+IF(Filter_Options!$J$26="",0,COUNTIFS(Itinerary_Tags!$A:$A,$A6,Itinerary_Tags!$B:$B,Filter_Options!$J$26))+IF(Filter_Options!$K$26="",0,COUNTIFS(Itinerary_Tags!$A:$A,$A6,Itinerary_Tags!$B:$B,Filter_Options!$K$26)))>0)) | AB6: =IF($A6="","",--((IF(Filter_Options!$I$27="",0,COUNTIFS(Itinerary_Tags!$A:$A,$A6,Itinerary_Tags!$B:$B,Filter_Options!$I$27))+IF(Filter_Options!$J$27="",0,COUNTIFS(Itinerary_Tags!$A:$A,$A6,Itinerary_Tags!$B:$B,Filter_Options!$J$27))+IF(Filter_Options!$K$27="",0,COUNTIFS(Itinerary_Tags!$A:$A,$A6,Itinerary_Tags!$B:$B,Filter_Options!$K$27)))>0)) | AC6: =IF($A6="","",--((IF(Filter_Options!$I$28="",0,COUNTIFS(Itinerary_Tags!$A:$A,$A6,Itinerary_Tags!$B:$B,Filter_Options!$I$28))+IF(Filter_Options!$J$28="",0,COUNTIFS(Itinerary_Tags!$A:$A,$A6,Itinerary_Tags!$B:$B,Filter_Options!$J$28))+IF(Filter_Options!$K$28="",0,COUNTIFS(Itinerary_Tags!$A:$A,$A6,Itinerary_Tags!$B:$B,Filter_Options!$K$28)))>0)) | AD6: =IF($A6="","",--((IF(Filter_Options!$I$29="",0,COUNTIFS(Itinerary_Tags!$A:$A,$A6,Itinerary_Tags!$B:$B,Filter_Options!$I$29))+IF(Filter_Options!$J$29="",0,COUNTIFS(Itinerary_Tags!$A:$A,$A6,Itinerary_Tags!$B:$B,Filter_Options!$J$29))+IF(Filter_Options!$K$29="",0,COUNTIFS(Itinerary_Tags!$A:$A,$A6,Itinerary_Tags!$B:$B,Filter_Options!$K$29)))>0)) | AE6: =IF($A6="","",--((IF(Filter_Options!$I$30="",0,COUNTIFS(Itinerary_Tags!$A:$A,$A6,Itinerary_Tags!$B:$B,Filter_Options!$I$30))+IF(Filter_Options!$J$30="",0,COUNTIFS(Itinerary_Tags!$A:$A,$A6,Itinerary_Tags!$B:$B,Filter_Options!$J$30))+IF(Filter_Options!$K$30="",0,COUNTIFS(Itinerary_Tags!$A:$A,$A6,Itinerary_Tags!$B:$B,Filter_Options!$K$30)))>0)) | AF6: =IF($A6="","",--((IF(Filter_Options!$I$31="",0,COUNTIFS(Itinerary_Tags!$A:$A,$A6,Itinerary_Tags!$B:$B,Filter_Options!$I$31))+IF(Filter_Options!$J$31="",0,COUNTIFS(Itinerary_Tags!$A:$A,$A6,Itinerary_Tags!$B:$B,Filter_Options!$J$31))+IF(Filter_Options!$K$31="",0,COUNTIFS(Itinerary_Tags!$A:$A,$A6,Itinerary_Tags!$B:$B,Filter_Options!$K$31)))>0)) | AG6: =IF($A6="","",--((IF(Filter_Options!$I$32="",0,COUNTIFS(Itinerary_Tags!$A:$A,$A6,Itinerary_Tags!$B:$B,Filter_Options!$I$32))+IF(Filter_Options!$J$32="",0,COUNTIFS(Itinerary_Tags!$A:$A,$A6,Itinerary_Tags!$B:$B,Filter_Options!$J$32))+IF(Filter_Options!$K$32="",0,COUNTIFS(Itinerary_Tags!$A:$A,$A6,Itinerary_Tags!$B:$B,Filter_Options!$K$32)))>0)) | AH6: =IF($A6="","",--((IF(Filter_Options!$I$33="",0,COUNTIFS(Itinerary_Tags!$A:$A,$A6,Itinerary_Tags!$B:$B,Filter_Options!$I$33))+IF(Filter_Options!$J$33="",0,COUNTIFS(Itinerary_Tags!$A:$A,$A6,Itinerary_Tags!$B:$B,Filter_Options!$J$33))+IF(Filter_Options!$K$33="",0,COUNTIFS(Itinerary_Tags!$A:$A,$A6,Itinerary_Tags!$B:$B,Filter_Options!$K$33)))>0)) | AI6: =IF($A6="","",--((IF(Filter_Options!$I$34="",0,COUNTIFS(Itinerary_Tags!$A:$A,$A6,Itinerary_Tags!$B:$B,Filter_Options!$I$34))+IF(Filter_Options!$J$34="",0,COUNTIFS(Itinerary_Tags!$A:$A,$A6,Itinerary_Tags!$B:$B,Filter_Options!$J$34))+IF(Filter_Options!$K$34="",0,COUNTIFS(Itinerary_Tags!$A:$A,$A6,Itinerary_Tags!$B:$B,Filter_Options!$K$34)))>0)) | AJ6: =IF($A6="","",--((IF(Filter_Options!$I$35="",0,COUNTIFS(Itinerary_Tags!$A:$A,$A6,Itinerary_Tags!$B:$B,Filter_Options!$I$35))+IF(Filter_Options!$J$35="",0,COUNTIFS(Itinerary_Tags!$A:$A,$A6,Itinerary_Tags!$B:$B,Filter_Options!$J$35))+IF(Filter_Options!$K$35="",0,COUNTIFS(Itinerary_Tags!$A:$A,$A6,Itinerary_Tags!$B:$B,Filter_Options!$K$35)))>0)) | AK6: =IF($A6="","",--((IF(Filter_Options!$I$36="",0,COUNTIFS(Itinerary_Tags!$A:$A,$A6,Itinerary_Tags!$B:$B,Filter_Options!$I$36))+IF(Filter_Options!$J$36="",0,COUNTIFS(Itinerary_Tags!$A:$A,$A6,Itinerary_Tags!$B:$B,Filter_Options!$J$36))+IF(Filter_Options!$K$36="",0,COUNTIFS(Itinerary_Tags!$A:$A,$A6,Itinerary_Tags!$B:$B,Filter_Options!$K$36)))>0)) | AL6: =IF($A6="","",--((IF(Filter_Options!$I$37="",0,COUNTIFS(Itinerary_Tags!$A:$A,$A6,Itinerary_Tags!$B:$B,Filter_Options!$I$37))+IF(Filter_Options!$J$37="",0,COUNTIFS(Itinerary_Tags!$A:$A,$A6,Itinerary_Tags!$B:$B,Filter_Options!$J$37))+IF(Filter_Options!$K$37="",0,COUNTIFS(Itinerary_Tags!$A:$A,$A6,Itinerary_Tags!$B:$B,Filter_Options!$K$37)))>0))
A7: =IF(Itineraries!A7="","",Itineraries!A7) | B7: =IF(Itineraries!A7="","",Itineraries!C7) | C7: =IF($A7="","",--(Itineraries!$J7=Filter_Options!$F$2)) | D7: =IF($A7="","",--(Itineraries!$J7=Filter_Options!$F$3)) | E7: =IF($A7="","",--(Itineraries!$J7=Filter_Options!$F$4)) | F7: =IF($A7="","",--(Itineraries!$J7=Filter_Options!$F$5)) | G7: =IF($A7="","",--(Itineraries!$J7=Filter_Options!$F$6)) | H7: =IF($A7="","",--(Itineraries!$J7=Filter_Options!$F$7)) | I7: =IF($A7="","",--AND(Itineraries!$K7<=Filter_Options!$H$8,Itineraries!$L7>=Filter_Options!$G$8)) | J7: =IF($A7="","",--AND(Itineraries!$K7<=Filter_Options!$H$9,Itineraries!$L7>=Filter_Options!$G$9)) | K7: =IF($A7="","",--AND(Itineraries!$K7<=Filter_Options!$H$10,Itineraries!$L7>=Filter_Options!$G$10)) | L7: =IF($A7="","",--AND(Itineraries!$K7<=Filter_Options!$H$11,Itineraries!$L7>=Filter_Options!$G$11)) | M7: =IF($A7="","",--AND(Itineraries!$K7<=Filter_Options!$H$12,Itineraries!$L7>=Filter_Options!$G$12)) | N7: =IF($A7="","",--AND(Itineraries!$K7<=Filter_Options!$H$13,Itineraries!$L7>=Filter_Options!$G$13)) | O7: =IF($A7="","",--AND(Itineraries!$E7>=Filter_Options!$G$14,Itineraries!$E7<=Filter_Options!$H$14)) | P7: =IF($A7="","",--AND(Itineraries!$E7>=Filter_Options!$G$15,Itineraries!$E7<=Filter_Options!$H$15)) | Q7: =IF($A7="","",--AND(Itineraries!$E7>=Filter_Options!$G$16,Itineraries!$E7<=Filter_Options!$H$16)) | R7: =IF($A7="","",--AND(Itineraries!$E7>=Filter_Options!$G$17,Itineraries!$E7<=Filter_Options!$H$17)) | S7: =IF($A7="","",--AND(Itineraries!$E7>=Filter_Options!$G$18,Itineraries!$E7<=Filter_Options!$H$18)) | T7: =IF($A7="","",--AND(Itineraries!$E7>=Filter_Options!$G$19,Itineraries!$E7<=Filter_Options!$H$19)) | U7: =IF($A7="","",--((IF(Filter_Options!$I$20="",0,COUNTIFS(Itinerary_Tags!$A:$A,$A7,Itinerary_Tags!$B:$B,Filter_Options!$I$20))+IF(Filter_Options!$J$20="",0,COUNTIFS(Itinerary_Tags!$A:$A,$A7,Itinerary_Tags!$B:$B,Filter_Options!$J$20))+IF(Filter_Options!$K$20="",0,COUNTIFS(Itinerary_Tags!$A:$A,$A7,Itinerary_Tags!$B:$B,Filter_Options!$K$20)))>0)) | V7: =IF($A7="","",--((IF(Filter_Options!$I$21="",0,COUNTIFS(Itinerary_Tags!$A:$A,$A7,Itinerary_Tags!$B:$B,Filter_Options!$I$21))+IF(Filter_Options!$J$21="",0,COUNTIFS(Itinerary_Tags!$A:$A,$A7,Itinerary_Tags!$B:$B,Filter_Options!$J$21))+IF(Filter_Options!$K$21="",0,COUNTIFS(Itinerary_Tags!$A:$A,$A7,Itinerary_Tags!$B:$B,Filter_Options!$K$21)))>0)) | W7: =IF($A7="","",--((IF(Filter_Options!$I$22="",0,COUNTIFS(Itinerary_Tags!$A:$A,$A7,Itinerary_Tags!$B:$B,Filter_Options!$I$22))+IF(Filter_Options!$J$22="",0,COUNTIFS(Itinerary_Tags!$A:$A,$A7,Itinerary_Tags!$B:$B,Filter_Options!$J$22))+IF(Filter_Options!$K$22="",0,COUNTIFS(Itinerary_Tags!$A:$A,$A7,Itinerary_Tags!$B:$B,Filter_Options!$K$22)))>0)) | X7: =IF($A7="","",--((IF(Filter_Options!$I$23="",0,COUNTIFS(Itinerary_Tags!$A:$A,$A7,Itinerary_Tags!$B:$B,Filter_Options!$I$23))+IF(Filter_Options!$J$23="",0,COUNTIFS(Itinerary_Tags!$A:$A,$A7,Itinerary_Tags!$B:$B,Filter_Options!$J$23))+IF(Filter_Options!$K$23="",0,COUNTIFS(Itinerary_Tags!$A:$A,$A7,Itinerary_Tags!$B:$B,Filter_Options!$K$23)))>0)) | Y7: =IF($A7="","",--((IF(Filter_Options!$I$24="",0,COUNTIFS(Itinerary_Tags!$A:$A,$A7,Itinerary_Tags!$B:$B,Filter_Options!$I$24))+IF(Filter_Options!$J$24="",0,COUNTIFS(Itinerary_Tags!$A:$A,$A7,Itinerary_Tags!$B:$B,Filter_Options!$J$24))+IF(Filter_Options!$K$24="",0,COUNTIFS(Itinerary_Tags!$A:$A,$A7,Itinerary_Tags!$B:$B,Filter_Options!$K$24)))>0)) | Z7: =IF($A7="","",--((IF(Filter_Options!$I$25="",0,COUNTIFS(Itinerary_Tags!$A:$A,$A7,Itinerary_Tags!$B:$B,Filter_Options!$I$25))+IF(Filter_Options!$J$25="",0,COUNTIFS(Itinerary_Tags!$A:$A,$A7,Itinerary_Tags!$B:$B,Filter_Options!$J$25))+IF(Filter_Options!$K$25="",0,COUNTIFS(Itinerary_Tags!$A:$A,$A7,Itinerary_Tags!$B:$B,Filter_Options!$K$25)))>0)) | AA7: =IF($A7="","",--((IF(Filter_Options!$I$26="",0,COUNTIFS(Itinerary_Tags!$A:$A,$A7,Itinerary_Tags!$B:$B,Filter_Options!$I$26))+IF(Filter_Options!$J$26="",0,COUNTIFS(Itinerary_Tags!$A:$A,$A7,Itinerary_Tags!$B:$B,Filter_Options!$J$26))+IF(Filter_Options!$K$26="",0,COUNTIFS(Itinerary_Tags!$A:$A,$A7,Itinerary_Tags!$B:$B,Filter_Options!$K$26)))>0)) | AB7: =IF($A7="","",--((IF(Filter_Options!$I$27="",0,COUNTIFS(Itinerary_Tags!$A:$A,$A7,Itinerary_Tags!$B:$B,Filter_Options!$I$27))+IF(Filter_Options!$J$27="",0,COUNTIFS(Itinerary_Tags!$A:$A,$A7,Itinerary_Tags!$B:$B,Filter_Options!$J$27))+IF(Filter_Options!$K$27="",0,COUNTIFS(Itinerary_Tags!$A:$A,$A7,Itinerary_Tags!$B:$B,Filter_Options!$K$27)))>0)) | AC7: =IF($A7="","",--((IF(Filter_Options!$I$28="",0,COUNTIFS(Itinerary_Tags!$A:$A,$A7,Itinerary_Tags!$B:$B,Filter_Options!$I$28))+IF(Filter_Options!$J$28="",0,COUNTIFS(Itinerary_Tags!$A:$A,$A7,Itinerary_Tags!$B:$B,Filter_Options!$J$28))+IF(Filter_Options!$K$28="",0,COUNTIFS(Itinerary_Tags!$A:$A,$A7,Itinerary_Tags!$B:$B,Filter_Options!$K$28)))>0)) | AD7: =IF($A7="","",--((IF(Filter_Options!$I$29="",0,COUNTIFS(Itinerary_Tags!$A:$A,$A7,Itinerary_Tags!$B:$B,Filter_Options!$I$29))+IF(Filter_Options!$J$29="",0,COUNTIFS(Itinerary_Tags!$A:$A,$A7,Itinerary_Tags!$B:$B,Filter_Options!$J$29))+IF(Filter_Options!$K$29="",0,COUNTIFS(Itinerary_Tags!$A:$A,$A7,Itinerary_Tags!$B:$B,Filter_Options!$K$29)))>0)) | AE7: =IF($A7="","",--((IF(Filter_Options!$I$30="",0,COUNTIFS(Itinerary_Tags!$A:$A,$A7,Itinerary_Tags!$B:$B,Filter_Options!$I$30))+IF(Filter_Options!$J$30="",0,COUNTIFS(Itinerary_Tags!$A:$A,$A7,Itinerary_Tags!$B:$B,Filter_Options!$J$30))+IF(Filter_Options!$K$30="",0,COUNTIFS(Itinerary_Tags!$A:$A,$A7,Itinerary_Tags!$B:$B,Filter_Options!$K$30)))>0)) | AF7: =IF($A7="","",--((IF(Filter_Options!$I$31="",0,COUNTIFS(Itinerary_Tags!$A:$A,$A7,Itinerary_Tags!$B:$B,Filter_Options!$I$31))+IF(Filter_Options!$J$31="",0,COUNTIFS(Itinerary_Tags!$A:$A,$A7,Itinerary_Tags!$B:$B,Filter_Options!$J$31))+IF(Filter_Options!$K$31="",0,COUNTIFS(Itinerary_Tags!$A:$A,$A7,Itinerary_Tags!$B:$B,Filter_Options!$K$31)))>0)) | AG7: =IF($A7="","",--((IF(Filter_Options!$I$32="",0,COUNTIFS(Itinerary_Tags!$A:$A,$A7,Itinerary_Tags!$B:$B,Filter_Options!$I$32))+IF(Filter_Options!$J$32="",0,COUNTIFS(Itinerary_Tags!$A:$A,$A7,Itinerary_Tags!$B:$B,Filter_Options!$J$32))+IF(Filter_Options!$K$32="",0,COUNTIFS(Itinerary_Tags!$A:$A,$A7,Itinerary_Tags!$B:$B,Filter_Options!$K$32)))>0)) | AH7: =IF($A7="","",--((IF(Filter_Options!$I$33="",0,COUNTIFS(Itinerary_Tags!$A:$A,$A7,Itinerary_Tags!$B:$B,Filter_Options!$I$33))+IF(Filter_Options!$J$33="",0,COUNTIFS(Itinerary_Tags!$A:$A,$A7,Itinerary_Tags!$B:$B,Filter_Options!$J$33))+IF(Filter_Options!$K$33="",0,COUNTIFS(Itinerary_Tags!$A:$A,$A7,Itinerary_Tags!$B:$B,Filter_Options!$K$33)))>0)) | AI7: =IF($A7="","",--((IF(Filter_Options!$I$34="",0,COUNTIFS(Itinerary_Tags!$A:$A,$A7,Itinerary_Tags!$B:$B,Filter_Options!$I$34))+IF(Filter_Options!$J$34="",0,COUNTIFS(Itinerary_Tags!$A:$A,$A7,Itinerary_Tags!$B:$B,Filter_Options!$J$34))+IF(Filter_Options!$K$34="",0,COUNTIFS(Itinerary_Tags!$A:$A,$A7,Itinerary_Tags!$B:$B,Filter_Options!$K$34)))>0)) | AJ7: =IF($A7="","",--((IF(Filter_Options!$I$35="",0,COUNTIFS(Itinerary_Tags!$A:$A,$A7,Itinerary_Tags!$B:$B,Filter_Options!$I$35))+IF(Filter_Options!$J$35="",0,COUNTIFS(Itinerary_Tags!$A:$A,$A7,Itinerary_Tags!$B:$B,Filter_Options!$J$35))+IF(Filter_Options!$K$35="",0,COUNTIFS(Itinerary_Tags!$A:$A,$A7,Itinerary_Tags!$B:$B,Filter_Options!$K$35)))>0)) | AK7: =IF($A7="","",--((IF(Filter_Options!$I$36="",0,COUNTIFS(Itinerary_Tags!$A:$A,$A7,Itinerary_Tags!$B:$B,Filter_Options!$I$36))+IF(Filter_Options!$J$36="",0,COUNTIFS(Itinerary_Tags!$A:$A,$A7,Itinerary_Tags!$B:$B,Filter_Options!$J$36))+IF(Filter_Options!$K$36="",0,COUNTIFS(Itinerary_Tags!$A:$A,$A7,Itinerary_Tags!$B:$B,Filter_Options!$K$36)))>0)) | AL7: =IF($A7="","",--((IF(Filter_Options!$I$37="",0,COUNTIFS(Itinerary_Tags!$A:$A,$A7,Itinerary_Tags!$B:$B,Filter_Options!$I$37))+IF(Filter_Options!$J$37="",0,COUNTIFS(Itinerary_Tags!$A:$A,$A7,Itinerary_Tags!$B:$B,Filter_Options!$J$37))+IF(Filter_Options!$K$37="",0,COUNTIFS(Itinerary_Tags!$A:$A,$A7,Itinerary_Tags!$B:$B,Filter_Options!$K$37)))>0))
A8: =IF(Itineraries!A8="","",Itineraries!A8) | B8: =IF(Itineraries!A8="","",Itineraries!C8) | C8: =IF($A8="","",--(Itineraries!$J8=Filter_Options!$F$2)) | D8: =IF($A8="","",--(Itineraries!$J8=Filter_Options!$F$3)) | E8: =IF($A8="","",--(Itineraries!$J8=Filter_Options!$F$4)) | F8: =IF($A8="","",--(Itineraries!$J8=Filter_Options!$F$5)) | G8: =IF($A8="","",--(Itineraries!$J8=Filter_Options!$F$6)) | H8: =IF($A8="","",--(Itineraries!$J8=Filter_Options!$F$7)) | I8: =IF($A8="","",--AND(Itineraries!$K8<=Filter_Options!$H$8,Itineraries!$L8>=Filter_Options!$G$8)) | J8: =IF($A8="","",--AND(Itineraries!$K8<=Filter_Options!$H$9,Itineraries!$L8>=Filter_Options!$G$9)) | K8: =IF($A8="","",--AND(Itineraries!$K8<=Filter_Options!$H$10,Itineraries!$L8>=Filter_Options!$G$10)) | L8: =IF($A8="","",--AND(Itineraries!$K8<=Filter_Options!$H$11,Itineraries!$L8>=Filter_Options!$G$11)) | M8: =IF($A8="","",--AND(Itineraries!$K8<=Filter_Options!$H$12,Itineraries!$L8>=Filter_Options!$G$12)) | N8: =IF($A8="","",--AND(Itineraries!$K8<=Filter_Options!$H$13,Itineraries!$L8>=Filter_Options!$G$13)) | O8: =IF($A8="","",--AND(Itineraries!$E8>=Filter_Options!$G$14,Itineraries!$E8<=Filter_Options!$H$14)) | P8: =IF($A8="","",--AND(Itineraries!$E8>=Filter_Options!$G$15,Itineraries!$E8<=Filter_Options!$H$15)) | Q8: =IF($A8="","",--AND(Itineraries!$E8>=Filter_Options!$G$16,Itineraries!$E8<=Filter_Options!$H$16)) | R8: =IF($A8="","",--AND(Itineraries!$E8>=Filter_Options!$G$17,Itineraries!$E8<=Filter_Options!$H$17)) | S8: =IF($A8="","",--AND(Itineraries!$E8>=Filter_Options!$G$18,Itineraries!$E8<=Filter_Options!$H$18)) | T8: =IF($A8="","",--AND(Itineraries!$E8>=Filter_Options!$G$19,Itineraries!$E8<=Filter_Options!$H$19)) | U8: =IF($A8="","",--((IF(Filter_Options!$I$20="",0,COUNTIFS(Itinerary_Tags!$A:$A,$A8,Itinerary_Tags!$B:$B,Filter_Options!$I$20))+IF(Filter_Options!$J$20="",0,COUNTIFS(Itinerary_Tags!$A:$A,$A8,Itinerary_Tags!$B:$B,Filter_Options!$J$20))+IF(Filter_Options!$K$20="",0,COUNTIFS(Itinerary_Tags!$A:$A,$A8,Itinerary_Tags!$B:$B,Filter_Options!$K$20)))>0)) | V8: =IF($A8="","",--((IF(Filter_Options!$I$21="",0,COUNTIFS(Itinerary_Tags!$A:$A,$A8,Itinerary_Tags!$B:$B,Filter_Options!$I$21))+IF(Filter_Options!$J$21="",0,COUNTIFS(Itinerary_Tags!$A:$A,$A8,Itinerary_Tags!$B:$B,Filter_Options!$J$21))+IF(Filter_Options!$K$21="",0,COUNTIFS(Itinerary_Tags!$A:$A,$A8,Itinerary_Tags!$B:$B,Filter_Options!$K$21)))>0)) | W8: =IF($A8="","",--((IF(Filter_Options!$I$22="",0,COUNTIFS(Itinerary_Tags!$A:$A,$A8,Itinerary_Tags!$B:$B,Filter_Options!$I$22))+IF(Filter_Options!$J$22="",0,COUNTIFS(Itinerary_Tags!$A:$A,$A8,Itinerary_Tags!$B:$B,Filter_Options!$J$22))+IF(Filter_Options!$K$22="",0,COUNTIFS(Itinerary_Tags!$A:$A,$A8,Itinerary_Tags!$B:$B,Filter_Options!$K$22)))>0)) | X8: =IF($A8="","",--((IF(Filter_Options!$I$23="",0,COUNTIFS(Itinerary_Tags!$A:$A,$A8,Itinerary_Tags!$B:$B,Filter_Options!$I$23))+IF(Filter_Options!$J$23="",0,COUNTIFS(Itinerary_Tags!$A:$A,$A8,Itinerary_Tags!$B:$B,Filter_Options!$J$23))+IF(Filter_Options!$K$23="",0,COUNTIFS(Itinerary_Tags!$A:$A,$A8,Itinerary_Tags!$B:$B,Filter_Options!$K$23)))>0)) | Y8: =IF($A8="","",--((IF(Filter_Options!$I$24="",0,COUNTIFS(Itinerary_Tags!$A:$A,$A8,Itinerary_Tags!$B:$B,Filter_Options!$I$24))+IF(Filter_Options!$J$24="",0,COUNTIFS(Itinerary_Tags!$A:$A,$A8,Itinerary_Tags!$B:$B,Filter_Options!$J$24))+IF(Filter_Options!$K$24="",0,COUNTIFS(Itinerary_Tags!$A:$A,$A8,Itinerary_Tags!$B:$B,Filter_Options!$K$24)))>0)) | Z8: =IF($A8="","",--((IF(Filter_Options!$I$25="",0,COUNTIFS(Itinerary_Tags!$A:$A,$A8,Itinerary_Tags!$B:$B,Filter_Options!$I$25))+IF(Filter_Options!$J$25="",0,COUNTIFS(Itinerary_Tags!$A:$A,$A8,Itinerary_Tags!$B:$B,Filter_Options!$J$25))+IF(Filter_Options!$K$25="",0,COUNTIFS(Itinerary_Tags!$A:$A,$A8,Itinerary_Tags!$B:$B,Filter_Options!$K$25)))>0)) | AA8: =IF($A8="","",--((IF(Filter_Options!$I$26="",0,COUNTIFS(Itinerary_Tags!$A:$A,$A8,Itinerary_Tags!$B:$B,Filter_Options!$I$26))+IF(Filter_Options!$J$26="",0,COUNTIFS(Itinerary_Tags!$A:$A,$A8,Itinerary_Tags!$B:$B,Filter_Options!$J$26))+IF(Filter_Options!$K$26="",0,COUNTIFS(Itinerary_Tags!$A:$A,$A8,Itinerary_Tags!$B:$B,Filter_Options!$K$26)))>0)) | AB8: =IF($A8="","",--((IF(Filter_Options!$I$27="",0,COUNTIFS(Itinerary_Tags!$A:$A,$A8,Itinerary_Tags!$B:$B,Filter_Options!$I$27))+IF(Filter_Options!$J$27="",0,COUNTIFS(Itinerary_Tags!$A:$A,$A8,Itinerary_Tags!$B:$B,Filter_Options!$J$27))+IF(Filter_Options!$K$27="",0,COUNTIFS(Itinerary_Tags!$A:$A,$A8,Itinerary_Tags!$B:$B,Filter_Options!$K$27)))>0)) | AC8: =IF($A8="","",--((IF(Filter_Options!$I$28="",0,COUNTIFS(Itinerary_Tags!$A:$A,$A8,Itinerary_Tags!$B:$B,Filter_Options!$I$28))+IF(Filter_Options!$J$28="",0,COUNTIFS(Itinerary_Tags!$A:$A,$A8,Itinerary_Tags!$B:$B,Filter_Options!$J$28))+IF(Filter_Options!$K$28="",0,COUNTIFS(Itinerary_Tags!$A:$A,$A8,Itinerary_Tags!$B:$B,Filter_Options!$K$28)))>0)) | AD8: =IF($A8="","",--((IF(Filter_Options!$I$29="",0,COUNTIFS(Itinerary_Tags!$A:$A,$A8,Itinerary_Tags!$B:$B,Filter_Options!$I$29))+IF(Filter_Options!$J$29="",0,COUNTIFS(Itinerary_Tags!$A:$A,$A8,Itinerary_Tags!$B:$B,Filter_Options!$J$29))+IF(Filter_Options!$K$29="",0,COUNTIFS(Itinerary_Tags!$A:$A,$A8,Itinerary_Tags!$B:$B,Filter_Options!$K$29)))>0)) | AE8: =IF($A8="","",--((IF(Filter_Options!$I$30="",0,COUNTIFS(Itinerary_Tags!$A:$A,$A8,Itinerary_Tags!$B:$B,Filter_Options!$I$30))+IF(Filter_Options!$J$30="",0,COUNTIFS(Itinerary_Tags!$A:$A,$A8,Itinerary_Tags!$B:$B,Filter_Options!$J$30))+IF(Filter_Options!$K$30="",0,COUNTIFS(Itinerary_Tags!$A:$A,$A8,Itinerary_Tags!$B:$B,Filter_Options!$K$30)))>0)) | AF8: =IF($A8="","",--((IF(Filter_Options!$I$31="",0,COUNTIFS(Itinerary_Tags!$A:$A,$A8,Itinerary_Tags!$B:$B,Filter_Options!$I$31))+IF(Filter_Options!$J$31="",0,COUNTIFS(Itinerary_Tags!$A:$A,$A8,Itinerary_Tags!$B:$B,Filter_Options!$J$31))+IF(Filter_Options!$K$31="",0,COUNTIFS(Itinerary_Tags!$A:$A,$A8,Itinerary_Tags!$B:$B,Filter_Options!$K$31)))>0)) | AG8: =IF($A8="","",--((IF(Filter_Options!$I$32="",0,COUNTIFS(Itinerary_Tags!$A:$A,$A8,Itinerary_Tags!$B:$B,Filter_Options!$I$32))+IF(Filter_Options!$J$32="",0,COUNTIFS(Itinerary_Tags!$A:$A,$A8,Itinerary_Tags!$B:$B,Filter_Options!$J$32))+IF(Filter_Options!$K$32="",0,COUNTIFS(Itinerary_Tags!$A:$A,$A8,Itinerary_Tags!$B:$B,Filter_Options!$K$32)))>0)) | AH8: =IF($A8="","",--((IF(Filter_Options!$I$33="",0,COUNTIFS(Itinerary_Tags!$A:$A,$A8,Itinerary_Tags!$B:$B,Filter_Options!$I$33))+IF(Filter_Options!$J$33="",0,COUNTIFS(Itinerary_Tags!$A:$A,$A8,Itinerary_Tags!$B:$B,Filter_Options!$J$33))+IF(Filter_Options!$K$33="",0,COUNTIFS(Itinerary_Tags!$A:$A,$A8,Itinerary_Tags!$B:$B,Filter_Options!$K$33)))>0)) | AI8: =IF($A8="","",--((IF(Filter_Options!$I$34="",0,COUNTIFS(Itinerary_Tags!$A:$A,$A8,Itinerary_Tags!$B:$B,Filter_Options!$I$34))+IF(Filter_Options!$J$34="",0,COUNTIFS(Itinerary_Tags!$A:$A,$A8,Itinerary_Tags!$B:$B,Filter_Options!$J$34))+IF(Filter_Options!$K$34="",0,COUNTIFS(Itinerary_Tags!$A:$A,$A8,Itinerary_Tags!$B:$B,Filter_Options!$K$34)))>0)) | AJ8: =IF($A8="","",--((IF(Filter_Options!$I$35="",0,COUNTIFS(Itinerary_Tags!$A:$A,$A8,Itinerary_Tags!$B:$B,Filter_Options!$I$35))+IF(Filter_Options!$J$35="",0,COUNTIFS(Itinerary_Tags!$A:$A,$A8,Itinerary_Tags!$B:$B,Filter_Options!$J$35))+IF(Filter_Options!$K$35="",0,COUNTIFS(Itinerary_Tags!$A:$A,$A8,Itinerary_Tags!$B:$B,Filter_Options!$K$35)))>0)) | AK8: =IF($A8="","",--((IF(Filter_Options!$I$36="",0,COUNTIFS(Itinerary_Tags!$A:$A,$A8,Itinerary_Tags!$B:$B,Filter_Options!$I$36))+IF(Filter_Options!$J$36="",0,COUNTIFS(Itinerary_Tags!$A:$A,$A8,Itinerary_Tags!$B:$B,Filter_Options!$J$36))+IF(Filter_Options!$K$36="",0,COUNTIFS(Itinerary_Tags!$A:$A,$A8,Itinerary_Tags!$B:$B,Filter_Options!$K$36)))>0)) | AL8: =IF($A8="","",--((IF(Filter_Options!$I$37="",0,COUNTIFS(Itinerary_Tags!$A:$A,$A8,Itinerary_Tags!$B:$B,Filter_Options!$I$37))+IF(Filter_Options!$J$37="",0,COUNTIFS(Itinerary_Tags!$A:$A,$A8,Itinerary_Tags!$B:$B,Filter_Options!$J$37))+IF(Filter_Options!$K$37="",0,COUNTIFS(Itinerary_Tags!$A:$A,$A8,Itinerary_Tags!$B:$B,Filter_Options!$K$37)))>0))
A9: =IF(Itineraries!A9="","",Itineraries!A9) | B9: =IF(Itineraries!A9="","",Itineraries!C9) | C9: =IF($A9="","",--(Itineraries!$J9=Filter_Options!$F$2)) | D9: =IF($A9="","",--(Itineraries!$J9=Filter_Options!$F$3)) | E9: =IF($A9="","",--(Itineraries!$J9=Filter_Options!$F$4)) | F9: =IF($A9="","",--(Itineraries!$J9=Filter_Options!$F$5)) | G9: =IF($A9="","",--(Itineraries!$J9=Filter_Options!$F$6)) | H9: =IF($A9="","",--(Itineraries!$J9=Filter_Options!$F$7)) | I9: =IF($A9="","",--AND(Itineraries!$K9<=Filter_Options!$H$8,Itineraries!$L9>=Filter_Options!$G$8)) | J9: =IF($A9="","",--AND(Itineraries!$K9<=Filter_Options!$H$9,Itineraries!$L9>=Filter_Options!$G$9)) | K9: =IF($A9="","",--AND(Itineraries!$K9<=Filter_Options!$H$10,Itineraries!$L9>=Filter_Options!$G$10)) | L9: =IF($A9="","",--AND(Itineraries!$K9<=Filter_Options!$H$11,Itineraries!$L9>=Filter_Options!$G$11)) | M9: =IF($A9="","",--AND(Itineraries!$K9<=Filter_Options!$H$12,Itineraries!$L9>=Filter_Options!$G$12)) | N9: =IF($A9="","",--AND(Itineraries!$K9<=Filter_Options!$H$13,Itineraries!$L9>=Filter_Options!$G$13)) | O9: =IF($A9="","",--AND(Itineraries!$E9>=Filter_Options!$G$14,Itineraries!$E9<=Filter_Options!$H$14)) | P9: =IF($A9="","",--AND(Itineraries!$E9>=Filter_Options!$G$15,Itineraries!$E9<=Filter_Options!$H$15)) | Q9: =IF($A9="","",--AND(Itineraries!$E9>=Filter_Options!$G$16,Itineraries!$E9<=Filter_Options!$H$16)) | R9: =IF($A9="","",--AND(Itineraries!$E9>=Filter_Options!$G$17,Itineraries!$E9<=Filter_Options!$H$17)) | S9: =IF($A9="","",--AND(Itineraries!$E9>=Filter_Options!$G$18,Itineraries!$E9<=Filter_Options!$H$18)) | T9: =IF($A9="","",--AND(Itineraries!$E9>=Filter_Options!$G$19,Itineraries!$E9<=Filter_Options!$H$19)) | U9: =IF($A9="","",--((IF(Filter_Options!$I$20="",0,COUNTIFS(Itinerary_Tags!$A:$A,$A9,Itinerary_Tags!$B:$B,Filter_Options!$I$20))+IF(Filter_Options!$J$20="",0,COUNTIFS(Itinerary_Tags!$A:$A,$A9,Itinerary_Tags!$B:$B,Filter_Options!$J$20))+IF(Filter_Options!$K$20="",0,COUNTIFS(Itinerary_Tags!$A:$A,$A9,Itinerary_Tags!$B:$B,Filter_Options!$K$20)))>0)) | V9: =IF($A9="","",--((IF(Filter_Options!$I$21="",0,COUNTIFS(Itinerary_Tags!$A:$A,$A9,Itinerary_Tags!$B:$B,Filter_Options!$I$21))+IF(Filter_Options!$J$21="",0,COUNTIFS(Itinerary_Tags!$A:$A,$A9,Itinerary_Tags!$B:$B,Filter_Options!$J$21))+IF(Filter_Options!$K$21="",0,COUNTIFS(Itinerary_Tags!$A:$A,$A9,Itinerary_Tags!$B:$B,Filter_Options!$K$21)))>0)) | W9: =IF($A9="","",--((IF(Filter_Options!$I$22="",0,COUNTIFS(Itinerary_Tags!$A:$A,$A9,Itinerary_Tags!$B:$B,Filter_Options!$I$22))+IF(Filter_Options!$J$22="",0,COUNTIFS(Itinerary_Tags!$A:$A,$A9,Itinerary_Tags!$B:$B,Filter_Options!$J$22))+IF(Filter_Options!$K$22="",0,COUNTIFS(Itinerary_Tags!$A:$A,$A9,Itinerary_Tags!$B:$B,Filter_Options!$K$22)))>0)) | X9: =IF($A9="","",--((IF(Filter_Options!$I$23="",0,COUNTIFS(Itinerary_Tags!$A:$A,$A9,Itinerary_Tags!$B:$B,Filter_Options!$I$23))+IF(Filter_Options!$J$23="",0,COUNTIFS(Itinerary_Tags!$A:$A,$A9,Itinerary_Tags!$B:$B,Filter_Options!$J$23))+IF(Filter_Options!$K$23="",0,COUNTIFS(Itinerary_Tags!$A:$A,$A9,Itinerary_Tags!$B:$B,Filter_Options!$K$23)))>0)) | Y9: =IF($A9="","",--((IF(Filter_Options!$I$24="",0,COUNTIFS(Itinerary_Tags!$A:$A,$A9,Itinerary_Tags!$B:$B,Filter_Options!$I$24))+IF(Filter_Options!$J$24="",0,COUNTIFS(Itinerary_Tags!$A:$A,$A9,Itinerary_Tags!$B:$B,Filter_Options!$J$24))+IF(Filter_Options!$K$24="",0,COUNTIFS(Itinerary_Tags!$A:$A,$A9,Itinerary_Tags!$B:$B,Filter_Options!$K$24)))>0)) | Z9: =IF($A9="","",--((IF(Filter_Options!$I$25="",0,COUNTIFS(Itinerary_Tags!$A:$A,$A9,Itinerary_Tags!$B:$B,Filter_Options!$I$25))+IF(Filter_Options!$J$25="",0,COUNTIFS(Itinerary_Tags!$A:$A,$A9,Itinerary_Tags!$B:$B,Filter_Options!$J$25))+IF(Filter_Options!$K$25="",0,COUNTIFS(Itinerary_Tags!$A:$A,$A9,Itinerary_Tags!$B:$B,Filter_Options!$K$25)))>0)) | AA9: =IF($A9="","",--((IF(Filter_Options!$I$26="",0,COUNTIFS(Itinerary_Tags!$A:$A,$A9,Itinerary_Tags!$B:$B,Filter_Options!$I$26))+IF(Filter_Options!$J$26="",0,COUNTIFS(Itinerary_Tags!$A:$A,$A9,Itinerary_Tags!$B:$B,Filter_Options!$J$26))+IF(Filter_Options!$K$26="",0,COUNTIFS(Itinerary_Tags!$A:$A,$A9,Itinerary_Tags!$B:$B,Filter_Options!$K$26)))>0)) | AB9: =IF($A9="","",--((IF(Filter_Options!$I$27="",0,COUNTIFS(Itinerary_Tags!$A:$A,$A9,Itinerary_Tags!$B:$B,Filter_Options!$I$27))+IF(Filter_Options!$J$27="",0,COUNTIFS(Itinerary_Tags!$A:$A,$A9,Itinerary_Tags!$B:$B,Filter_Options!$J$27))+IF(Filter_Options!$K$27="",0,COUNTIFS(Itinerary_Tags!$A:$A,$A9,Itinerary_Tags!$B:$B,Filter_Options!$K$27)))>0)) | AC9: =IF($A9="","",--((IF(Filter_Options!$I$28="",0,COUNTIFS(Itinerary_Tags!$A:$A,$A9,Itinerary_Tags!$B:$B,Filter_Options!$I$28))+IF(Filter_Options!$J$28="",0,COUNTIFS(Itinerary_Tags!$A:$A,$A9,Itinerary_Tags!$B:$B,Filter_Options!$J$28))+IF(Filter_Options!$K$28="",0,COUNTIFS(Itinerary_Tags!$A:$A,$A9,Itinerary_Tags!$B:$B,Filter_Options!$K$28)))>0)) | AD9: =IF($A9="","",--((IF(Filter_Options!$I$29="",0,COUNTIFS(Itinerary_Tags!$A:$A,$A9,Itinerary_Tags!$B:$B,Filter_Options!$I$29))+IF(Filter_Options!$J$29="",0,COUNTIFS(Itinerary_Tags!$A:$A,$A9,Itinerary_Tags!$B:$B,Filter_Options!$J$29))+IF(Filter_Options!$K$29="",0,COUNTIFS(Itinerary_Tags!$A:$A,$A9,Itinerary_Tags!$B:$B,Filter_Options!$K$29)))>0)) | AE9: =IF($A9="","",--((IF(Filter_Options!$I$30="",0,COUNTIFS(Itinerary_Tags!$A:$A,$A9,Itinerary_Tags!$B:$B,Filter_Options!$I$30))+IF(Filter_Options!$J$30="",0,COUNTIFS(Itinerary_Tags!$A:$A,$A9,Itinerary_Tags!$B:$B,Filter_Options!$J$30))+IF(Filter_Options!$K$30="",0,COUNTIFS(Itinerary_Tags!$A:$A,$A9,Itinerary_Tags!$B:$B,Filter_Options!$K$30)))>0)) | AF9: =IF($A9="","",--((IF(Filter_Options!$I$31="",0,COUNTIFS(Itinerary_Tags!$A:$A,$A9,Itinerary_Tags!$B:$B,Filter_Options!$I$31))+IF(Filter_Options!$J$31="",0,COUNTIFS(Itinerary_Tags!$A:$A,$A9,Itinerary_Tags!$B:$B,Filter_Options!$J$31))+IF(Filter_Options!$K$31="",0,COUNTIFS(Itinerary_Tags!$A:$A,$A9,Itinerary_Tags!$B:$B,Filter_Options!$K$31)))>0)) | AG9: =IF($A9="","",--((IF(Filter_Options!$I$32="",0,COUNTIFS(Itinerary_Tags!$A:$A,$A9,Itinerary_Tags!$B:$B,Filter_Options!$I$32))+IF(Filter_Options!$J$32="",0,COUNTIFS(Itinerary_Tags!$A:$A,$A9,Itinerary_Tags!$B:$B,Filter_Options!$J$32))+IF(Filter_Options!$K$32="",0,COUNTIFS(Itinerary_Tags!$A:$A,$A9,Itinerary_Tags!$B:$B,Filter_Options!$K$32)))>0)) | AH9: =IF($A9="","",--((IF(Filter_Options!$I$33="",0,COUNTIFS(Itinerary_Tags!$A:$A,$A9,Itinerary_Tags!$B:$B,Filter_Options!$I$33))+IF(Filter_Options!$J$33="",0,COUNTIFS(Itinerary_Tags!$A:$A,$A9,Itinerary_Tags!$B:$B,Filter_Options!$J$33))+IF(Filter_Options!$K$33="",0,COUNTIFS(Itinerary_Tags!$A:$A,$A9,Itinerary_Tags!$B:$B,Filter_Options!$K$33)))>0)) | AI9: =IF($A9="","",--((IF(Filter_Options!$I$34="",0,COUNTIFS(Itinerary_Tags!$A:$A,$A9,Itinerary_Tags!$B:$B,Filter_Options!$I$34))+IF(Filter_Options!$J$34="",0,COUNTIFS(Itinerary_Tags!$A:$A,$A9,Itinerary_Tags!$B:$B,Filter_Options!$J$34))+IF(Filter_Options!$K$34="",0,COUNTIFS(Itinerary_Tags!$A:$A,$A9,Itinerary_Tags!$B:$B,Filter_Options!$K$34)))>0)) | AJ9: =IF($A9="","",--((IF(Filter_Options!$I$35="",0,COUNTIFS(Itinerary_Tags!$A:$A,$A9,Itinerary_Tags!$B:$B,Filter_Options!$I$35))+IF(Filter_Options!$J$35="",0,COUNTIFS(Itinerary_Tags!$A:$A,$A9,Itinerary_Tags!$B:$B,Filter_Options!$J$35))+IF(Filter_Options!$K$35="",0,COUNTIFS(Itinerary_Tags!$A:$A,$A9,Itinerary_Tags!$B:$B,Filter_Options!$K$35)))>0)) | AK9: =IF($A9="","",--((IF(Filter_Options!$I$36="",0,COUNTIFS(Itinerary_Tags!$A:$A,$A9,Itinerary_Tags!$B:$B,Filter_Options!$I$36))+IF(Filter_Options!$J$36="",0,COUNTIFS(Itinerary_Tags!$A:$A,$A9,Itinerary_Tags!$B:$B,Filter_Options!$J$36))+IF(Filter_Options!$K$36="",0,COUNTIFS(Itinerary_Tags!$A:$A,$A9,Itinerary_Tags!$B:$B,Filter_Options!$K$36)))>0)) | AL9: =IF($A9="","",--((IF(Filter_Options!$I$37="",0,COUNTIFS(Itinerary_Tags!$A:$A,$A9,Itinerary_Tags!$B:$B,Filter_Options!$I$37))+IF(Filter_Options!$J$37="",0,COUNTIFS(Itinerary_Tags!$A:$A,$A9,Itinerary_Tags!$B:$B,Filter_Options!$J$37))+IF(Filter_Options!$K$37="",0,COUNTIFS(Itinerary_Tags!$A:$A,$A9,Itinerary_Tags!$B:$B,Filter_Options!$K$37)))>0))
A10: =IF(Itineraries!A10="","",Itineraries!A10) | B10: =IF(Itineraries!A10="","",Itineraries!C10) | C10: =IF($A10="","",--(Itineraries!$J10=Filter_Options!$F$2)) | D10: =IF($A10="","",--(Itineraries!$J10=Filter_Options!$F$3)) | E10: =IF($A10="","",--(Itineraries!$J10=Filter_Options!$F$4)) | F10: =IF($A10="","",--(Itineraries!$J10=Filter_Options!$F$5)) | G10: =IF($A10="","",--(Itineraries!$J10=Filter_Options!$F$6)) | H10: =IF($A10="","",--(Itineraries!$J10=Filter_Options!$F$7)) | I10: =IF($A10="","",--AND(Itineraries!$K10<=Filter_Options!$H$8,Itineraries!$L10>=Filter_Options!$G$8)) | J10: =IF($A10="","",--AND(Itineraries!$K10<=Filter_Options!$H$9,Itineraries!$L10>=Filter_Options!$G$9)) | K10: =IF($A10="","",--AND(Itineraries!$K10<=Filter_Options!$H$10,Itineraries!$L10>=Filter_Options!$G$10)) | L10: =IF($A10="","",--AND(Itineraries!$K10<=Filter_Options!$H$11,Itineraries!$L10>=Filter_Options!$G$11)) | M10: =IF($A10="","",--AND(Itineraries!$K10<=Filter_Options!$H$12,Itineraries!$L10>=Filter_Options!$G$12)) | N10: =IF($A10="","",--AND(Itineraries!$K10<=Filter_Options!$H$13,Itineraries!$L10>=Filter_Options!$G$13)) | O10: =IF($A10="","",--AND(Itineraries!$E10>=Filter_Options!$G$14,Itineraries!$E10<=Filter_Options!$H$14)) | P10: =IF($A10="","",--AND(Itineraries!$E10>=Filter_Options!$G$15,Itineraries!$E10<=Filter_Options!$H$15)) | Q10: =IF($A10="","",--AND(Itineraries!$E10>=Filter_Options!$G$16,Itineraries!$E10<=Filter_Options!$H$16)) | R10: =IF($A10="","",--AND(Itineraries!$E10>=Filter_Options!$G$17,Itineraries!$E10<=Filter_Options!$H$17)) | S10: =IF($A10="","",--AND(Itineraries!$E10>=Filter_Options!$G$18,Itineraries!$E10<=Filter_Options!$H$18)) | T10: =IF($A10="","",--AND(Itineraries!$E10>=Filter_Options!$G$19,Itineraries!$E10<=Filter_Options!$H$19)) | U10: =IF($A10="","",--((IF(Filter_Options!$I$20="",0,COUNTIFS(Itinerary_Tags!$A:$A,$A10,Itinerary_Tags!$B:$B,Filter_Options!$I$20))+IF(Filter_Options!$J$20="",0,COUNTIFS(Itinerary_Tags!$A:$A,$A10,Itinerary_Tags!$B:$B,Filter_Options!$J$20))+IF(Filter_Options!$K$20="",0,COUNTIFS(Itinerary_Tags!$A:$A,$A10,Itinerary_Tags!$B:$B,Filter_Options!$K$20)))>0)) | V10: =IF($A10="","",--((IF(Filter_Options!$I$21="",0,COUNTIFS(Itinerary_Tags!$A:$A,$A10,Itinerary_Tags!$B:$B,Filter_Options!$I$21))+IF(Filter_Options!$J$21="",0,COUNTIFS(Itinerary_Tags!$A:$A,$A10,Itinerary_Tags!$B:$B,Filter_Options!$J$21))+IF(Filter_Options!$K$21="",0,COUNTIFS(Itinerary_Tags!$A:$A,$A10,Itinerary_Tags!$B:$B,Filter_Options!$K$21)))>0)) | W10: =IF($A10="","",--((IF(Filter_Options!$I$22="",0,COUNTIFS(Itinerary_Tags!$A:$A,$A10,Itinerary_Tags!$B:$B,Filter_Options!$I$22))+IF(Filter_Options!$J$22="",0,COUNTIFS(Itinerary_Tags!$A:$A,$A10,Itinerary_Tags!$B:$B,Filter_Options!$J$22))+IF(Filter_Options!$K$22="",0,COUNTIFS(Itinerary_Tags!$A:$A,$A10,Itinerary_Tags!$B:$B,Filter_Options!$K$22)))>0)) | X10: =IF($A10="","",--((IF(Filter_Options!$I$23="",0,COUNTIFS(Itinerary_Tags!$A:$A,$A10,Itinerary_Tags!$B:$B,Filter_Options!$I$23))+IF(Filter_Options!$J$23="",0,COUNTIFS(Itinerary_Tags!$A:$A,$A10,Itinerary_Tags!$B:$B,Filter_Options!$J$23))+IF(Filter_Options!$K$23="",0,COUNTIFS(Itinerary_Tags!$A:$A,$A10,Itinerary_Tags!$B:$B,Filter_Options!$K$23)))>0)) | Y10: =IF($A10="","",--((IF(Filter_Options!$I$24="",0,COUNTIFS(Itinerary_Tags!$A:$A,$A10,Itinerary_Tags!$B:$B,Filter_Options!$I$24))+IF(Filter_Options!$J$24="",0,COUNTIFS(Itinerary_Tags!$A:$A,$A10,Itinerary_Tags!$B:$B,Filter_Options!$J$24))+IF(Filter_Options!$K$24="",0,COUNTIFS(Itinerary_Tags!$A:$A,$A10,Itinerary_Tags!$B:$B,Filter_Options!$K$24)))>0)) | Z10: =IF($A10="","",--((IF(Filter_Options!$I$25="",0,COUNTIFS(Itinerary_Tags!$A:$A,$A10,Itinerary_Tags!$B:$B,Filter_Options!$I$25))+IF(Filter_Options!$J$25="",0,COUNTIFS(Itinerary_Tags!$A:$A,$A10,Itinerary_Tags!$B:$B,Filter_Options!$J$25))+IF(Filter_Options!$K$25="",0,COUNTIFS(Itinerary_Tags!$A:$A,$A10,Itinerary_Tags!$B:$B,Filter_Options!$K$25)))>0)) | AA10: =IF($A10="","",--((IF(Filter_Options!$I$26="",0,COUNTIFS(Itinerary_Tags!$A:$A,$A10,Itinerary_Tags!$B:$B,Filter_Options!$I$26))+IF(Filter_Options!$J$26="",0,COUNTIFS(Itinerary_Tags!$A:$A,$A10,Itinerary_Tags!$B:$B,Filter_Options!$J$26))+IF(Filter_Options!$K$26="",0,COUNTIFS(Itinerary_Tags!$A:$A,$A10,Itinerary_Tags!$B:$B,Filter_Options!$K$26)))>0)) | AB10: =IF($A10="","",--((IF(Filter_Options!$I$27="",0,COUNTIFS(Itinerary_Tags!$A:$A,$A10,Itinerary_Tags!$B:$B,Filter_Options!$I$27))+IF(Filter_Options!$J$27="",0,COUNTIFS(Itinerary_Tags!$A:$A,$A10,Itinerary_Tags!$B:$B,Filter_Options!$J$27))+IF(Filter_Options!$K$27="",0,COUNTIFS(Itinerary_Tags!$A:$A,$A10,Itinerary_Tags!$B:$B,Filter_Options!$K$27)))>0)) | AC10: =IF($A10="","",--((IF(Filter_Options!$I$28="",0,COUNTIFS(Itinerary_Tags!$A:$A,$A10,Itinerary_Tags!$B:$B,Filter_Options!$I$28))+IF(Filter_Options!$J$28="",0,COUNTIFS(Itinerary_Tags!$A:$A,$A10,Itinerary_Tags!$B:$B,Filter_Options!$J$28))+IF(Filter_Options!$K$28="",0,COUNTIFS(Itinerary_Tags!$A:$A,$A10,Itinerary_Tags!$B:$B,Filter_Options!$K$28)))>0)) | AD10: =IF($A10="","",--((IF(Filter_Options!$I$29="",0,COUNTIFS(Itinerary_Tags!$A:$A,$A10,Itinerary_Tags!$B:$B,Filter_Options!$I$29))+IF(Filter_Options!$J$29="",0,COUNTIFS(Itinerary_Tags!$A:$A,$A10,Itinerary_Tags!$B:$B,Filter_Options!$J$29))+IF(Filter_Options!$K$29="",0,COUNTIFS(Itinerary_Tags!$A:$A,$A10,Itinerary_Tags!$B:$B,Filter_Options!$K$29)))>0)) | AE10: =IF($A10="","",--((IF(Filter_Options!$I$30="",0,COUNTIFS(Itinerary_Tags!$A:$A,$A10,Itinerary_Tags!$B:$B,Filter_Options!$I$30))+IF(Filter_Options!$J$30="",0,COUNTIFS(Itinerary_Tags!$A:$A,$A10,Itinerary_Tags!$B:$B,Filter_Options!$J$30))+IF(Filter_Options!$K$30="",0,COUNTIFS(Itinerary_Tags!$A:$A,$A10,Itinerary_Tags!$B:$B,Filter_Options!$K$30)))>0)) | AF10: =IF($A10="","",--((IF(Filter_Options!$I$31="",0,COUNTIFS(Itinerary_Tags!$A:$A,$A10,Itinerary_Tags!$B:$B,Filter_Options!$I$31))+IF(Filter_Options!$J$31="",0,COUNTIFS(Itinerary_Tags!$A:$A,$A10,Itinerary_Tags!$B:$B,Filter_Options!$J$31))+IF(Filter_Options!$K$31="",0,COUNTIFS(Itinerary_Tags!$A:$A,$A10,Itinerary_Tags!$B:$B,Filter_Options!$K$31)))>0)) | AG10: =IF($A10="","",--((IF(Filter_Options!$I$32="",0,COUNTIFS(Itinerary_Tags!$A:$A,$A10,Itinerary_Tags!$B:$B,Filter_Options!$I$32))+IF(Filter_Options!$J$32="",0,COUNTIFS(Itinerary_Tags!$A:$A,$A10,Itinerary_Tags!$B:$B,Filter_Options!$J$32))+IF(Filter_Options!$K$32="",0,COUNTIFS(Itinerary_Tags!$A:$A,$A10,Itinerary_Tags!$B:$B,Filter_Options!$K$32)))>0)) | AH10: =IF($A10="","",--((IF(Filter_Options!$I$33="",0,COUNTIFS(Itinerary_Tags!$A:$A,$A10,Itinerary_Tags!$B:$B,Filter_Options!$I$33))+IF(Filter_Options!$J$33="",0,COUNTIFS(Itinerary_Tags!$A:$A,$A10,Itinerary_Tags!$B:$B,Filter_Options!$J$33))+IF(Filter_Options!$K$33="",0,COUNTIFS(Itinerary_Tags!$A:$A,$A10,Itinerary_Tags!$B:$B,Filter_Options!$K$33)))>0)) | AI10: =IF($A10="","",--((IF(Filter_Options!$I$34="",0,COUNTIFS(Itinerary_Tags!$A:$A,$A10,Itinerary_Tags!$B:$B,Filter_Options!$I$34))+IF(Filter_Options!$J$34="",0,COUNTIFS(Itinerary_Tags!$A:$A,$A10,Itinerary_Tags!$B:$B,Filter_Options!$J$34))+IF(Filter_Options!$K$34="",0,COUNTIFS(Itinerary_Tags!$A:$A,$A10,Itinerary_Tags!$B:$B,Filter_Options!$K$34)))>0)) | AJ10: =IF($A10="","",--((IF(Filter_Options!$I$35="",0,COUNTIFS(Itinerary_Tags!$A:$A,$A10,Itinerary_Tags!$B:$B,Filter_Options!$I$35))+IF(Filter_Options!$J$35="",0,COUNTIFS(Itinerary_Tags!$A:$A,$A10,Itinerary_Tags!$B:$B,Filter_Options!$J$35))+IF(Filter_Options!$K$35="",0,COUNTIFS(Itinerary_Tags!$A:$A,$A10,Itinerary_Tags!$B:$B,Filter_Options!$K$35)))>0)) | AK10: =IF($A10="","",--((IF(Filter_Options!$I$36="",0,COUNTIFS(Itinerary_Tags!$A:$A,$A10,Itinerary_Tags!$B:$B,Filter_Options!$I$36))+IF(Filter_Options!$J$36="",0,COUNTIFS(Itinerary_Tags!$A:$A,$A10,Itinerary_Tags!$B:$B,Filter_Options!$J$36))+IF(Filter_Options!$K$36="",0,COUNTIFS(Itinerary_Tags!$A:$A,$A10,Itinerary_Tags!$B:$B,Filter_Options!$K$36)))>0)) | AL10: =IF($A10="","",--((IF(Filter_Options!$I$37="",0,COUNTIFS(Itinerary_Tags!$A:$A,$A10,Itinerary_Tags!$B:$B,Filter_Options!$I$37))+IF(Filter_Options!$J$37="",0,COUNTIFS(Itinerary_Tags!$A:$A,$A10,Itinerary_Tags!$B:$B,Filter_Options!$J$37))+IF(Filter_Options!$K$37="",0,COUNTIFS(Itinerary_Tags!$A:$A,$A10,Itinerary_Tags!$B:$B,Filter_Options!$K$37)))>0))
A11: =IF(Itineraries!A11="","",Itineraries!A11) | B11: =IF(Itineraries!A11="","",Itineraries!C11) | C11: =IF($A11="","",--(Itineraries!$J11=Filter_Options!$F$2)) | D11: =IF($A11="","",--(Itineraries!$J11=Filter_Options!$F$3)) | E11: =IF($A11="","",--(Itineraries!$J11=Filter_Options!$F$4)) | F11: =IF($A11="","",--(Itineraries!$J11=Filter_Options!$F$5)) | G11: =IF($A11="","",--(Itineraries!$J11=Filter_Options!$F$6)) | H11: =IF($A11="","",--(Itineraries!$J11=Filter_Options!$F$7)) | I11: =IF($A11="","",--AND(Itineraries!$K11<=Filter_Options!$H$8,Itineraries!$L11>=Filter_Options!$G$8)) | J11: =IF($A11="","",--AND(Itineraries!$K11<=Filter_Options!$H$9,Itineraries!$L11>=Filter_Options!$G$9)) | K11: =IF($A11="","",--AND(Itineraries!$K11<=Filter_Options!$H$10,Itineraries!$L11>=Filter_Options!$G$10)) | L11: =IF($A11="","",--AND(Itineraries!$K11<=Filter_Options!$H$11,Itineraries!$L11>=Filter_Options!$G$11)) | M11: =IF($A11="","",--AND(Itineraries!$K11<=Filter_Options!$H$12,Itineraries!$L11>=Filter_Options!$G$12)) | N11: =IF($A11="","",--AND(Itineraries!$K11<=Filter_Options!$H$13,Itineraries!$L11>=Filter_Options!$G$13)) | O11: =IF($A11="","",--AND(Itineraries!$E11>=Filter_Options!$G$14,Itineraries!$E11<=Filter_Options!$H$14)) | P11: =IF($A11="","",--AND(Itineraries!$E11>=Filter_Options!$G$15,Itineraries!$E11<=Filter_Options!$H$15)) | Q11: =IF($A11="","",--AND(Itineraries!$E11>=Filter_Options!$G$16,Itineraries!$E11<=Filter_Options!$H$16)) | R11: =IF($A11="","",--AND(Itineraries!$E11>=Filter_Options!$G$17,Itineraries!$E11<=Filter_Options!$H$17)) | S11: =IF($A11="","",--AND(Itineraries!$E11>=Filter_Options!$G$18,Itineraries!$E11<=Filter_Options!$H$18)) | T11: =IF($A11="","",--AND(Itineraries!$E11>=Filter_Options!$G$19,Itineraries!$E11<=Filter_Options!$H$19)) | U11: =IF($A11="","",--((IF(Filter_Options!$I$20="",0,COUNTIFS(Itinerary_Tags!$A:$A,$A11,Itinerary_Tags!$B:$B,Filter_Options!$I$20))+IF(Filter_Options!$J$20="",0,COUNTIFS(Itinerary_Tags!$A:$A,$A11,Itinerary_Tags!$B:$B,Filter_Options!$J$20))+IF(Filter_Options!$K$20="",0,COUNTIFS(Itinerary_Tags!$A:$A,$A11,Itinerary_Tags!$B:$B,Filter_Options!$K$20)))>0)) | V11: =IF($A11="","",--((IF(Filter_Options!$I$21="",0,COUNTIFS(Itinerary_Tags!$A:$A,$A11,Itinerary_Tags!$B:$B,Filter_Options!$I$21))+IF(Filter_Options!$J$21="",0,COUNTIFS(Itinerary_Tags!$A:$A,$A11,Itinerary_Tags!$B:$B,Filter_Options!$J$21))+IF(Filter_Options!$K$21="",0,COUNTIFS(Itinerary_Tags!$A:$A,$A11,Itinerary_Tags!$B:$B,Filter_Options!$K$21)))>0)) | W11: =IF($A11="","",--((IF(Filter_Options!$I$22="",0,COUNTIFS(Itinerary_Tags!$A:$A,$A11,Itinerary_Tags!$B:$B,Filter_Options!$I$22))+IF(Filter_Options!$J$22="",0,COUNTIFS(Itinerary_Tags!$A:$A,$A11,Itinerary_Tags!$B:$B,Filter_Options!$J$22))+IF(Filter_Options!$K$22="",0,COUNTIFS(Itinerary_Tags!$A:$A,$A11,Itinerary_Tags!$B:$B,Filter_Options!$K$22)))>0)) | X11: =IF($A11="","",--((IF(Filter_Options!$I$23="",0,COUNTIFS(Itinerary_Tags!$A:$A,$A11,Itinerary_Tags!$B:$B,Filter_Options!$I$23))+IF(Filter_Options!$J$23="",0,COUNTIFS(Itinerary_Tags!$A:$A,$A11,Itinerary_Tags!$B:$B,Filter_Options!$J$23))+IF(Filter_Options!$K$23="",0,COUNTIFS(Itinerary_Tags!$A:$A,$A11,Itinerary_Tags!$B:$B,Filter_Options!$K$23)))>0)) | Y11: =IF($A11="","",--((IF(Filter_Options!$I$24="",0,COUNTIFS(Itinerary_Tags!$A:$A,$A11,Itinerary_Tags!$B:$B,Filter_Options!$I$24))+IF(Filter_Options!$J$24="",0,COUNTIFS(Itinerary_Tags!$A:$A,$A11,Itinerary_Tags!$B:$B,Filter_Options!$J$24))+IF(Filter_Options!$K$24="",0,COUNTIFS(Itinerary_Tags!$A:$A,$A11,Itinerary_Tags!$B:$B,Filter_Options!$K$24)))>0)) | Z11: =IF($A11="","",--((IF(Filter_Options!$I$25="",0,COUNTIFS(Itinerary_Tags!$A:$A,$A11,Itinerary_Tags!$B:$B,Filter_Options!$I$25))+IF(Filter_Options!$J$25="",0,COUNTIFS(Itinerary_Tags!$A:$A,$A11,Itinerary_Tags!$B:$B,Filter_Options!$J$25))+IF(Filter_Options!$K$25="",0,COUNTIFS(Itinerary_Tags!$A:$A,$A11,Itinerary_Tags!$B:$B,Filter_Options!$K$25)))>0)) | AA11: =IF($A11="","",--((IF(Filter_Options!$I$26="",0,COUNTIFS(Itinerary_Tags!$A:$A,$A11,Itinerary_Tags!$B:$B,Filter_Options!$I$26))+IF(Filter_Options!$J$26="",0,COUNTIFS(Itinerary_Tags!$A:$A,$A11,Itinerary_Tags!$B:$B,Filter_Options!$J$26))+IF(Filter_Options!$K$26="",0,COUNTIFS(Itinerary_Tags!$A:$A,$A11,Itinerary_Tags!$B:$B,Filter_Options!$K$26)))>0)) | AB11: =IF($A11="","",--((IF(Filter_Options!$I$27="",0,COUNTIFS(Itinerary_Tags!$A:$A,$A11,Itinerary_Tags!$B:$B,Filter_Options!$I$27))+IF(Filter_Options!$J$27="",0,COUNTIFS(Itinerary_Tags!$A:$A,$A11,Itinerary_Tags!$B:$B,Filter_Options!$J$27))+IF(Filter_Options!$K$27="",0,COUNTIFS(Itinerary_Tags!$A:$A,$A11,Itinerary_Tags!$B:$B,Filter_Options!$K$27)))>0)) | AC11: =IF($A11="","",--((IF(Filter_Options!$I$28="",0,COUNTIFS(Itinerary_Tags!$A:$A,$A11,Itinerary_Tags!$B:$B,Filter_Options!$I$28))+IF(Filter_Options!$J$28="",0,COUNTIFS(Itinerary_Tags!$A:$A,$A11,Itinerary_Tags!$B:$B,Filter_Options!$J$28))+IF(Filter_Options!$K$28="",0,COUNTIFS(Itinerary_Tags!$A:$A,$A11,Itinerary_Tags!$B:$B,Filter_Options!$K$28)))>0)) | AD11: =IF($A11="","",--((IF(Filter_Options!$I$29="",0,COUNTIFS(Itinerary_Tags!$A:$A,$A11,Itinerary_Tags!$B:$B,Filter_Options!$I$29))+IF(Filter_Options!$J$29="",0,COUNTIFS(Itinerary_Tags!$A:$A,$A11,Itinerary_Tags!$B:$B,Filter_Options!$J$29))+IF(Filter_Options!$K$29="",0,COUNTIFS(Itinerary_Tags!$A:$A,$A11,Itinerary_Tags!$B:$B,Filter_Options!$K$29)))>0)) | AE11: =IF($A11="","",--((IF(Filter_Options!$I$30="",0,COUNTIFS(Itinerary_Tags!$A:$A,$A11,Itinerary_Tags!$B:$B,Filter_Options!$I$30))+IF(Filter_Options!$J$30="",0,COUNTIFS(Itinerary_Tags!$A:$A,$A11,Itinerary_Tags!$B:$B,Filter_Options!$J$30))+IF(Filter_Options!$K$30="",0,COUNTIFS(Itinerary_Tags!$A:$A,$A11,Itinerary_Tags!$B:$B,Filter_Options!$K$30)))>0)) | AF11: =IF($A11="","",--((IF(Filter_Options!$I$31="",0,COUNTIFS(Itinerary_Tags!$A:$A,$A11,Itinerary_Tags!$B:$B,Filter_Options!$I$31))+IF(Filter_Options!$J$31="",0,COUNTIFS(Itinerary_Tags!$A:$A,$A11,Itinerary_Tags!$B:$B,Filter_Options!$J$31))+IF(Filter_Options!$K$31="",0,COUNTIFS(Itinerary_Tags!$A:$A,$A11,Itinerary_Tags!$B:$B,Filter_Options!$K$31)))>0)) | AG11: =IF($A11="","",--((IF(Filter_Options!$I$32="",0,COUNTIFS(Itinerary_Tags!$A:$A,$A11,Itinerary_Tags!$B:$B,Filter_Options!$I$32))+IF(Filter_Options!$J$32="",0,COUNTIFS(Itinerary_Tags!$A:$A,$A11,Itinerary_Tags!$B:$B,Filter_Options!$J$32))+IF(Filter_Options!$K$32="",0,COUNTIFS(Itinerary_Tags!$A:$A,$A11,Itinerary_Tags!$B:$B,Filter_Options!$K$32)))>0)) | AH11: =IF($A11="","",--((IF(Filter_Options!$I$33="",0,COUNTIFS(Itinerary_Tags!$A:$A,$A11,Itinerary_Tags!$B:$B,Filter_Options!$I$33))+IF(Filter_Options!$J$33="",0,COUNTIFS(Itinerary_Tags!$A:$A,$A11,Itinerary_Tags!$B:$B,Filter_Options!$J$33))+IF(Filter_Options!$K$33="",0,COUNTIFS(Itinerary_Tags!$A:$A,$A11,Itinerary_Tags!$B:$B,Filter_Options!$K$33)))>0)) | AI11: =IF($A11="","",--((IF(Filter_Options!$I$34="",0,COUNTIFS(Itinerary_Tags!$A:$A,$A11,Itinerary_Tags!$B:$B,Filter_Options!$I$34))+IF(Filter_Options!$J$34="",0,COUNTIFS(Itinerary_Tags!$A:$A,$A11,Itinerary_Tags!$B:$B,Filter_Options!$J$34))+IF(Filter_Options!$K$34="",0,COUNTIFS(Itinerary_Tags!$A:$A,$A11,Itinerary_Tags!$B:$B,Filter_Options!$K$34)))>0)) | AJ11: =IF($A11="","",--((IF(Filter_Options!$I$35="",0,COUNTIFS(Itinerary_Tags!$A:$A,$A11,Itinerary_Tags!$B:$B,Filter_Options!$I$35))+IF(Filter_Options!$J$35="",0,COUNTIFS(Itinerary_Tags!$A:$A,$A11,Itinerary_Tags!$B:$B,Filter_Options!$J$35))+IF(Filter_Options!$K$35="",0,COUNTIFS(Itinerary_Tags!$A:$A,$A11,Itinerary_Tags!$B:$B,Filter_Options!$K$35)))>0)) | AK11: =IF($A11="","",--((IF(Filter_Options!$I$36="",0,COUNTIFS(Itinerary_Tags!$A:$A,$A11,Itinerary_Tags!$B:$B,Filter_Options!$I$36))+IF(Filter_Options!$J$36="",0,COUNTIFS(Itinerary_Tags!$A:$A,$A11,Itinerary_Tags!$B:$B,Filter_Options!$J$36))+IF(Filter_Options!$K$36="",0,COUNTIFS(Itinerary_Tags!$A:$A,$A11,Itinerary_Tags!$B:$B,Filter_Options!$K$36)))>0)) | AL11: =IF($A11="","",--((IF(Filter_Options!$I$37="",0,COUNTIFS(Itinerary_Tags!$A:$A,$A11,Itinerary_Tags!$B:$B,Filter_Options!$I$37))+IF(Filter_Options!$J$37="",0,COUNTIFS(Itinerary_Tags!$A:$A,$A11,Itinerary_Tags!$B:$B,Filter_Options!$J$37))+IF(Filter_Options!$K$37="",0,COUNTIFS(Itinerary_Tags!$A:$A,$A11,Itinerary_Tags!$B:$B,Filter_Options!$K$37)))>0))
A12: =IF(Itineraries!A12="","",Itineraries!A12) | B12: =IF(Itineraries!A12="","",Itineraries!C12) | C12: =IF($A12="","",--(Itineraries!$J12=Filter_Options!$F$2)) | D12: =IF($A12="","",--(Itineraries!$J12=Filter_Options!$F$3)) | E12: =IF($A12="","",--(Itineraries!$J12=Filter_Options!$F$4)) | F12: =IF($A12="","",--(Itineraries!$J12=Filter_Options!$F$5)) | G12: =IF($A12="","",--(Itineraries!$J12=Filter_Options!$F$6)) | H12: =IF($A12="","",--(Itineraries!$J12=Filter_Options!$F$7)) | I12: =IF($A12="","",--AND(Itineraries!$K12<=Filter_Options!$H$8,Itineraries!$L12>=Filter_Options!$G$8)) | J12: =IF($A12="","",--AND(Itineraries!$K12<=Filter_Options!$H$9,Itineraries!$L12>=Filter_Options!$G$9)) | K12: =IF($A12="","",--AND(Itineraries!$K12<=Filter_Options!$H$10,Itineraries!$L12>=Filter_Options!$G$10)) | L12: =IF($A12="","",--AND(Itineraries!$K12<=Filter_Options!$H$11,Itineraries!$L12>=Filter_Options!$G$11)) | M12: =IF($A12="","",--AND(Itineraries!$K12<=Filter_Options!$H$12,Itineraries!$L12>=Filter_Options!$G$12)) | N12: =IF($A12="","",--AND(Itineraries!$K12<=Filter_Options!$H$13,Itineraries!$L12>=Filter_Options!$G$13)) | O12: =IF($A12="","",--AND(Itineraries!$E12>=Filter_Options!$G$14,Itineraries!$E12<=Filter_Options!$H$14)) | P12: =IF($A12="","",--AND(Itineraries!$E12>=Filter_Options!$G$15,Itineraries!$E12<=Filter_Options!$H$15)) | Q12: =IF($A12="","",--AND(Itineraries!$E12>=Filter_Options!$G$16,Itineraries!$E12<=Filter_Options!$H$16)) | R12: =IF($A12="","",--AND(Itineraries!$E12>=Filter_Options!$G$17,Itineraries!$E12<=Filter_Options!$H$17)) | S12: =IF($A12="","",--AND(Itineraries!$E12>=Filter_Options!$G$18,Itineraries!$E12<=Filter_Options!$H$18)) | T12: =IF($A12="","",--AND(Itineraries!$E12>=Filter_Options!$G$19,Itineraries!$E12<=Filter_Options!$H$19)) | U12: =IF($A12="","",--((IF(Filter_Options!$I$20="",0,COUNTIFS(Itinerary_Tags!$A:$A,$A12,Itinerary_Tags!$B:$B,Filter_Options!$I$20))+IF(Filter_Options!$J$20="",0,COUNTIFS(Itinerary_Tags!$A:$A,$A12,Itinerary_Tags!$B:$B,Filter_Options!$J$20))+IF(Filter_Options!$K$20="",0,COUNTIFS(Itinerary_Tags!$A:$A,$A12,Itinerary_Tags!$B:$B,Filter_Options!$K$20)))>0)) | V12: =IF($A12="","",--((IF(Filter_Options!$I$21="",0,COUNTIFS(Itinerary_Tags!$A:$A,$A12,Itinerary_Tags!$B:$B,Filter_Options!$I$21))+IF(Filter_Options!$J$21="",0,COUNTIFS(Itinerary_Tags!$A:$A,$A12,Itinerary_Tags!$B:$B,Filter_Options!$J$21))+IF(Filter_Options!$K$21="",0,COUNTIFS(Itinerary_Tags!$A:$A,$A12,Itinerary_Tags!$B:$B,Filter_Options!$K$21)))>0)) | W12: =IF($A12="","",--((IF(Filter_Options!$I$22="",0,COUNTIFS(Itinerary_Tags!$A:$A,$A12,Itinerary_Tags!$B:$B,Filter_Options!$I$22))+IF(Filter_Options!$J$22="",0,COUNTIFS(Itinerary_Tags!$A:$A,$A12,Itinerary_Tags!$B:$B,Filter_Options!$J$22))+IF(Filter_Options!$K$22="",0,COUNTIFS(Itinerary_Tags!$A:$A,$A12,Itinerary_Tags!$B:$B,Filter_Options!$K$22)))>0)) | X12: =IF($A12="","",--((IF(Filter_Options!$I$23="",0,COUNTIFS(Itinerary_Tags!$A:$A,$A12,Itinerary_Tags!$B:$B,Filter_Options!$I$23))+IF(Filter_Options!$J$23="",0,COUNTIFS(Itinerary_Tags!$A:$A,$A12,Itinerary_Tags!$B:$B,Filter_Options!$J$23))+IF(Filter_Options!$K$23="",0,COUNTIFS(Itinerary_Tags!$A:$A,$A12,Itinerary_Tags!$B:$B,Filter_Options!$K$23)))>0)) | Y12: =IF($A12="","",--((IF(Filter_Options!$I$24="",0,COUNTIFS(Itinerary_Tags!$A:$A,$A12,Itinerary_Tags!$B:$B,Filter_Options!$I$24))+IF(Filter_Options!$J$24="",0,COUNTIFS(Itinerary_Tags!$A:$A,$A12,Itinerary_Tags!$B:$B,Filter_Options!$J$24))+IF(Filter_Options!$K$24="",0,COUNTIFS(Itinerary_Tags!$A:$A,$A12,Itinerary_Tags!$B:$B,Filter_Options!$K$24)))>0)) | Z12: =IF($A12="","",--((IF(Filter_Options!$I$25="",0,COUNTIFS(Itinerary_Tags!$A:$A,$A12,Itinerary_Tags!$B:$B,Filter_Options!$I$25))+IF(Filter_Options!$J$25="",0,COUNTIFS(Itinerary_Tags!$A:$A,$A12,Itinerary_Tags!$B:$B,Filter_Options!$J$25))+IF(Filter_Options!$K$25="",0,COUNTIFS(Itinerary_Tags!$A:$A,$A12,Itinerary_Tags!$B:$B,Filter_Options!$K$25)))>0)) | AA12: =IF($A12="","",--((IF(Filter_Options!$I$26="",0,COUNTIFS(Itinerary_Tags!$A:$A,$A12,Itinerary_Tags!$B:$B,Filter_Options!$I$26))+IF(Filter_Options!$J$26="",0,COUNTIFS(Itinerary_Tags!$A:$A,$A12,Itinerary_Tags!$B:$B,Filter_Options!$J$26))+IF(Filter_Options!$K$26="",0,COUNTIFS(Itinerary_Tags!$A:$A,$A12,Itinerary_Tags!$B:$B,Filter_Options!$K$26)))>0)) | AB12: =IF($A12="","",--((IF(Filter_Options!$I$27="",0,COUNTIFS(Itinerary_Tags!$A:$A,$A12,Itinerary_Tags!$B:$B,Filter_Options!$I$27))+IF(Filter_Options!$J$27="",0,COUNTIFS(Itinerary_Tags!$A:$A,$A12,Itinerary_Tags!$B:$B,Filter_Options!$J$27))+IF(Filter_Options!$K$27="",0,COUNTIFS(Itinerary_Tags!$A:$A,$A12,Itinerary_Tags!$B:$B,Filter_Options!$K$27)))>0)) | AC12: =IF($A12="","",--((IF(Filter_Options!$I$28="",0,COUNTIFS(Itinerary_Tags!$A:$A,$A12,Itinerary_Tags!$B:$B,Filter_Options!$I$28))+IF(Filter_Options!$J$28="",0,COUNTIFS(Itinerary_Tags!$A:$A,$A12,Itinerary_Tags!$B:$B,Filter_Options!$J$28))+IF(Filter_Options!$K$28="",0,COUNTIFS(Itinerary_Tags!$A:$A,$A12,Itinerary_Tags!$B:$B,Filter_Options!$K$28)))>0)) | AD12: =IF($A12="","",--((IF(Filter_Options!$I$29="",0,COUNTIFS(Itinerary_Tags!$A:$A,$A12,Itinerary_Tags!$B:$B,Filter_Options!$I$29))+IF(Filter_Options!$J$29="",0,COUNTIFS(Itinerary_Tags!$A:$A,$A12,Itinerary_Tags!$B:$B,Filter_Options!$J$29))+IF(Filter_Options!$K$29="",0,COUNTIFS(Itinerary_Tags!$A:$A,$A12,Itinerary_Tags!$B:$B,Filter_Options!$K$29)))>0)) | AE12: =IF($A12="","",--((IF(Filter_Options!$I$30="",0,COUNTIFS(Itinerary_Tags!$A:$A,$A12,Itinerary_Tags!$B:$B,Filter_Options!$I$30))+IF(Filter_Options!$J$30="",0,COUNTIFS(Itinerary_Tags!$A:$A,$A12,Itinerary_Tags!$B:$B,Filter_Options!$J$30))+IF(Filter_Options!$K$30="",0,COUNTIFS(Itinerary_Tags!$A:$A,$A12,Itinerary_Tags!$B:$B,Filter_Options!$K$30)))>0)) | AF12: =IF($A12="","",--((IF(Filter_Options!$I$31="",0,COUNTIFS(Itinerary_Tags!$A:$A,$A12,Itinerary_Tags!$B:$B,Filter_Options!$I$31))+IF(Filter_Options!$J$31="",0,COUNTIFS(Itinerary_Tags!$A:$A,$A12,Itinerary_Tags!$B:$B,Filter_Options!$J$31))+IF(Filter_Options!$K$31="",0,COUNTIFS(Itinerary_Tags!$A:$A,$A12,Itinerary_Tags!$B:$B,Filter_Options!$K$31)))>0)) | AG12: =IF($A12="","",--((IF(Filter_Options!$I$32="",0,COUNTIFS(Itinerary_Tags!$A:$A,$A12,Itinerary_Tags!$B:$B,Filter_Options!$I$32))+IF(Filter_Options!$J$32="",0,COUNTIFS(Itinerary_Tags!$A:$A,$A12,Itinerary_Tags!$B:$B,Filter_Options!$J$32))+IF(Filter_Options!$K$32="",0,COUNTIFS(Itinerary_Tags!$A:$A,$A12,Itinerary_Tags!$B:$B,Filter_Options!$K$32)))>0)) | AH12: =IF($A12="","",--((IF(Filter_Options!$I$33="",0,COUNTIFS(Itinerary_Tags!$A:$A,$A12,Itinerary_Tags!$B:$B,Filter_Options!$I$33))+IF(Filter_Options!$J$33="",0,COUNTIFS(Itinerary_Tags!$A:$A,$A12,Itinerary_Tags!$B:$B,Filter_Options!$J$33))+IF(Filter_Options!$K$33="",0,COUNTIFS(Itinerary_Tags!$A:$A,$A12,Itinerary_Tags!$B:$B,Filter_Options!$K$33)))>0)) | AI12: =IF($A12="","",--((IF(Filter_Options!$I$34="",0,COUNTIFS(Itinerary_Tags!$A:$A,$A12,Itinerary_Tags!$B:$B,Filter_Options!$I$34))+IF(Filter_Options!$J$34="",0,COUNTIFS(Itinerary_Tags!$A:$A,$A12,Itinerary_Tags!$B:$B,Filter_Options!$J$34))+IF(Filter_Options!$K$34="",0,COUNTIFS(Itinerary_Tags!$A:$A,$A12,Itinerary_Tags!$B:$B,Filter_Options!$K$34)))>0)) | AJ12: =IF($A12="","",--((IF(Filter_Options!$I$35="",0,COUNTIFS(Itinerary_Tags!$A:$A,$A12,Itinerary_Tags!$B:$B,Filter_Options!$I$35))+IF(Filter_Options!$J$35="",0,COUNTIFS(Itinerary_Tags!$A:$A,$A12,Itinerary_Tags!$B:$B,Filter_Options!$J$35))+IF(Filter_Options!$K$35="",0,COUNTIFS(Itinerary_Tags!$A:$A,$A12,Itinerary_Tags!$B:$B,Filter_Options!$K$35)))>0)) | AK12: =IF($A12="","",--((IF(Filter_Options!$I$36="",0,COUNTIFS(Itinerary_Tags!$A:$A,$A12,Itinerary_Tags!$B:$B,Filter_Options!$I$36))+IF(Filter_Options!$J$36="",0,COUNTIFS(Itinerary_Tags!$A:$A,$A12,Itinerary_Tags!$B:$B,Filter_Options!$J$36))+IF(Filter_Options!$K$36="",0,COUNTIFS(Itinerary_Tags!$A:$A,$A12,Itinerary_Tags!$B:$B,Filter_Options!$K$36)))>0)) | AL12: =IF($A12="","",--((IF(Filter_Options!$I$37="",0,COUNTIFS(Itinerary_Tags!$A:$A,$A12,Itinerary_Tags!$B:$B,Filter_Options!$I$37))+IF(Filter_Options!$J$37="",0,COUNTIFS(Itinerary_Tags!$A:$A,$A12,Itinerary_Tags!$B:$B,Filter_Options!$J$37))+IF(Filter_Options!$K$37="",0,COUNTIFS(Itinerary_Tags!$A:$A,$A12,Itinerary_Tags!$B:$B,Filter_Options!$K$37)))>0))
A13: =IF(Itineraries!A13="","",Itineraries!A13) | B13: =IF(Itineraries!A13="","",Itineraries!C13) | C13: =IF($A13="","",--(Itineraries!$J13=Filter_Options!$F$2)) | D13: =IF($A13="","",--(Itineraries!$J13=Filter_Options!$F$3)) | E13: =IF($A13="","",--(Itineraries!$J13=Filter_Options!$F$4)) | F13: =IF($A13="","",--(Itineraries!$J13=Filter_Options!$F$5)) | G13: =IF($A13="","",--(Itineraries!$J13=Filter_Options!$F$6)) | H13: =IF($A13="","",--(Itineraries!$J13=Filter_Options!$F$7)) | I13: =IF($A13="","",--AND(Itineraries!$K13<=Filter_Options!$H$8,Itineraries!$L13>=Filter_Options!$G$8)) | J13: =IF($A13="","",--AND(Itineraries!$K13<=Filter_Options!$H$9,Itineraries!$L13>=Filter_Options!$G$9)) | K13: =IF($A13="","",--AND(Itineraries!$K13<=Filter_Options!$H$10,Itineraries!$L13>=Filter_Options!$G$10)) | L13: =IF($A13="","",--AND(Itineraries!$K13<=Filter_Options!$H$11,Itineraries!$L13>=Filter_Options!$G$11)) | M13: =IF($A13="","",--AND(Itineraries!$K13<=Filter_Options!$H$12,Itineraries!$L13>=Filter_Options!$G$12)) | N13: =IF($A13="","",--AND(Itineraries!$K13<=Filter_Options!$H$13,Itineraries!$L13>=Filter_Options!$G$13)) | O13: =IF($A13="","",--AND(Itineraries!$E13>=Filter_Options!$G$14,Itineraries!$E13<=Filter_Options!$H$14)) | P13: =IF($A13="","",--AND(Itineraries!$E13>=Filter_Options!$G$15,Itineraries!$E13<=Filter_Options!$H$15)) | Q13: =IF($A13="","",--AND(Itineraries!$E13>=Filter_Options!$G$16,Itineraries!$E13<=Filter_Options!$H$16)) | R13: =IF($A13="","",--AND(Itineraries!$E13>=Filter_Options!$G$17,Itineraries!$E13<=Filter_Options!$H$17)) | S13: =IF($A13="","",--AND(Itineraries!$E13>=Filter_Options!$G$18,Itineraries!$E13<=Filter_Options!$H$18)) | T13: =IF($A13="","",--AND(Itineraries!$E13>=Filter_Options!$G$19,Itineraries!$E13<=Filter_Options!$H$19)) | U13: =IF($A13="","",--((IF(Filter_Options!$I$20="",0,COUNTIFS(Itinerary_Tags!$A:$A,$A13,Itinerary_Tags!$B:$B,Filter_Options!$I$20))+IF(Filter_Options!$J$20="",0,COUNTIFS(Itinerary_Tags!$A:$A,$A13,Itinerary_Tags!$B:$B,Filter_Options!$J$20))+IF(Filter_Options!$K$20="",0,COUNTIFS(Itinerary_Tags!$A:$A,$A13,Itinerary_Tags!$B:$B,Filter_Options!$K$20)))>0)) | V13: =IF($A13="","",--((IF(Filter_Options!$I$21="",0,COUNTIFS(Itinerary_Tags!$A:$A,$A13,Itinerary_Tags!$B:$B,Filter_Options!$I$21))+IF(Filter_Options!$J$21="",0,COUNTIFS(Itinerary_Tags!$A:$A,$A13,Itinerary_Tags!$B:$B,Filter_Options!$J$21))+IF(Filter_Options!$K$21="",0,COUNTIFS(Itinerary_Tags!$A:$A,$A13,Itinerary_Tags!$B:$B,Filter_Options!$K$21)))>0)) | W13: =IF($A13="","",--((IF(Filter_Options!$I$22="",0,COUNTIFS(Itinerary_Tags!$A:$A,$A13,Itinerary_Tags!$B:$B,Filter_Options!$I$22))+IF(Filter_Options!$J$22="",0,COUNTIFS(Itinerary_Tags!$A:$A,$A13,Itinerary_Tags!$B:$B,Filter_Options!$J$22))+IF(Filter_Options!$K$22="",0,COUNTIFS(Itinerary_Tags!$A:$A,$A13,Itinerary_Tags!$B:$B,Filter_Options!$K$22)))>0)) | X13: =IF($A13="","",--((IF(Filter_Options!$I$23="",0,COUNTIFS(Itinerary_Tags!$A:$A,$A13,Itinerary_Tags!$B:$B,Filter_Options!$I$23))+IF(Filter_Options!$J$23="",0,COUNTIFS(Itinerary_Tags!$A:$A,$A13,Itinerary_Tags!$B:$B,Filter_Options!$J$23))+IF(Filter_Options!$K$23="",0,COUNTIFS(Itinerary_Tags!$A:$A,$A13,Itinerary_Tags!$B:$B,Filter_Options!$K$23)))>0)) | Y13: =IF($A13="","",--((IF(Filter_Options!$I$24="",0,COUNTIFS(Itinerary_Tags!$A:$A,$A13,Itinerary_Tags!$B:$B,Filter_Options!$I$24))+IF(Filter_Options!$J$24="",0,COUNTIFS(Itinerary_Tags!$A:$A,$A13,Itinerary_Tags!$B:$B,Filter_Options!$J$24))+IF(Filter_Options!$K$24="",0,COUNTIFS(Itinerary_Tags!$A:$A,$A13,Itinerary_Tags!$B:$B,Filter_Options!$K$24)))>0)) | Z13: =IF($A13="","",--((IF(Filter_Options!$I$25="",0,COUNTIFS(Itinerary_Tags!$A:$A,$A13,Itinerary_Tags!$B:$B,Filter_Options!$I$25))+IF(Filter_Options!$J$25="",0,COUNTIFS(Itinerary_Tags!$A:$A,$A13,Itinerary_Tags!$B:$B,Filter_Options!$J$25))+IF(Filter_Options!$K$25="",0,COUNTIFS(Itinerary_Tags!$A:$A,$A13,Itinerary_Tags!$B:$B,Filter_Options!$K$25)))>0)) | AA13: =IF($A13="","",--((IF(Filter_Options!$I$26="",0,COUNTIFS(Itinerary_Tags!$A:$A,$A13,Itinerary_Tags!$B:$B,Filter_Options!$I$26))+IF(Filter_Options!$J$26="",0,COUNTIFS(Itinerary_Tags!$A:$A,$A13,Itinerary_Tags!$B:$B,Filter_Options!$J$26))+IF(Filter_Options!$K$26="",0,COUNTIFS(Itinerary_Tags!$A:$A,$A13,Itinerary_Tags!$B:$B,Filter_Options!$K$26)))>0)) | AB13: =IF($A13="","",--((IF(Filter_Options!$I$27="",0,COUNTIFS(Itinerary_Tags!$A:$A,$A13,Itinerary_Tags!$B:$B,Filter_Options!$I$27))+IF(Filter_Options!$J$27="",0,COUNTIFS(Itinerary_Tags!$A:$A,$A13,Itinerary_Tags!$B:$B,Filter_Options!$J$27))+IF(Filter_Options!$K$27="",0,COUNTIFS(Itinerary_Tags!$A:$A,$A13,Itinerary_Tags!$B:$B,Filter_Options!$K$27)))>0)) | AC13: =IF($A13="","",--((IF(Filter_Options!$I$28="",0,COUNTIFS(Itinerary_Tags!$A:$A,$A13,Itinerary_Tags!$B:$B,Filter_Options!$I$28))+IF(Filter_Options!$J$28="",0,COUNTIFS(Itinerary_Tags!$A:$A,$A13,Itinerary_Tags!$B:$B,Filter_Options!$J$28))+IF(Filter_Options!$K$28="",0,COUNTIFS(Itinerary_Tags!$A:$A,$A13,Itinerary_Tags!$B:$B,Filter_Options!$K$28)))>0)) | AD13: =IF($A13="","",--((IF(Filter_Options!$I$29="",0,COUNTIFS(Itinerary_Tags!$A:$A,$A13,Itinerary_Tags!$B:$B,Filter_Options!$I$29))+IF(Filter_Options!$J$29="",0,COUNTIFS(Itinerary_Tags!$A:$A,$A13,Itinerary_Tags!$B:$B,Filter_Options!$J$29))+IF(Filter_Options!$K$29="",0,COUNTIFS(Itinerary_Tags!$A:$A,$A13,Itinerary_Tags!$B:$B,Filter_Options!$K$29)))>0)) | AE13: =IF($A13="","",--((IF(Filter_Options!$I$30="",0,COUNTIFS(Itinerary_Tags!$A:$A,$A13,Itinerary_Tags!$B:$B,Filter_Options!$I$30))+IF(Filter_Options!$J$30="",0,COUNTIFS(Itinerary_Tags!$A:$A,$A13,Itinerary_Tags!$B:$B,Filter_Options!$J$30))+IF(Filter_Options!$K$30="",0,COUNTIFS(Itinerary_Tags!$A:$A,$A13,Itinerary_Tags!$B:$B,Filter_Options!$K$30)))>0)) | AF13: =IF($A13="","",--((IF(Filter_Options!$I$31="",0,COUNTIFS(Itinerary_Tags!$A:$A,$A13,Itinerary_Tags!$B:$B,Filter_Options!$I$31))+IF(Filter_Options!$J$31="",0,COUNTIFS(Itinerary_Tags!$A:$A,$A13,Itinerary_Tags!$B:$B,Filter_Options!$J$31))+IF(Filter_Options!$K$31="",0,COUNTIFS(Itinerary_Tags!$A:$A,$A13,Itinerary_Tags!$B:$B,Filter_Options!$K$31)))>0)) | AG13: =IF($A13="","",--((IF(Filter_Options!$I$32="",0,COUNTIFS(Itinerary_Tags!$A:$A,$A13,Itinerary_Tags!$B:$B,Filter_Options!$I$32))+IF(Filter_Options!$J$32="",0,COUNTIFS(Itinerary_Tags!$A:$A,$A13,Itinerary_Tags!$B:$B,Filter_Options!$J$32))+IF(Filter_Options!$K$32="",0,COUNTIFS(Itinerary_Tags!$A:$A,$A13,Itinerary_Tags!$B:$B,Filter_Options!$K$32)))>0)) | AH13: =IF($A13="","",--((IF(Filter_Options!$I$33="",0,COUNTIFS(Itinerary_Tags!$A:$A,$A13,Itinerary_Tags!$B:$B,Filter_Options!$I$33))+IF(Filter_Options!$J$33="",0,COUNTIFS(Itinerary_Tags!$A:$A,$A13,Itinerary_Tags!$B:$B,Filter_Options!$J$33))+IF(Filter_Options!$K$33="",0,COUNTIFS(Itinerary_Tags!$A:$A,$A13,Itinerary_Tags!$B:$B,Filter_Options!$K$33)))>0)) | AI13: =IF($A13="","",--((IF(Filter_Options!$I$34="",0,COUNTIFS(Itinerary_Tags!$A:$A,$A13,Itinerary_Tags!$B:$B,Filter_Options!$I$34))+IF(Filter_Options!$J$34="",0,COUNTIFS(Itinerary_Tags!$A:$A,$A13,Itinerary_Tags!$B:$B,Filter_Options!$J$34))+IF(Filter_Options!$K$34="",0,COUNTIFS(Itinerary_Tags!$A:$A,$A13,Itinerary_Tags!$B:$B,Filter_Options!$K$34)))>0)) | AJ13: =IF($A13="","",--((IF(Filter_Options!$I$35="",0,COUNTIFS(Itinerary_Tags!$A:$A,$A13,Itinerary_Tags!$B:$B,Filter_Options!$I$35))+IF(Filter_Options!$J$35="",0,COUNTIFS(Itinerary_Tags!$A:$A,$A13,Itinerary_Tags!$B:$B,Filter_Options!$J$35))+IF(Filter_Options!$K$35="",0,COUNTIFS(Itinerary_Tags!$A:$A,$A13,Itinerary_Tags!$B:$B,Filter_Options!$K$35)))>0)) | AK13: =IF($A13="","",--((IF(Filter_Options!$I$36="",0,COUNTIFS(Itinerary_Tags!$A:$A,$A13,Itinerary_Tags!$B:$B,Filter_Options!$I$36))+IF(Filter_Options!$J$36="",0,COUNTIFS(Itinerary_Tags!$A:$A,$A13,Itinerary_Tags!$B:$B,Filter_Options!$J$36))+IF(Filter_Options!$K$36="",0,COUNTIFS(Itinerary_Tags!$A:$A,$A13,Itinerary_Tags!$B:$B,Filter_Options!$K$36)))>0)) | AL13: =IF($A13="","",--((IF(Filter_Options!$I$37="",0,COUNTIFS(Itinerary_Tags!$A:$A,$A13,Itinerary_Tags!$B:$B,Filter_Options!$I$37))+IF(Filter_Options!$J$37="",0,COUNTIFS(Itinerary_Tags!$A:$A,$A13,Itinerary_Tags!$B:$B,Filter_Options!$J$37))+IF(Filter_Options!$K$37="",0,COUNTIFS(Itinerary_Tags!$A:$A,$A13,Itinerary_Tags!$B:$B,Filter_Options!$K$37)))>0))
... A60: =IF(Itineraries!A60="","",Itineraries!A60) | B60: =IF(Itineraries!A60="","",Itineraries!C60) | C60: =IF($A60="","",--(Itineraries!$J60=Filter_Options!$F$2)) | D60: =IF($A60="","",--(Itineraries!$J60=Filter_Options!$F$3)) | E60: =IF($A60="","",--(Itineraries!$J60=Filter_Options!$F$4)) | F60: =IF($A60="","",--(Itineraries!$J60=Filter_Options!$F$5)) | G60: =IF($A60="","",--(Itineraries!$J60=Filter_Options!$F$6)) | H60: =IF($A60="","",--(Itineraries!$J60=Filter_Options!$F$7)) | I60: =IF($A60="","",--AND(Itineraries!$K60<=Filter_Options!$H$8,Itineraries!$L60>=Filter_Options!$G$8)) | J60: =IF($A60="","",--AND(Itineraries!$K60<=Filter_Options!$H$9,Itineraries!$L60>=Filter_Options!$G$9)) | K60: =IF($A60="","",--AND(Itineraries!$K60<=Filter_Options!$H$10,Itineraries!$L60>=Filter_Options!$G$10)) | L60: =IF($A60="","",--AND(Itineraries!$K60<=Filter_Options!$H$11,Itineraries!$L60>=Filter_Options!$G$11)) | M60: =IF($A60="","",--AND(Itineraries!$K60<=Filter_Options!$H$12,Itineraries!$L60>=Filter_Options!$G$12)) | N60: =IF($A60="","",--AND(Itineraries!$K60<=Filter_Options!$H$13,Itineraries!$L60>=Filter_Options!$G$13)) | O60: =IF($A60="","",--AND(Itineraries!$E60>=Filter_Options!$G$14,Itineraries!$E60<=Filter_Options!$H$14)) | P60: =IF($A60="","",--AND(Itineraries!$E60>=Filter_Options!$G$15,Itineraries!$E60<=Filter_Options!$H$15)) | Q60: =IF($A60="","",--AND(Itineraries!$E60>=Filter_Options!$G$16,Itineraries!$E60<=Filter_Options!$H$16)) | R60: =IF($A60="","",--AND(Itineraries!$E60>=Filter_Options!$G$17,Itineraries!$E60<=Filter_Options!$H$17)) | S60: =IF($A60="","",--AND(Itineraries!$E60>=Filter_Options!$G$18,Itineraries!$E60<=Filter_Options!$H$18)) | T60: =IF($A60="","",--AND(Itineraries!$E60>=Filter_Options!$G$19,Itineraries!$E60<=Filter_Options!$H$19)) | U60: =IF($A60="","",--((IF(Filter_Options!$I$20="",0,COUNTIFS(Itinerary_Tags!$A:$A,$A60,Itinerary_Tags!$B:$B,Filter_Options!$I$20))+IF(Filter_Options!$J$20="",0,COUNTIFS(Itinerary_Tags!$A:$A,$A60,Itinerary_Tags!$B:$B,Filter_Options!$J$20))+IF(Filter_Options!$K$20="",0,COUNTIFS(Itinerary_Tags!$A:$A,$A60,Itinerary_Tags!$B:$B,Filter_Options!$K$20)))>0)) | V60: =IF($A60="","",--((IF(Filter_Options!$I$21="",0,COUNTIFS(Itinerary_Tags!$A:$A,$A60,Itinerary_Tags!$B:$B,Filter_Options!$I$21))+IF(Filter_Options!$J$21="",0,COUNTIFS(Itinerary_Tags!$A:$A,$A60,Itinerary_Tags!$B:$B,Filter_Options!$J$21))+IF(Filter_Options!$K$21="",0,COUNTIFS(Itinerary_Tags!$A:$A,$A60,Itinerary_Tags!$B:$B,Filter_Options!$K$21)))>0)) | W60: =IF($A60="","",--((IF(Filter_Options!$I$22="",0,COUNTIFS(Itinerary_Tags!$A:$A,$A60,Itinerary_Tags!$B:$B,Filter_Options!$I$22))+IF(Filter_Options!$J$22="",0,COUNTIFS(Itinerary_Tags!$A:$A,$A60,Itinerary_Tags!$B:$B,Filter_Options!$J$22))+IF(Filter_Options!$K$22="",0,COUNTIFS(Itinerary_Tags!$A:$A,$A60,Itinerary_Tags!$B:$B,Filter_Options!$K$22)))>0)) | X60: =IF($A60="","",--((IF(Filter_Options!$I$23="",0,COUNTIFS(Itinerary_Tags!$A:$A,$A60,Itinerary_Tags!$B:$B,Filter_Options!$I$23))+IF(Filter_Options!$J$23="",0,COUNTIFS(Itinerary_Tags!$A:$A,$A60,Itinerary_Tags!$B:$B,Filter_Options!$J$23))+IF(Filter_Options!$K$23="",0,COUNTIFS(Itinerary_Tags!$A:$A,$A60,Itinerary_Tags!$B:$B,Filter_Options!$K$23)))>0)) | Y60: =IF($A60="","",--((IF(Filter_Options!$I$24="",0,COUNTIFS(Itinerary_Tags!$A:$A,$A60,Itinerary_Tags!$B:$B,Filter_Options!$I$24))+IF(Filter_Options!$J$24="",0,COUNTIFS(Itinerary_Tags!$A:$A,$A60,Itinerary_Tags!$B:$B,Filter_Options!$J$24))+IF(Filter_Options!$K$24="",0,COUNTIFS(Itinerary_Tags!$A:$A,$A60,Itinerary_Tags!$B:$B,Filter_Options!$K$24)))>0)) | Z60: =IF($A60="","",--((IF(Filter_Options!$I$25="",0,COUNTIFS(Itinerary_Tags!$A:$A,$A60,Itinerary_Tags!$B:$B,Filter_Options!$I$25))+IF(Filter_Options!$J$25="",0,COUNTIFS(Itinerary_Tags!$A:$A,$A60,Itinerary_Tags!$B:$B,Filter_Options!$J$25))+IF(Filter_Options!$K$25="",0,COUNTIFS(Itinerary_Tags!$A:$A,$A60,Itinerary_Tags!$B:$B,Filter_Options!$K$25)))>0)) | AA60: =IF($A60="","",--((IF(Filter_Options!$I$26="",0,COUNTIFS(Itinerary_Tags!$A:$A,$A60,Itinerary_Tags!$B:$B,Filter_Options!$I$26))+IF(Filter_Options!$J$26="",0,COUNTIFS(Itinerary_Tags!$A:$A,$A60,Itinerary_Tags!$B:$B,Filter_Options!$J$26))+IF(Filter_Options!$K$26="",0,COUNTIFS(Itinerary_Tags!$A:$A,$A60,Itinerary_Tags!$B:$B,Filter_Options!$K$26)))>0)) | AB60: =IF($A60="","",--((IF(Filter_Options!$I$27="",0,COUNTIFS(Itinerary_Tags!$A:$A,$A60,Itinerary_Tags!$B:$B,Filter_Options!$I$27))+IF(Filter_Options!$J$27="",0,COUNTIFS(Itinerary_Tags!$A:$A,$A60,Itinerary_Tags!$B:$B,Filter_Options!$J$27))+IF(Filter_Options!$K$27="",0,COUNTIFS(Itinerary_Tags!$A:$A,$A60,Itinerary_Tags!$B:$B,Filter_Options!$K$27)))>0)) | AC60: =IF($A60="","",--((IF(Filter_Options!$I$28="",0,COUNTIFS(Itinerary_Tags!$A:$A,$A60,Itinerary_Tags!$B:$B,Filter_Options!$I$28))+IF(Filter_Options!$J$28="",0,COUNTIFS(Itinerary_Tags!$A:$A,$A60,Itinerary_Tags!$B:$B,Filter_Options!$J$28))+IF(Filter_Options!$K$28="",0,COUNTIFS(Itinerary_Tags!$A:$A,$A60,Itinerary_Tags!$B:$B,Filter_Options!$K$28)))>0)) | AD60: =IF($A60="","",--((IF(Filter_Options!$I$29="",0,COUNTIFS(Itinerary_Tags!$A:$A,$A60,Itinerary_Tags!$B:$B,Filter_Options!$I$29))+IF(Filter_Options!$J$29="",0,COUNTIFS(Itinerary_Tags!$A:$A,$A60,Itinerary_Tags!$B:$B,Filter_Options!$J$29))+IF(Filter_Options!$K$29="",0,COUNTIFS(Itinerary_Tags!$A:$A,$A60,Itinerary_Tags!$B:$B,Filter_Options!$K$29)))>0)) | AE60: =IF($A60="","",--((IF(Filter_Options!$I$30="",0,COUNTIFS(Itinerary_Tags!$A:$A,$A60,Itinerary_Tags!$B:$B,Filter_Options!$I$30))+IF(Filter_Options!$J$30="",0,COUNTIFS(Itinerary_Tags!$A:$A,$A60,Itinerary_Tags!$B:$B,Filter_Options!$J$30))+IF(Filter_Options!$K$30="",0,COUNTIFS(Itinerary_Tags!$A:$A,$A60,Itinerary_Tags!$B:$B,Filter_Options!$K$30)))>0)) | AF60: =IF($A60="","",--((IF(Filter_Options!$I$31="",0,COUNTIFS(Itinerary_Tags!$A:$A,$A60,Itinerary_Tags!$B:$B,Filter_Options!$I$31))+IF(Filter_Options!$J$31="",0,COUNTIFS(Itinerary_Tags!$A:$A,$A60,Itinerary_Tags!$B:$B,Filter_Options!$J$31))+IF(Filter_Options!$K$31="",0,COUNTIFS(Itinerary_Tags!$A:$A,$A60,Itinerary_Tags!$B:$B,Filter_Options!$K$31)))>0)) | AG60: =IF($A60="","",--((IF(Filter_Options!$I$32="",0,COUNTIFS(Itinerary_Tags!$A:$A,$A60,Itinerary_Tags!$B:$B,Filter_Options!$I$32))+IF(Filter_Options!$J$32="",0,COUNTIFS(Itinerary_Tags!$A:$A,$A60,Itinerary_Tags!$B:$B,Filter_Options!$J$32))+IF(Filter_Options!$K$32="",0,COUNTIFS(Itinerary_Tags!$A:$A,$A60,Itinerary_Tags!$B:$B,Filter_Options!$K$32)))>0)) | AH60: =IF($A60="","",--((IF(Filter_Options!$I$33="",0,COUNTIFS(Itinerary_Tags!$A:$A,$A60,Itinerary_Tags!$B:$B,Filter_Options!$I$33))+IF(Filter_Options!$J$33="",0,COUNTIFS(Itinerary_Tags!$A:$A,$A60,Itinerary_Tags!$B:$B,Filter_Options!$J$33))+IF(Filter_Options!$K$33="",0,COUNTIFS(Itinerary_Tags!$A:$A,$A60,Itinerary_Tags!$B:$B,Filter_Options!$K$33)))>0)) | AI60: =IF($A60="","",--((IF(Filter_Options!$I$34="",0,COUNTIFS(Itinerary_Tags!$A:$A,$A60,Itinerary_Tags!$B:$B,Filter_Options!$I$34))+IF(Filter_Options!$J$34="",0,COUNTIFS(Itinerary_Tags!$A:$A,$A60,Itinerary_Tags!$B:$B,Filter_Options!$J$34))+IF(Filter_Options!$K$34="",0,COUNTIFS(Itinerary_Tags!$A:$A,$A60,Itinerary_Tags!$B:$B,Filter_Options!$K$34)))>0)) | AJ60: =IF($A60="","",--((IF(Filter_Options!$I$35="",0,COUNTIFS(Itinerary_Tags!$A:$A,$A60,Itinerary_Tags!$B:$B,Filter_Options!$I$35))+IF(Filter_Options!$J$35="",0,COUNTIFS(Itinerary_Tags!$A:$A,$A60,Itinerary_Tags!$B:$B,Filter_Options!$J$35))+IF(Filter_Options!$K$35="",0,COUNTIFS(Itinerary_Tags!$A:$A,$A60,Itinerary_Tags!$B:$B,Filter_Options!$K$35)))>0)) | AK60: =IF($A60="","",--((IF(Filter_Options!$I$36="",0,COUNTIFS(Itinerary_Tags!$A:$A,$A60,Itinerary_Tags!$B:$B,Filter_Options!$I$36))+IF(Filter_Options!$J$36="",0,COUNTIFS(Itinerary_Tags!$A:$A,$A60,Itinerary_Tags!$B:$B,Filter_Options!$J$36))+IF(Filter_Options!$K$36="",0,COUNTIFS(Itinerary_Tags!$A:$A,$A60,Itinerary_Tags!$B:$B,Filter_Options!$K$36)))>0)) | AL60: =IF($A60="","",--((IF(Filter_Options!$I$37="",0,COUNTIFS(Itinerary_Tags!$A:$A,$A60,Itinerary_Tags!$B:$B,Filter_Options!$I$37))+IF(Filter_Options!$J$37="",0,COUNTIFS(Itinerary_Tags!$A:$A,$A60,Itinerary_Tags!$B:$B,Filter_Options!$J$37))+IF(Filter_Options!$K$37="",0,COUNTIFS(Itinerary_Tags!$A:$A,$A60,Itinerary_Tags!$B:$B,Filter_Options!$K$37)))>0))

Sheet Itineraries
A1: itinerary_id | B1: slug | C1: title | D1: destination | E1: duration_days | F1: description | G1: cover_image | H1: is_premium | I1: price | J1: direction | K1: budget_min | L1: budget_max | M1: currency | N1: days_entered | O1: days_check | P1: stops_total | Q1: tags_total
A2: Delhi-Jodhpur-Jaisalmer-Bikaner-6n7d | B2: Delhi-Bikaner-Jaisalmer-Jodhpur-6n7d | C2: Delhi–Bikaner–Jaisalmer–Jodhpur 6N/7D | D2: Rajasthan | E2: 7 | F2: Explore Jodhpur's blue lanes, Jaisalmer's golden fort and the Thar Desert, followed by Bikaner's royal forts and historic havelis. | G2: /images/Itinerary/jodhpur.jpg | H2: =FALSE() | I2: 0 | J2: west | K2: 6000 | L2: 12000 | M2: INR | N2: 7 | O2: OK | P2: 33 | Q2: 13
A3: Jaisalmer-Winter-4n5d | B3: Jaisalmer-Winter-4n5d | C3: Jaisalmer Winter 4N/5D | D3: Jaisalmer, Rajasthan | E3: 5 | F3: A winter escape through Jaisalmer's golden fort, historic havelis, desert villages, Sam Sand Dunes and peaceful desert sunsets. | G3: /images/Itinerary/jaisalmer.jpg | H3: =FALSE() | I3: 0 | J3: west | K3: 5000 | L3: 12000 | M3: INR | N3: 5 | O3: OK | P3: 22 | Q3: 14
A4: kashmir-autumn | B4: kashmir-autumn | C4: Kashmir in Autumn | D4: Kashmir | E4: 5 | F4: A scenic Kashmir journey focused on autumn chinar trees, Dal Lake, Srinagar's old neighbourhoods and the dramatic mountain route towards Kargil. | G4: /images/Itinerary/kashmirs.jpg | H4: =FALSE() | I4: 49 | J4: north | K4: 8000 | L4: 18000 | M4: INR | N4: 5 | O4: OK | P4: 20 | Q4: 13
A5: delhi-zanskar-4-days | B5: delhi-zanskar-4-days | C5: Delhi to Zanskar — 3N/4D Road Trip Under 10K | D5: Zanskar, Ladakh | E5: 4 | F5: A demanding high-altitude road trip concept via Manali, Sissu, Jispa and the mountain routes towards Zanskar. Verify route access and realistic travel times before booking. | G5: /images/Itinerary/zanskars.jpg | H5: =FALSE() | I5: 99 | J5: north | K5: 7000 | L5: 15000 | M5: INR | N5: 4 | O5: OK | P5: 15 | Q5: 13
A6: udaipur-weekend-plan | B6: udaipur-weekend | C6: Udaipur — 3 Day Weekend Itinerary | D6: Udaipur, Rajasthan | E6: 3 | F6: A relaxed Udaipur escape covering lakeside walks, historic palaces, local food, hilltop viewpoints and the city's colourful old streets. | G6: /images/Itinerary/udaipur.jpg | H6: =FALSE() | I6: 0 | J6: west | K6: 4000 | L6: 9000 | M6: INR | N6: 3 | O6: OK | P6: 11 | Q6: 13
A7: spiti-valley-10-days | B7: spiti-valley-10-days | C7: Spiti Valley — 10 Day Complete Itinerary | D7: Spiti Valley, Himachal Pradesh | E7: 10 | F7: A mountain journey through Kinnaur and Spiti, covering remote villages, monasteries, high-altitude landscapes and the route towards Chandratal and Manali. | G7: /images/Itinerary/spitis.jpg | H7: =FALSE() | I7: 0 | J7: north | K7: 12000 | L7: 25000 | M7: INR | N7: 10 | O7: OK | P7: 33 | Q7: 15
A8: kerala-7-days | B8: kerala-7-days | C8: Kerala — 7 Day Complete Itinerary | D8: Kerala | E8: 7 | F8: A relaxed Kerala journey combining Kochi's heritage streets, Alleppey's backwaters, village life, coastal scenery and the green landscapes around Munnar. | G8: /images/Itinerary/kerla.jpg | H8: =FALSE() | I8: 29 | J8: south | K8: 7000 | L8: 15000 | M8: INR | N8: 7 | O8: OK | P8: 22 | Q8: 15
A9: delhi-kalpa-4-days | B9: delhi-kalpa-4-days | C9: Delhi to Kalpa — 3N/4D Road Trip | D9: Kalpa, Himachal Pradesh | E9: 4 | F9: A short but demanding mountain journey from Delhi to Kalpa through Shimla and Kinnaur, with village walks, mountain views and local Himachali food. | G9: /images/Itinerary/kalpa.jpg | H9: =FALSE() | I9: 39 | J9: north | K9: 5000 | L9: 11000 | M9: INR | N9: 4 | O9: OK | P9: 15 | Q9: 15
A10: udaipur-chittorgarh-kumbhalgarh-4-days | B10: udaipur-chittorgarh-kumbhalgarh-4-days | C10: Skip Jaipur: Udaipur, Chittorgarh and Kumbhalgarh — 3N/4D | D10: Udaipur, Rajasthan | E10: 4 | F10: A long-weekend Rajasthan itinerary featuring Udaipur's lakes and palaces, Kumbhalgarh's mountain fort and the monumental history of Chittorgarh. | G10: /images/Itinerary/chittaurgarh.jpg | H10: =FALSE() | I10: 0 | J10: west | K10: 5000 | L10: 11000 | M10: INR | N10: 4 | O10: OK | P10: 19 | Q10: 13
A11: madurai-kanyakumari-rameshwaram-7-days | B11: madurai-kanyakumari-rameshwaram-7-days | C11: Madurai, Rameswaram and Kanyakumari — 7 Days | D11: Madurai, Rameswaram and Kanyakumari, Tamil Nadu | E11: 7 | F11: Explore Madurai's temple heritage, Rameswaram's sacred coastline, the Pamban region and Kanyakumari's dramatic meeting of the seas on a week-long Tamil Nadu journey. | G11: /images/Itinerary/rameshwaram.jpg | H11: =FALSE() | I11: 29 | J11: south | K11: 7000 | L11: 15000 | M11: INR | N11: 7 | O11: OK | P11: 22 | Q11: 12
A12: guwahati-shillong-dawki-7-days | B12: guwahati-shillong-dawki-7-days | C12: Guwahati, Shillong and Dawki — 7 Days | D12: Guwahati, Assam and Meghalaya | E12: 7 | F12: A Northeast India journey through Guwahati, Shillong's hill scenery, waterfalls, local markets and the clear river landscapes around Dawki and the India–Bangladesh border. | G12: /images/Itinerary/shilong.jpg | H12: =FALSE() | I12: 99 | J12: northeast | K12: 8000 | L12: 18000 | M12: INR | N12: 7 | O12: OK | P12: 20 | Q12: 17
A13: gangtok-darjeeling-yumthang-7-days | B13: gangtok-darjeeling-yumthang-7-days | C13: Gangtok, Darjeeling and Yumthang Valley — 7 Days | D13: Sikkim and Darjeeling, Northeast India | E13: 7 | F13: A mountain itinerary connecting Gangtok, Darjeeling and the Yumthang Valley, with Himalayan viewpoints, tea gardens, monasteries and scenic road journeys. | G13: /images/Itinerary/gangtok.jpg | H13: =FALSE() | I13: 99 | J13: northeast | K13: 10000 | L13: 22000 | M13: INR | N13: 7 | O13: OK | P13: 18 | Q13: 15
... A30: garba-dandiya-raas | B30: garba-dandiya-raas | C30: Garba & Dandiya Raas Experience | D30: Ahmedabad, Gujarat | E30: 5 | F30: Experience Gujarat’s vibrant folk culture through Garba, a traditional circle dance, and Dandiya Raas, performed with decorated sticks. Discover the music, colourful traditional attire and festive atmosphere. | G30: /images/Itinerary/dandiya-night.jpg | H30: =FALSE() | I30: 22 | J30: west | K30: 5000 | L30: 10000 | M30: INR | N30: 5 | O30: OK | P30: 5 | Q30: 1

Sheet Themes
A1: itinerary_id | B1: primary | C1: secondary | D1: background | E1: surface | F1: accent | G1: text | H1: muted | I1: border | J1: buttonText
A2: Delhi-Jodhpur-Jaisalmer-Bikaner-6n7d | B2: #285A83 | C2: #D8E7F0 | D2: #F8F4ED | E2: #FFFFFF | F2: #C9794B | G2: #263747 | H2: #77736C | I2: #D7E0E5 | J2: #FFFFFF
A3: Jaisalmer-Winter-4n5d | B3: #C58B2A | C3: #F4E3BD | D3: #FBF6EB | E3: #FFFFFF | F3: #E8B85D | G3: #49351F | H3: #87745B | I3: #E6D3AE | J3: #FFFFFF
A4: kashmir-autumn | B4: #A64B32 | C4: #F0D9C4 | D4: #FBF5ED | E4: #FFFFFF | F4: #C98A45 | G4: #49372F | H4: #88766B | I4: #E6D4C4 | J4: #FFFFFF
A5: delhi-zanskar-4-days | B5: #526777 | C5: #DCE5E9 | D5: #F5F7F8 | E5: #FFFFFF | F5: #C98E56 | G5: #293943 | H5: #78858D | I5: #D6E0E5 | J5: #FFFFFF
A6: udaipur-weekend-plan | B6: #356B78 | C6: #D9E8E8 | D6: #F7F6EF | E6: #FFFFFF | F6: #C59A50 | G6: #2C4247 | H6: #778589 | I6: #D6E1E1 | J6: #FFFFFF
A7: spiti-valley-10-days | B7: #526777 | C7: #DCE5E9 | D7: #F5F7F8 | E7: #FFFFFF | F7: #C98E56 | G7: #293943 | H7: #78858D | I7: #D6E0E5 | J7: #FFFFFF
A8: kerala-7-days | B8: #286653 | C8: #DDEBE2 | D8: #F5F8F1 | E8: #FFFFFF | F8: #D5A45B | G8: #263D32 | H8: #718278 | I8: #D3E1D6 | J8: #FFFFFF
A9: delhi-kalpa-4-days | B9: #526777 | C9: #DCE5E9 | D9: #F5F7F8 | E9: #FFFFFF | F9: #C98E56 | G9: #293943 | H9: #78858D | I9: #D6E0E5 | J9: #FFFFFF
A10: udaipur-chittorgarh-kumbhalgarh-4-days | B10: #356B78 | C10: #D9E8E8 | D10: #F7F6EF | E10: #FFFFFF | F10: #C59A50 | G10: #2C4247 | H10: #778589 | I10: #D6E1E1 | J10: #FFFFFF
A11: madurai-kanyakumari-rameshwaram-7-days | B11: #87452D | C11: #F3E2CC | D11: #FFF9F0 | E11: #FFFFFF | F11: #D7A84B | G11: #432D24 | H11: #89776A | I11: #E9D6C1 | J11: #FFFFFF
A12: guwahati-shillong-dawki-7-days | B12: #3D6858 | C12: #DCE9E2 | D12: #F4F7F4 | E12: #FFFFFF | F12: #83A9A0 | G12: #2B4037 | H12: #7B8982 | I12: #D5E1DA | J12: #FFFFFF
... A28: sangla-holi-5-days | B28: #6B7350 | C28: #E3DFC7 | D28: #F7F6EE | E28: #FFFFFF | F28: #C58A3A | G28: #30372B | H28: #777B69 | I28: #DFE0D2 | J28: #FFFFFF

Sheet Days
A1: itinerary_id | B1: day_number | C1: title | D1: description | E1: day_key
A2: Delhi-Jodhpur-Jaisalmer-Bikaner-6n7d | B2: 1 | C2: Delhi to Jodhpur | D2: Travel from Delhi to Jodhpur by train or overnight transport. After checking in, explore the Clock Tower, Sardar Market and the blue lanes of the old city. Try local Rajasthani food and enjoy the atmosphere around the historic centre. | E2: =A2&"|"&B2
A3: Delhi-Jodhpur-Jaisalmer-Bikaner-6n7d | B3: 2 | C3: Jodhpur — Mehrangarh Fort and Blue City | D3: Explore Mehrangarh Fort and its palaces, courtyards and panoramic city views. Continue to Jaswant Thada and explore the old blue neighbourhoods. In the evening, travel towards Jaisalmer if your train or bus schedule allows. | E3: =A3&"|"&B3
A4: Delhi-Jodhpur-Jaisalmer-Bikaner-6n7d | B4: 3 | C4: Jaisalmer — Golden Fort and Havelis | D4: Explore Jaisalmer Fort, its historic lanes and Jain temples. Visit Patwon Ki Haveli and discover the old city before spending the evening around Gadisar Lake. | E4: =A4&"|"&B4
A5: Delhi-Jodhpur-Jaisalmer-Bikaner-6n7d | B5: 4 | C5: Thar Desert — Sunset and Camping | D5: Spend the morning at a relaxed pace, then travel towards Sam Sand Dunes. Enjoy the desert landscape at sunset and consider a camel ride or jeep safari. Stay at a desert camp and experience local food and folk performances where available. | E5: =A5&"|"&B5
A6: Delhi-Jodhpur-Jaisalmer-Bikaner-6n7d | B6: 5 | C6: Kuldhara, Bada Bagh and Bikaner | D6: Enjoy the desert morning and return towards Jaisalmer. Visit Kuldhara and Bada Bagh if transport and opening hours permit. Later, travel to Bikaner by train or bus; check schedules before finalising the route. | E6: =A6&"|"&B6
A7: Delhi-Jodhpur-Jaisalmer-Bikaner-6n7d | B7: 6 | C7: Bikaner — Junagarh Fort and Old City | D7: Explore Junagarh Fort and its royal architecture. Continue to the historic Rampuria Havelis and the old city markets. Try Bikaner's famous local snacks and enjoy an evening in the city. | E7: =A7&"|"&B7
A8: Delhi-Jodhpur-Jaisalmer-Bikaner-6n7d | B8: 7 | C8: Bikaner to Delhi | D8: If time permits, visit Karni Mata Temple in Deshnok before returning to Bikaner. Collect local snacks, check out and take your return train to Delhi. | E8: =A8&"|"&B8
A9: Jaisalmer-Winter-4n5d | B9: 1 | C9: Golden City — Fort, Havelis and Lake | D9: Arrive in Jaisalmer, check in and explore the living fort, narrow lanes and Jain temples. Visit Patwon Ki Haveli and other historic havelis before spending the evening at Gadisar Lake. | E9: =A9&"|"&B9
A10: Jaisalmer-Winter-4n5d | B10: 2 | C10: Sam Sand Dunes — Desert Sunset | D10: Enjoy a relaxed morning in town before heading to Sam Sand Dunes. Experience the desert landscape around sunset and choose a camel ride or jeep safari if you wish. Stay at a desert camp and check which meals and cultural activities are included. | E10: =A10&"|"&B10
A11: Jaisalmer-Winter-4n5d | B11: 3 | C11: Desert Sunrise, Kuldhara and Khuri | D11: Watch the sunrise if weather permits, then return towards Jaisalmer. Explore Kuldhara and continue to Khuri for a quieter village and desert experience. Return to town in the evening. | E11: =A11&"|"&B11
A12: Jaisalmer-Winter-4n5d | B12: 4 | C12: Bada Bagh and Slow Jaisalmer | D12: Explore any missed lanes and local markets. Later, visit Bada Bagh and its royal cenotaphs, then return to the city for a relaxed evening overlooking the illuminated fort. | E12: =A12&"|"&B12
A13: Jaisalmer-Winter-4n5d | B13: 5 | C13: Local Breakfast and Departure | D13: Enjoy breakfast, take a final walk through the old city and pick up local snacks or handicrafts. Check out and begin your onward journey. | E13: =A13&"|"&B13
... A145: sangla-holi-5-days | B145: 5 | C145: A Slow Mountain Morning and Departure | D145: Enjoy breakfast with your homestay host, take a final village walk and begin your return journey. Allow extra time for mountain roads and confirm transport in advance. | E145: =A145&"|"&B145
A146: ziro-valley-folk-dance | B146: 1 | C146: Arrive in Ziro Valley | D146: Arrive, settle in and explore the surrounding village landscape. | E146: ziro-valley-folk-dance|1
A147: ziro-valley-folk-dance | B147: 2 | C147: Apatani Culture & Folk Traditions | D147: Learn about Apatani heritage and seek out locally hosted cultural performances. | E147: ziro-valley-folk-dance|2
A148: ziro-valley-folk-dance | B148: 3 | C148: Village Walk & Departure | D148: Explore local village life respectfully before departure. | E148: ziro-valley-folk-dance|3
A149: garba-dandiya-raas | B149: 1 | C149: Arrive in Ahmedabad | D149: Arrive in Ahmedabad, check in and explore the old city at a relaxed pace. Try Gujarati snacks and learn about the local culture. Confirm event dates and transport before planning festival activities. | E149: garba-dandiya-raas-day-1
A150: garba-dandiya-raas | B150: 2 | C150: Ahmedabad Heritage & Local Food | D150: Explore Ahmedabad’s historic neighbourhoods and architecture, then sample local Gujarati food. Keep the afternoon flexible and check current opening times for any attractions. | E150: garba-dandiya-raas-day-2
A151: garba-dandiya-raas | B151: 3 | C151: Garba & Dandiya Raas | D151: Experience Garba and Dandiya Raas at a scheduled Navratri event or cultural venue. Event access, dates and ticket requirements vary, so verify details before travelling. | E151: garba-dandiya-raas-day-3
A152: garba-dandiya-raas | B152: 4 | C152: Gujarati Culture & Markets | D152: Visit local markets for traditional clothing, handicrafts and regional snacks. Ask locally about cultural performances or community events happening during your visit. | E152: garba-dandiya-raas-day-4
A153: garba-dandiya-raas | B153: 5 | C153: Slow Morning & Departure | D153: Enjoy a relaxed breakfast, revisit a favourite neighbourhood or pick up local snacks, then depart from Ahmedabad according to your onward transport schedule. | E153: garba-dandiya-raas-day-5

Sheet Locations
A1: location_id | B1: name | C1: state (optional) | D1: latitude (optional) | E1: longitude (optional) | F1: times_used
A2: 1 | B2: New Delhi | F2: =COUNTIF(Day_Locations!$D:$D,A2)
A3: 2 | B3: Jodhpur | F3: =COUNTIF(Day_Locations!$D:$D,A3)
A4: 3 | B4: Clock Tower | F4: =COUNTIF(Day_Locations!$D:$D,A4)
A5: 4 | B5: Sardar Market | F5: =COUNTIF(Day_Locations!$D:$D,A5)
A6: 5 | B6: Blue City | F6: =COUNTIF(Day_Locations!$D:$D,A6)
A7: 6 | B7: Mehrangarh Fort | F7: =COUNTIF(Day_Locations!$D:$D,A7)
A8: 7 | B8: Jaswant Thada | F8: =COUNTIF(Day_Locations!$D:$D,A8)
A9: 8 | B9: Jodhpur Old City | F9: =COUNTIF(Day_Locations!$D:$D,A9)
A10: 9 | B10: Jaisalmer | F10: =COUNTIF(Day_Locations!$D:$D,A10)
A11: 10 | B11: Jaisalmer Fort | F11: =COUNTIF(Day_Locations!$D:$D,A11)
A12: 11 | B12: Jain Temples | F12: =COUNTIF(Day_Locations!$D:$D,A12)
A13: 12 | B13: Patwon Ki Haveli | F13: =COUNTIF(Day_Locations!$D:$D,A13)
... A244: 243 | B244: Hapoli | F244: =COUNTIF(Day_Locations!$D:$D,A244)
A245: 244 | B245: Ahmedabad | C245: Gujarat

Sheet Day_Locations
A1: itinerary_id | B1: day_number | C1: sort_order | D1: location_id | E1: location_name
A2: Delhi-Jodhpur-Jaisalmer-Bikaner-6n7d | B2: 1 | C2: 1 | D2: 1 | E2: New Delhi
A3: Delhi-Jodhpur-Jaisalmer-Bikaner-6n7d | B3: 1 | C3: 2 | D3: 2 | E3: Jodhpur
A4: Delhi-Jodhpur-Jaisalmer-Bikaner-6n7d | B4: 1 | C4: 3 | D4: 3 | E4: Clock Tower
A5: Delhi-Jodhpur-Jaisalmer-Bikaner-6n7d | B5: 1 | C5: 4 | D5: 4 | E5: Sardar Market
A6: Delhi-Jodhpur-Jaisalmer-Bikaner-6n7d | B6: 1 | C6: 5 | D6: 5 | E6: Blue City
A7: Delhi-Jodhpur-Jaisalmer-Bikaner-6n7d | B7: 2 | C7: 1 | D7: 6 | E7: Mehrangarh Fort
A8: Delhi-Jodhpur-Jaisalmer-Bikaner-6n7d | B8: 2 | C8: 2 | D8: 7 | E8: Jaswant Thada
A9: Delhi-Jodhpur-Jaisalmer-Bikaner-6n7d | B9: 2 | C9: 3 | D9: 5 | E9: Blue City
A10: Delhi-Jodhpur-Jaisalmer-Bikaner-6n7d | B10: 2 | C10: 4 | D10: 8 | E10: Jodhpur Old City
A11: Delhi-Jodhpur-Jaisalmer-Bikaner-6n7d | B11: 2 | C11: 5 | D11: 9 | E11: Jaisalmer
A12: Delhi-Jodhpur-Jaisalmer-Bikaner-6n7d | B12: 3 | C12: 1 | D12: 10 | E12: Jaisalmer Fort
A13: Delhi-Jodhpur-Jaisalmer-Bikaner-6n7d | B13: 3 | C13: 2 | D13: 11 | E13: Jain Temples
... A441: garba-dandiya-raas | B441: 5 | C441: 5 | D441: 244 | E441: Ahmedabad

Sheet Tags
A1: tag_id | B1: category | C1: value | D1: used_by_itineraries
A2: 1 | B2: occasion | C2: long-weekend | D2: 16
A3: 2 | B3: travel_style | C3: backpacker | D3: 26
A4: 3 | B4: travel_style | C4: culture | D4: 21
A5: 4 | B5: travel_style | C5: history | D5: 5
A6: 5 | B6: travel_style | C6: road-trip | D6: 8
A7: 6 | B7: culture | C7: heritage | D7: 24
A8: 7 | B8: culture | C8: local-food | D8: 16
A9: 8 | B9: culture | C9: folk-art | D9: 3
A10: 9 | B10: culture | C10: crafts | D10: 9
A11: 10 | B11: season | C11: winter | D11: 11
A12: 11 | B12: season | C12: pleasant | D12: 16
A13: 12 | B13: trip_type | C13: desert | D13: 2
... A60: 59 | B60: trip_type | C60: city-break | D60: 4

Sheet Itinerary_Tags
A1: itinerary_id | B1: tag_id | C1: category | D1: value | E1: itinerary_title
A2: Delhi-Jodhpur-Jaisalmer-Bikaner-6n7d | B2: 1 | C2: occasion | D2: long-weekend | E2: Delhi–Bikaner–Jaisalmer–Jodhpur 6N/7D
A3: Delhi-Jodhpur-Jaisalmer-Bikaner-6n7d | B3: 2 | C3: travel_style | D3: backpacker | E3: Delhi–Bikaner–Jaisalmer–Jodhpur 6N/7D
A4: Delhi-Jodhpur-Jaisalmer-Bikaner-6n7d | B4: 3 | C4: travel_style | D4: culture | E4: Delhi–Bikaner–Jaisalmer–Jodhpur 6N/7D
A5: Delhi-Jodhpur-Jaisalmer-Bikaner-6n7d | B5: 4 | C5: travel_style | D5: history | E5: Delhi–Bikaner–Jaisalmer–Jodhpur 6N/7D
A6: Delhi-Jodhpur-Jaisalmer-Bikaner-6n7d | B6: 5 | C6: travel_style | D6: road-trip | E6: Delhi–Bikaner–Jaisalmer–Jodhpur 6N/7D
A7: Delhi-Jodhpur-Jaisalmer-Bikaner-6n7d | B7: 6 | C7: culture | D7: heritage | E7: Delhi–Bikaner–Jaisalmer–Jodhpur 6N/7D
A8: Delhi-Jodhpur-Jaisalmer-Bikaner-6n7d | B8: 7 | C8: culture | D8: local-food | E8: Delhi–Bikaner–Jaisalmer–Jodhpur 6N/7D
A9: Delhi-Jodhpur-Jaisalmer-Bikaner-6n7d | B9: 9 | C9: culture | D9: crafts | E9: Delhi–Bikaner–Jaisalmer–Jodhpur 6N/7D
A10: Delhi-Jodhpur-Jaisalmer-Bikaner-6n7d | B10: 10 | C10: season | D10: winter | E10: Delhi–Bikaner–Jaisalmer–Jodhpur 6N/7D
A11: Delhi-Jodhpur-Jaisalmer-Bikaner-6n7d | B11: 11 | C11: season | D11: pleasant | E11: Delhi–Bikaner–Jaisalmer–Jodhpur 6N/7D
A12: Delhi-Jodhpur-Jaisalmer-Bikaner-6n7d | B12: 12 | C12: trip_type | D12: desert | E12: Delhi–Bikaner–Jaisalmer–Jodhpur 6N/7D
A13: Delhi-Jodhpur-Jaisalmer-Bikaner-6n7d | B13: 13 | C13: trip_type | D13: forts | E13: Delhi–Bikaner–Jaisalmer–Jodhpur 6N/7D
... A376: garba-dandiya-raas | B376: 8 | C376: culture | D376: folk-art | E376: Garba & Dandiya Raas Experience
